Workbook

Sheet Claude Log
A1: Turn # | B1: Date | C1: User Request | D1: Action Taken | E1: Details | F1: Outcome
A2: 1 | B2: 46244 | C2: Provided full transcript from previous session (classifying HQ VAV/FCU tags as Included/Not Included in column D by room type across Ground Floor–Level 11). New session; selection at D1174. | D2: Loaded prior context; set up Claude Log sheet; inspected the registry section around D1174. | E2: Row 1170 = AHUB_0005; FCU numbering restarts at FCU0001 on row 1171 — this is a separate building/section where column D holds room descriptions (e.g. 'SPRINKLER AND WATER','B.M.S'), not Included/Not Included marks. AHUs (rows 4-28) still unmarked pending direction. | F2: Awaiting user direction on next step (new floor, AHU handling, or final excluded-room verification).
A3: 3 | B3: 46244 | C3: Clarified: wants room names (rooms served by each equipment tag) filled for the HQ block, rows 3–763, in column E (keeping the Included/Not Included marks in column D). | D3: Confirmed target column E via question; checked E is empty apart from a legend at E3/E4. Explained I cannot view the previous session's drawing images and my prior notes are not a clean per-row room map. | E3: Room names must be exact; prior notes grouped multiple tags per room label. Requested the floor drawings be resent one at a time to fill column E accurately, floor by floor. | F3: Awaiting user to resend the first HQ floor drawing to begin populating column E.
A4: 4 | B4: 46244 | C4: Said they will send the floor drawings later tonight. | D4: Acknowledged; no workbook changes made. Confirmed the floor-by-floor workflow to populate column E with room names once drawings arrive. | E4: No cells written to Controllable Asset Registry this turn. | F4: On hold — awaiting HQ floor drawings from user (expected tonight).
A5: 5 | B5: 46244 | C5: Sent HQ Roof Top (Level 12) drawing; asked me to start filling room names in column E for that floor. | D5: Wrote FCU room names to E155:E160 (FCU0126/0127 → 12.002 MCC Closet; FCU0128/0129 → 12.003 MCC Closet; FCU0130 → 12.004 MCC Closet; FCU0131 → roof plant/walkway near CSRR-0008). Verified by re-reading A155:E160. | E5: Roof VAV/12/01-13 units are NOT in the tag list (all VAV0001-0607 already assigned to Ground-L11; HQ block ends row 763, QNL starts 764). AHU/12/01-10 (rows 4-12) left blank — parked per earlier decision and AHUs don't serve a single room. | F5: Level 12 FCUs done. Flagged: SE 12.001 Electrical Closet sits beside 12.002 MCC Closet — could not confirm if one FCU serves 12.001 instead; FCU0131 has no room number on the drawing.
A6: 6 | B6: 46245 | C6: Sent the 3rd image pair — new: South Building L0 Section A1.3; old: North Building L0 Section A2.3. Asked me to continue the established workflow (map the new floor, extract standalone tags from the old floor). | D6: Filled 3 blank FCU rows (FCU6987 row 2118, SB FCU0001 row 2159, SB FCU2001 row 2168). Appended 33 new rows (2365-2397): 5 A1.3 South Building AT tags, 24 A2.3 North Building AT tags, 4 A2.3 standalone EV valves. Flagged 7 uncertain rows yellow in C:D. | E6: Duplicate avoidance: skipped AT-0006 (already row 2262 from B1.1) and all A2.3 numbers already embedded in existing VAV rows (5000/5002, 5001/5003, 5010/5011, 5015/5016, 5030/5031, 5040/5041, 5045/5046, 5395, 5400, 5405, 5410/5411, 6000/6001, 6010/6011, 6025/6026, 6240/6241, 6300, 6305, 6310, 6315/6316). Appended only valves with no VAV row: EV-5021, EV-5035, EV-6016, EV-6127. Equipment type = each tag's own prefix (AT/EV) per the standing rule. NB FCU5982/5991/5992/6985/6986 were already populated from an earlier session and matched A2.3, so left untouched. | F6: 3rd pair complete and verified (rows 2118, 2159, 2168, 2365-2397 re-read; no gaps). Next append row = 2398. Flagged yellow: AT-0002, AT-0005, AT-2001, AT-5030, AT-5045, EV-5035, EV-6127. Open note: A2.3 right-hand area is labelled RECEPTION AREA N-0169, which duplicates the left-side EXP. OFFICE N-0169 label - no tag sits there so no row was written.
A7: 7 | B7: 46245 | C7: Sent the 4th image pair — new: South Building L0 Section A1.2; old: North Building L0 Section B2.1. Continue the established workflow. | D7: Filled SB FCU2002-2005 (rows 2169-2172). Mapped 45 of 46 blank VAV rows for A1.2 (C/D 1738:1783 = VAV2002-VAV2047). Appended 112 rows (2398-2509): 45 A1.2 AT-20xx, 8 A1.2 standalone 0-series AT, 43 B2.1 AT, 15 B2.1 valves, FCU6997. Corrected AT-2001 (row 2369). Flagged 39 uncertain rows yellow, then fixed 14 misplaced flags. | E7: A1.2 turned out to be a map-the-rooms floor: VAV2002-VAV2047 existed but were blank, and AT numbers correspond 1:1 to VAV numbers. There is no VAV2001 row and no VAV rows for the 0115-0124 series, so those 9 tags were appended only. VAV2005 (row 1741) left blank - AT-2005 does not appear on A1.2. Self-caught error: skipping AT-2005 in the append shifted my flag row offsets by one, so 7 flags landed on confident rows (AT-2010/2014/2017/2018/2026/2034/2036) and 7 uncertain rows were unflagged; cleared and re-applied correctly. AT-2001 moved from Vestibule S-0202 (per A1.3) to High-Density Room S-0206 (per A1.2, box sits inside the room outline) - still flagged. | F7: 4th pair complete and verified (rows 2169-2172, 2369, 1738-1783, 2398-2510 re-read; no gaps; flag colours confirmed on C:D). Next append row = 2510. DEFERRED / NEEDS USER DECISION: (1) 21 blank NB VAV rows discovered - 1468 (VAV6295), 1473-1490 (VAV6320-6410), 1543-1544 (VAV7385/7390) - not filled because two existing rows conflict with the drawing, so a bulk same-number fill is unsafe. (2) Conflict A: registry row 1465 VAV6220 = Conf N-0331 and row 1463 VAV6205 = Emergency Elec. N-0333, but B2.1 shows AT-6220 at Emergency Elec. N-0333 and AT-6205 at Conference N-0331 (appears swapped). (3) Conflict B: registry row 1485 VAV6380 = Office N-0376, but B2.1 shows AT-6370 at Office N-0376 and AT-6380 at Workstation N-0378 (possible off-by-one, same pattern as the A2.2 fix).
A8: 8 | B8: 46245 | C8: Sent the 5th image pair — new: South Building L0 Section A1.1; old: North Building L0 Section B2.2. Continue the established workflow. | D8: A1.1: filled VAV3001-3007 (rows 1784-1790) and FCU3001 (row 2173); appended 45 tags (2510-2554) = 32 AT-30xx plus 13 of the 2301-AT-01xx BACnet points. B2.2: appended 77 rows (2555-2631) = 51 AT (incl. the AT-7090/7105/7120 multi-node sensors), 8 standalone EV, 17 lab valves, FCU7993. Flagged 34 rows yellow across both. | E8: B2.2's VAV rows mostly already existed with rooms, so the AT twins inherited the registry room (consistent with the A2.1/A2.2 approach) rather than my read of the drawing; the five places where the drawing disagrees were flagged instead of overwritten. Multi-node tags (AT-7090-N1/N2, AT-7105-N1/N2, AT-7120-N1..N9) have no VAV rows and were mapped from the drawing to N-0412/0412A, N-0415/0415A, N-0418/0418A and N-0430A..N-0430F - all flagged. Skipped every valve already embedded in a VAV row name (VEV7031, VEV7051, VEV7061, CEV7221, VEV7231, VEV7241A, VEV7251/7261/7271/7281/7291/7311/7321/7331/7341/7351/7361/7371, EV7126/7141/7186/7216/7495). FEV-7232 appears twice on the drawing - appended once and flagged. | F8: 5th pair complete and verified (rows 1784-1790, 2173, 2510-2632 re-read; 122 appended rows with no gaps; flag colours spot-checked against tag names). Next append row = 2632. NEW CONFLICTS FLAGGED, NOT OVERWRITTEN: (1) FCU rows 2119/2120/2121 (FCU7981 = Stair 5 N-0STO5, FCU7982 and FCU7983 = Service Corridor N-0344) disagree with B2.2, which shows FCU-7993 at Stair 5, FCU-7981 at IDF N-0419 and FCU-7982 near Mech/FPC N-0434. (2) Row 2085 FCU7790 is tagged NB_1F but B2.2 (Level 0) shows FCU-7790 at Stair 6 N-0ST06. (3) Registry rows 1517/1518 give both VAV7145 and VAV7155 the same room (Office N-0427) - drawing suggests 7145 = N-0425. (4) Row 1519 VAV7165 = N-0428 vs drawing N-0429. (5) Row 1523 VAV7185 = Office N-0426 vs drawing Emer. Elec. Room N-0433, and row 1526 VAV7215 = Emergency Elec. N-0433 vs drawing Office N-0438. STILL OPEN from turn 7: the 21 blank NB VAV rows (1468, 1473-1490, 1543-1544) and the VAV6205/6220 and VAV6380 conflicts.
A9: 9 | B9: 46245 | C9: Sent the 6th image pair — new: South Building Level 1 Section B1.2; old: North Building Level 01 Section A2.1. First pair on Level 1 rather than Level 0. | D9: B1.2: filled 45 blank VAV rows (C/D across 1595:1645) and FCU1503 (row 2132); appended 49 AT tags (2632-2680). A2.1 L01: appended 28 rows (2681-2708) = 8 AT twins, 19 valves, FCU2004. Flagged 5 rows yellow after correcting 2 that landed one row off. | E9: Both drawings are Level 1, so writes went to the SB_1F and NB_1F blocks (not GF). SB VAV15xx occupies rows 1590-1645 but the series is not contiguous - VAV1504, 1535, 1537, 1538 and 1541 have no rows, so AT-1504/1535/1537 were appended only. NB_1F registry rooms for VAV4660-4745 matched my reading of the drawing exactly (N-1227 through N-1244), so those 8 AT twins needed no flags. NB_1F FCU4910/4915/4916/4917 were already correctly populated and match A2.1, so left untouched. Skipped valves already embedded in VAV row names (VEV4621, VEV4631, VEV4051/4061/4091, the VAV4070-4083 high-bay pairs) and VEV-4041 which was already appended at row 2253. | F9: 6th pair complete and verified (rows 1590-1645, 2132, 2632-2709 re-read; 77 appended rows with no gaps; flag cells checked against tag names). Next append row = 2709. Flagged: AT-1504 (corridor position), AT-1533 and AT-1536 (sit between an electrical room and an office), AT-1537, CEV-4502, FCU2004. Still-blank SB L1 VAV rows with no tag on this drawing: 1590-1594 (VAV1501-1503, 1505, 1506), 1624-1625 (VAV1539/1540), 1627-1629 (VAV1543-1545), 1631 (VAV1547) - likely on the B1.1 half of Level 1. STILL OPEN: the 21 blank NB GF VAV rows (1468, 1473-1490, 1543-1544) and the registry conflicts at rows 1463/1465, 1485, 1517/1518, 1519, 1523/1526, 2085, 2119-2121.
A10: 10 | B10: 46245 | C10: Sent the 7th image pair — new: South Building Level 1 Section B1.1; old: North Building Level 1 Section A2.2. | D10: B1.1: filled 34 blank VAV rows (1566-1594, 1624-1631) + FCU1501/1502 (2130-2131); appended 46 AT tags (2709-2754). A2.2: filled FCU5986 (2076) and VAV4650 (1842); appended 67 rows (2755-2821) = 42 AT, 7 EV, 18 lab valves. Flagged 12 rows yellow. | E10: ERROR MADE AND CORRECTED: I wrote to FCU5983 (row 2073) and FCU5984 (row 2074) without reading them first - they already held 'Not Included / JC N-1139' and 'Included / Corridor N-1138'. I overwrote both with my own reading of the drawing (IDF N-1140 / JC N-1139), then restored the original values from the pre-write snapshot and flagged all three rows instead. Only FCU5986 was genuinely blank and kept a new value. Lesson: read FCU rows before writing, as several were populated in earlier sessions. Otherwise: NB_1F VAV5650-5940 rooms already matched the drawing closely, so those 38 AT twins inherited the registry room. Skipped valves embedded in VAV row names (VEV5601/5611/5622/5623/5631/5771/5781/5793/5795A/5801, EV5656/5716/5731/5736/5741/5761/5836). Unnumbered 'TAG 0.0' boxes on A2.2 could not be appended. | F10: 7th pair complete and verified (rows 1566-1645, 1842, 2073-2076, 2130-2132, 2709-2822 re-read; 113 appended rows with no gaps; all 12 flag cells checked against tag names). Next append row = 2822. South Building Level 1 is now fully mapped except VAV0509 (row 1569) - no AT-0509 appears on either B1.1 or B1.2. Flagged: AT-0504, AT-0505, AT-0515, AT-0534, AT-0529, AT-5685 (registry calls N-1126 an Office, drawing calls it Corridor), AT-5840 and AT-5905 (registry gives both Office N-1163), EV-5686, VEV-5581 (label appears twice on drawing), VEV-5821, FCU1503 (row 2132 - B1.2 shows it at Stair 1, B1.1 shows it near FPC S-1108/UPS S-1107D), FCU5983/5984/5986. STILL OPEN: 21 blank NB GF VAV rows (1468, 1473-1490, 1543-1544) and conflicts at rows 1463/1465, 1485, 1517/1518, 1519, 1523/1526, 2085, 2119-2121.
A11: 11 | B11: 46245 | C11: Sent the 8th image pair — new: South Building Level 1 Section A1.3; old: North Building Level 1 Section A2.3. Both are sparse core/lobby sections. | D11: A1.3: filled VAV2501 (row 1646, Lobby S-1201), FCU0501 (2127, Stair 2 S-1ST02) and FCU2501 (2133, Stair 3 S-1ST03); appended 2 AT tags (2822-2823 = AT-2501 Lobby S-1201, AT-2507 Female S-1204); corrected AT-0503 and AT-0505 rooms. A2.3: NO rows written - see details. Flagged 4 rows. | E11: Pre-read all three fill targets before writing this turn (lesson from turn 10) - all were genuinely blank. AT-0503 changed from NCIR Office S-1115 to Women S-1106B and AT-0505 from UPS S-1107D to Emergency Elec. S-1107B: A1.3 is the section that actually contains the S-1105/S-1106B/S-1107B core, AT-0502 already matched Vestibule S-1105, and 0502/0503/0505 form a clean sequence onto those three rooms. A2.3 yielded nothing appendable: every sensor box on it is an unnumbered 'TAG' with no tag ID, so there is nothing to key a registry row on. Separately, FCU-2004 appears SIX times on A2.3 (Stair 3 N-1ST03, Stair 4 N-1ST04, Normal Elec. N-1310, IDF N-1311, Mech/FPC N-1353A, Reception N-1355) all reading 25.3 C - one BMS point bound to six graphic boxes, so no new rows could be derived; flagged row 2708 instead. | F11: 8th pair complete and verified (rows 1646, 2127, 2133, 2708, 2711-2713, 2822-2824 re-read; flag fills confirmed). Next append row = 2824. OPEN QUESTION raised: moving AT-0503 to Women S-1106B leaves NCIR Office S-1115 with no sensor and VAV0509 (row 1569) still blank - the B1.1 tag I read as AT-0503 in that office may actually be AT-0509. Needs user confirmation before writing. Flagged: AT-0503, AT-0505, AT-2501, FCU2004. STILL OPEN from earlier turns: 21 blank NB GF VAV rows (1468, 1473-1490, 1543-1544) and conflicts at rows 1463/1465, 1485, 1517/1518, 1519, 1523/1526, 2085, 2119-2121, 1889, 1910/1923, 2132, 2073/2074.
A12: 12 | B12: 46245 | C12: Sent the 9th image pair — new: South Building Level 1 Section A1.2; old: North Building Level 1 Section B2.1. | D12: A1.2: filled 50 blank VAV rows (C/D 1647:1696 = VAV2502-VAV2553) and 4 FCU rows (2134-2137); appended 51 AT tags (2824-2874). B2.1: appended 79 rows (2875-2953) = 40 AT, 8 EV, 31 lab valves. 130 appended rows total. Flagged 22 rows yellow. | E12: Pre-read all 54 fill targets before writing - all confirmed blank, no overwrite. Verified fill alignment by spot-checking VAV2511=Office S-1212, VAV2536=Normal Elec. S-1251, VAV2553=Male Prayer S-1278 after the block write. B2.1 registry rooms matched the drawing throughout (VAV6650-6725 = N-1319 to N-1336, VAV6900-6970 = N-1357 to N-1371, VAV7865 = N-1461A), so those 34 AT twins inherited the registry room with no flags. VAV6630B/6631B were checked and already populated (Bio-Med Chem Lab 1 N-1316L) so were skipped, as were FCU6988/6989 which already read Service Corridor N-1337 and match the drawing. Corridor-run valves EV-6936/6961/6969 were assigned by the EV-pairs-with-VAV convention (Workstation N-1363/N-1368/N-1371) and flagged, since the dotted corridor they sit on carries no room number on this drawing. | F12: 9th pair complete and verified (rows 1647-1696, 2080-2081, 2134-2137, 2824-2954 re-read; 130 appended rows with no gaps; all 22 flag cells checked against tag names). Next append row = 2954. Flagged: AT-2502/2503/2505/2506 and VAV2502/2503/2505/2506 (four lobby-band sensors with no room label of their own - all assigned Lobby S-1202), AT-2552/VAV2552 (label appears twice on A1.2), AT-4260 (4000-series tag on a South Building drawing, assigned Men S-1254), FCU2502-2505, AT-7500, EV-7501, EV-6936/6961/6969, CEV-6581, FEV-6731. STILL OPEN: 21 blank NB GF VAV rows (1468, 1473-1490, 1543-1544); conflicts at rows 1463/1465, 1485, 1517/1518, 1519, 1523/1526, 2085, 2119-2121, 1889, 1910/1923, 2132, 2073/2074; and the AT-0503/AT-0509 vs NCIR Office S-1115 question (row 1569 still blank).
A13: 13 | B13: 46245 | C13: Sent the 10th image pair — new: South Building Level 1 Section A1.1; old: North Building Level 1 Section B2.2. | D13: A1.1: filled 20 blank VAV rows (C/D 1697:1717 = VAV3504-VAV3524, leaving VAV3519 blank) and FCU3501 (row 2138, Stair S-1ST104); appended 28 AT tags (2954-2981). B2.2: appended 58 rows (2982-3039) = 42 AT, 8 EV, 8 lab valves. 86 appended rows total. Flagged 15 rows yellow. | E13: Pre-read all 22 fill targets and aborted-on-conflict guard was in the code; all were blank so nothing was overwritten. Verified alignment after the block write (VAV3504=Open Plan S-1229, VAV3514=Office S-1294, VAV3519 blank, VAV3524=Normal Elec. S-1238). VAV3519 left blank - no AT-3519 on the drawing. There are no VAV rows for AT-3501/3502/3503 or for the 2301-AT-02xx BACnet points, so those were appended only. B2.2 registry rooms matched the drawing throughout (VAV7620-7710 = N-1415 to N-1442, VAV7840-7960 = N-1458 to N-1480, and the N-1404x / N-1450x lab series), so all 42 AT twins inherited the registry room. RESOLVED an earlier flag: row 2085 FCU7790 was flagged in turn 8 because it carries the NB_1F tag but appeared on a Level 0 drawing - B2.2 (Level 1) now shows FCU-7790 at Stair 6 N-1ST06, matching the registry, so the NB_1F assignment looks correct and the Level 0 sighting was a graphic repeat. All seven NB_1F FCU rows (2085-2091) were already populated and match B2.2, so none were touched. | F13: 10th pair complete and verified (rows 1697-1717, 2085-2091, 2138, 2954-3040 re-read; 86 appended rows with no gaps; all 15 flag cells checked against tag names). Next append row = 3040. Flagged: AT-3501 (sits under Lobby S-0294 which is a Level 0 room number on a Level 1 drawing), AT-3502, AT-3511/VAV3511, AT-3514/VAV3514 and AT-3520/VAV3520 (drawing carries TWO rooms labelled OFFICE S-1294 - one bottom-centre, one right of the stair), AT-0207/AT-0208, AT-7705 (registry room is just 'Expansion (Office)' with no number), EV-7663, EV-7712, CEV-7761, CEV-7791. NEW pre-existing issue spotted: rows 2034 and 2036 both give Flow Cyto N-1450C (VEV7751 and VEV7781) but the drawing puts VEV-7781 in iPS-TC N-1450F. STILL OPEN: 21 blank NB GF VAV rows (1468, 1473-1490, 1543-1544); conflicts at rows 1463/1465, 1485, 1517/1518, 1519, 1523/1526, 2119-2121, 1889, 1910/1923, 2132, 2073/2074, 2034/2036; and the AT-0503/AT-0509 vs NCIR Office S-1115 question (row 1569 still blank).
... A59: 55 | B59: 46261 | C59: User asked to re-run the validation of the QNL room/equipment mapping. | D59: Re-audited 'Controllable Asset Registry' A779:A1329 against column D of 'QNL Room Names with Equip.'. Read-only; no changes made. | E59: Source range in the column D TRANSPOSE(FILTER(...)) formulas has widened since the earlier audit, from A779:A1229 to A779:A1329, and now carries an if_empty argument returning "No Equipment in entity". Rooms in column A run to row 353 (352 entities) with matching formulas in D2:D353. Audited against the widened range: 551 asset tags, 537 with a non-blank column E entity. Also checked CAR rows below 1329 - 271 further assets exist but all carry SSC_ prefixed entities (different building), so ending the range at 1329 is correct and no QNL assets are excluded. | F59: Clean. 537 of 537 eligible assets placed in the correct room row; 0 unplaced, 0 misplaced, 0 orphans, 0 spill errors, no duplicate tags or duplicate room entities. 14 blank-entity assets correctly excluded with no leakage. 154 rooms legitimately show "No Equipment in entity".

Sheet HQ Asset Register
A1: EQUIPMENT ASSET REGISTER
A2: Tag No. | B2: Equipment Type | C2: Description | D2: Remarks
A3: AHU12_0001 | B3: AHU | C3: Air Handling Unit
A4: AHU12_0002 | B4: AHU | C4: Air Handling Unit
A5: AHU12_0003 | B5: AHU | C5: Air Handling Unit
A6: AHU12_0004 | B6: AHU | C6: Air Handling Unit | F6: EQUIPMENT COUNT SUMMARY
A7: AHU12_0006 | B7: AHU | C7: Air Handling Unit | F7: AHU | G7: =COUNTIF(B:B,"AHU") -> 26
A8: AHU12_0007 | B8: AHU | C8: Air Handling Unit | F8: FCU | G8: =COUNTIF(B:B,"FCU") -> 133
A9: AHU12_0008 | B9: AHU | C9: Air Handling Unit | F9: CHW Pump | G9: =COUNTIF(B:B,"CHW Pump") -> 4
A10: AHU12_0009 | B10: AHU | C10: Air Handling Unit | F10: Variable Air Volume | G10: =COUNTIF(B:B,"VAV") -> 602
A11: AHU12_0010 | B11: AHU | C11: Air Handling Unit | F11: DX Unit | G11: =COUNTIF(B:B,"DX Unit") -> 24
A12: AHU2_0001 | B12: AHU | C12: Air Handling Unit | F12: Heat Exchanger | G12: =COUNTIF(B:B,"HEX") -> 5
A13: AHU5_0001 | B13: AHU | C13: Air Handling Unit | F13: CCU | G13: =COUNTIF(B:B,"CCU") -> 11
A14: AHU5_0002 | B14: AHU | C14: Air Handling Unit | F14: EF | G14: =COUNTIF(B:B,"EF") -> 12
A15: AHU9_0001 | B15: AHU | C15: Air Handling Unit | F15: GEF | G15: =COUNTIF(B:B,"GEF") -> 13
A16: AHU9_0002 | B16: AHU | C16: Air Handling Unit | F16: TEF | G16: =COUNTIF(B:B,"TEF") -> 4
A17: AHU9_0003 | B17: AHU | C17: Air Handling Unit | F17: CEF | G17: =COUNTIF(B:B,"CEF") -> 60
A18: AHUB_0001 | B18: AHU | C18: Air Handling Unit | F18: SF | G18: =COUNTIF(B:B,"SF") -> 16
A19: AHUB_0002 | B19: AHU | C19: Air Handling Unit | F19: Generator | G19: =COUNTIF(B:B,"Generator") -> 2
A20: AHUB_0003 | B20: AHU | C20: Air Handling Unit | F20: TOTAL | G20: =SUM(G7:G19) -> 912
A21: AHUB_0004 | B21: AHU | C21: Air Handling Unit
A22: AHUB_0005 | B22: AHU | C22: Air Handling Unit
A23: AHUB_0006 | B23: AHU | C23: Air Handling Unit
A24: AHUB_0007 | B24: AHU | C24: Air Handling Unit
A25: AHUB_0008 | B25: AHU | C25: Air Handling Unit
A26: AHUB_0009 | B26: AHU | C26: Air Handling Unit
A27: AHUB_0010 | B27: AHU | C27: Air Handling Unit | F27: # | G27: Equipment type | H27: Tag(s) in IO list | I27: Assumption
A28: AHUB_0011 | B28: AHU | C28: Air Handling Unit | F28: 1 | G28: AHU | H28: AHU12_0010 | I28: These two tags refer to the same physical unit
A29: DX_B0001 | B29: DX Unit | C29: DX Unit - Interior | H29: AHU12_10
A30: DX_B0002 | B30: DX Unit | C30: DX Unit - Interior | F30: 2 | G30: AHU | H30: AHUB01_02 | I30: These two tags refer to the same physical unit
A31: DX_B0003 | B31: DX Unit | C31: DX Unit - Interior | H31: AHUB_0002
A32: DX_B0004 | B32: DX Unit | C32: DX Unit - Interior | F32: 3 | G32: AHU | H32: AHUB03_04 | I32: These two tags refer to the same physical unit
A33: DX_B0005 | B33: DX Unit | C33: DX Unit - Interior | H33: AHUB_0004
A34: DX_B0006 | B34: DX Unit | C34: DX Unit - Interior | F34: 4 | G34: AHU | H34: AHUB05_06 | I34: These two tags refer to the same physical unit
A35: DX_B0007 | B35: DX Unit | C35: DX Unit - Interior | H35: AHUB_0006
A36: DX_B0008 | B36: DX Unit | C36: DX Unit - Interior | F36: 5 | G36: AHU | H36: AHUB07 | I36: These two tags refer to the same physical unit
A37: DX_B0009 | B37: DX Unit | C37: DX Unit - Interior | H37: AHUB_0007
A38: DX_B0010 | B38: DX Unit | C38: DX Unit - Interior | F38: 6 | G38: AHU | H38: AHUB08 | I38: These two tags refer to the same physical unit
A39: DX_B0011 | B39: DX Unit | C39: DX Unit - Interior | H39: AHUB_0008
A40: DX_B0012 | B40: DX Unit | C40: DX Unit - Interior | F40: 7 | G40: AHU | H40: AHUB10 | I40: These two tags refer to the same physical unit
A41: DX_B0013 | B41: DX Unit | C41: DX Unit - Interior | H41: AHUB_0010
A42: DX_B0014 | B42: DX Unit | C42: DX Unit - Interior | F42: 8 | G42: AHU | H42: AHUB11 | I42: These two tags refer to the same physical unit
A43: DX_B0015 | B43: DX Unit | C43: DX Unit - Interior | H43: AHUB_0011
A44: DX_B0016 | B44: DX Unit | C44: DX Unit - Interior | F44: 9 | G44: DX Unit | H44: DX_ODSB0101 | I44: This DX unit was added later and not reflected in the HVAC Drawing
A45: DX_CP_0001 | B45: DX Unit | C45: DX Unit - Interior | F45: 10 | G45: DX Unit | H45: DX_ODSB0102 | I45: This DX unit was added later and not reflected in the HVAC Drawing
A46: DX_G0001 | B46: DX Unit | C46: DX Unit - Interior | F46: 11 | G46: DX Unit | H46: DX_ODSB0201 | I46: This DX unit was added later and not reflected in the HVAC Drawing
A47: DX_G0002 | B47: DX Unit | C47: DX Unit - Interior | F47: 12 | G47: DX Unit | H47: DX_ODSB0202 | I47: This DX unit was added later and not reflected in the HVAC Drawing
A48: DX_G0003 | B48: DX Unit | C48: DX Unit - Interior | F48: 13 | G48: DX Unit | H48: DX_CP_0001 | I48: This DX unit was added later and not reflected in the HVAC Drawing
A49: DX_ODSB0101 | B49: DX Unit | C49: DX Unit - Exterior
A50: DX_ODSB0102 | B50: DX Unit | C50: DX Unit - Exterior
A51: DX_ODSB0201 | B51: DX Unit | C51: DX Unit - Exterior
A52: DX_ODSB0202 | B52: DX Unit | C52: DX Unit - Exterior
A53: FCU0001 | B53: FCU | C53: Fan Coil Unit
A54: FCU0002 | B54: FCU | C54: Fan Coil Unit
A55: FCU0003 | B55: FCU | C55: Fan Coil Unit
A56: FCU0004 | B56: FCU | C56: Fan Coil Unit
A57: FCU0005 | B57: FCU | C57: Fan Coil Unit
A58: FCU0006 | B58: FCU | C58: Fan Coil Unit
A59: FCU0007 | B59: FCU | C59: Fan Coil Unit
A60: FCU0008 | B60: FCU | C60: Fan Coil Unit
... A914: ELEC_Gen3 | B914: Generator | C914: Generator

Sheet QNL Asset Register
A1: EQUIPMENT ASSET REGISTER
A2: Tag No. | B2: Equipment Type | C2: Description | D2: Remarks
A3: AHUB001 | B3: AHU | C3: Air Handling Unit
A4: AHUB002 | B4: AHU | C4: Air Handling Unit
A5: AHUB003 | B5: AHU | C5: Air Handling Unit
A6: AHUB004 | B6: AHU | C6: Air Handling Unit | H6: EQUIPMENT COUNT SUMMARY
A7: AHUB005 | B7: AHU | C7: Air Handling Unit | H7: AHU | I7: =COUNTIF(B:B,"AHU") -> 15
A8: AHUB006 | B8: AHU | C8: Air Handling Unit | H8: FCU | I8: =COUNTIF(B:B,"FCU") -> 137
A9: AHUB007 | B9: AHU | C9: Air Handling Unit | H9: CHW Pump | I9: =COUNTIF(B:B,"CHW Pump") -> 6
A10: AHUB008 | B10: AHU | C10: Air Handling Unit | H10: Variable Air Volume | I10: =COUNTIF(B:B,"VAV") -> 248
A11: AHUB009 | B11: AHU | C11: Air Handling Unit | H11: Constant Air Volume | I11: =COUNTIF(B:B,"CAV") -> 51
A12: AHUB010 | B12: AHU | C12: Air Handling Unit | H12: DX Unit | I12: =COUNTIF(B:B,"DX Unit") -> 24
A13: AHUB011 | B13: AHU | C13: Air Handling Unit | H13: Heat Exchanger | I13: =COUNTIF(B:B,"HEX") -> 5
A14: AHUB012 | B14: AHU | C14: Air Handling Unit | H14: CCU | I14: =COUNTIF(B:B,"CCU") -> 22
A15: AHUB013 | B15: AHU | C15: Air Handling Unit | H15: EF | I15: =COUNTIF(B:B,"EF") -> 18
A16: AHUB014 | B16: AHU | C16: Air Handling Unit | H16: SEF | I16: =COUNTIF(B:B,"SEF") -> 12
A17: AHUB015 | B17: AHU | C17: Air Handling Unit | H17: TEF | I17: =COUNTIF(B:B,"TEF") -> 8
A18: DX_B01 | B18: DX Unit | C18: DX Unit | H18: KEF | I18: =COUNTIF(B:B,"KEF") -> 4
A19: DX_B02 | B19: DX Unit | C19: DX Unit | H19: Generator | I19: =COUNTIF(B:B,"Generator") -> 1
A20: DX_B03 | B20: DX Unit | C20: DX Unit | H20: TOTAL | I20: =SUM(I7:I18) -> 550
A21: DX_B04 | B21: DX Unit | C21: DX Unit
A22: DX_B05 | B22: DX Unit | C22: DX Unit
A23: DX_B06 | B23: DX Unit | C23: DX Unit
A24: DX_B07 | B24: DX Unit | C24: DX Unit | H24: # | I24: Equipment type | J24: Tag(s) in IO list | K24: Assumption
A25: DX_B08 | B25: DX Unit | C25: DX Unit | H25: 1 | I25: EF | J25: EF_RP001 | K25: This is the same asset as : EF_RP01
A26: DX_B09 | B26: DX Unit | C26: DX Unit | H26: 2 | I26: EF | J26: EF_RP002 | K26: This is the same asset as : EF_RP02
A27: DX_B10 | B27: DX Unit | C27: DX Unit | H27: 3 | I27: EF | J27: EF_RP003 | K27: This is the same asset as : EF_RP03
A28: DX_B11 | B28: DX Unit | C28: DX Unit | H28: 4 | I28: EF | J28: EF_B009 | K28: This is the same asset as : EF_B09
A29: DX_B12 | B29: DX Unit | C29: DX Unit | H29: 5 | I29: EF | J29: EF_B011 | K29: This is the same asset as : EF_B11
A30: DX_B13 | B30: DX Unit | C30: DX Unit | H30: 6 | I30: DX Unit | J30: DX_B0010 | K30: This is the same asset as : DX_B10
A31: DX_B14 | B31: DX Unit | C31: DX Unit | H31: 7 | I31: DX Unit | J31: DX_B0011 | K31: This is the same asset as : DX_B11
A32: DX_B15 | B32: DX Unit | C32: DX Unit | H32: 8 | I32: DX Unit | J32: DX_B0012 | K32: This is the same asset as : DX_B12
A33: DX_B16 | B33: DX Unit | C33: DX Unit | H33: 9 | I33: DX Unit | J33: DX_B0020 | K33: This is the same asset as : DX_B20
A34: DX_B17 | B34: DX Unit | C34: DX Unit | H34: 10 | I34: DX Unit | J34: DX_B022 | K34: This is the same asset as : DX_B21
A35: DX_B18 | B35: DX Unit | C35: DX Unit | H35: 11 | I35: DX Unit | J35: DX_B023 | K35: This is the same asset as : DX_B22
A36: DX_B19 | B36: DX Unit | C36: DX Unit | H36: 12 | I36: DX Unit | J36: DX_B22 | K36: This DX unit was added later and not reflected in the HVAC Drawing
... A38: DX_B21 | B38: DX Unit | C38: DX Unit | H38: 14 | I38: DX Unit | J38: DX_B24 | K38: This DX unit was added later and not reflected in the HVAC Drawing
A39: DX_B22 | B39: DX Unit | C39: DX Unit | D39: This asset is available in the Local and SWS SCADA but not in the HVAC Drawings | H39: 15 | I39: HEX | J39: HEX05 | K39: This Heat Exchanger was added later and not reflecteed in the HVAC Drawing
A40: DX_B23 | B40: DX Unit | C40: DX Unit | D40: This asset is available in the Local and SWS SCADA but not in the HVAC Drawings | H40: 16 | I40: CCU | J40: CCU_AVServer_Rm | K40: This CCU is available in the Local SCADA but not configures in the SWS
A41: DX_B24 | B41: DX Unit | C41: DX Unit | D41: This asset is available in the Local and SWS SCADA but not in the HVAC Drawings
A42: FCU_1F_001 | B42: FCU | C42: Fan Coil Unit
A43: FCU_1F_002 | B43: FCU | C43: Fan Coil Unit
A44: FCU_1F_003 | B44: FCU | C44: Fan Coil Unit
A45: FCU_1F_004 | B45: FCU | C45: Fan Coil Unit
A46: FCU_1F_005 | B46: FCU | C46: Fan Coil Unit
A47: FCU_1F_006 | B47: FCU | C47: Fan Coil Unit
A48: FCU_1F_007 | B48: FCU | C48: Fan Coil Unit
A49: FCU_1F_008 | B49: FCU | C49: Fan Coil Unit
A50: FCU_1F_009 | B50: FCU | C50: Fan Coil Unit
A51: FCU_1F_010 | B51: FCU | C51: Fan Coil Unit
A52: FCU_1F_011 | B52: FCU | C52: Fan Coil Unit
A53: FCU_1F_012 | B53: FCU | C53: Fan Coil Unit
... A182: HEX04 | B182: HEX | C182: Heat Exchanger
A183: HEX05 | B183: HEX | C183: Heat Exchanger | D183: This asset is available in the Local and SWS SCADA but not in the HVAC Drawings
A184: VAV0001 | B184: VAV | C184: Variable Air Volume
A185: VAV_1F_S11_001 | B185: VAV | C185: Variable Air Volume
A186: VAV_1F_S11_002 | B186: VAV | C186: Variable Air Volume
A187: VAV_1F_S11_003 | B187: VAV | C187: Variable Air Volume
A188: VAV_1F_S11_004 | B188: VAV | C188: Variable Air Volume
A189: VAV_1F_S11_005 | B189: VAV | C189: Variable Air Volume
A190: VAV_1F_S11_006 | B190: VAV | C190: Variable Air Volume
A191: VAV_1F_S11_007 | B191: VAV | C191: Variable Air Volume
A192: VAV_1F_S11_008 | B192: VAV | C192: Variable Air Volume
A193: VAV_1F_S11_009 | B193: VAV | C193: Variable Air Volume
A194: VAV_1F_S11_010 | B194: VAV | C194: Variable Air Volume
A195: VAV_1F_S11_011 | B195: VAV | C195: Variable Air Volume
... A544: CCU_Server_Rm | B544: CCU | C544: CCU
A545: CCU_AVServer_Rm | B545: CCU | C545: CCU | D545: This Asset is available in Local SCADA but not in SWS (Historian)
A546: CCU_HeritageVault | B546: CCU | C546: CCU
A547: CHW_P01 | B547: CHW Pump | C547: Primary CHW Pumps
A548: CHW_P02 | B548: CHW Pump | C548: Primary CHW Pumps
A549: CHW_P03 | B549: CHW Pump | C549: Primary CHW Pumps
A550: CHW_P04 | B550: CHW Pump | C550: Primary CHW Pumps
A551: CHWPU_P01 | B551: CHW Pump | C551: Chilled Water Pressurization Unit Pump
A552: CHWPU_P02 | B552: CHW Pump | C552: Chilled Water Pressurization Unit Pump
A553: ELEC_Gen | B553: Generator | C553: Generator

Sheet SSC Asset Register
A1: EQUIPMENT ASSET REGISTER
A2: Tag No. | B2: Equipment Type | C2: Description | D2: Remarks
A3: AHUB_0001 | B3: AHU | C3: Air Handling Unit
A4: AHUB_0002 | B4: AHU | C4: Air Handling Unit
A5: AHUB_0003 | B5: AHU | C5: Air Handling Unit
A6: AHUB_0004 | B6: AHU | C6: Air Handling Unit | F6: EQUIPMENT COUNT SUMMARY
A7: AHUB_0005 | B7: AHU | C7: Air Handling Unit | F7: AHU | G7: =COUNTIF(B:B,"AHU") -> 5
A8: FCU0001 | B8: FCU | C8: Fan Coil Unit | F8: FCU | G8: =COUNTIF(B:B,"FCU") -> 11
A9: FCU0002 | B9: FCU | C9: Fan Coil Unit | F9: CHW Pump | G9: =COUNTIF(B:B,"CHW Pump") -> 8
A10: FCU0003 | B10: FCU | C10: Fan Coil Unit | F10: Variable Air Volume | G10: =COUNTIF(B:B,"VAV") -> 108
A11: FCU0004 | B11: FCU | C11: Fan Coil Unit | F11: DX Unit | G11: =COUNTIF(B:B,"DX Unit") -> 10
A12: FCU0005 | B12: FCU | C12: Fan Coil Unit | F12: Heat Exchanger | G12: =COUNTIF(B:B,"HEX") -> 5
A13: FCU0006 | B13: FCU | C13: Fan Coil Unit | F13: CCU | G13: =COUNTIF(B:B,"CCU") -> 14
A14: FCU0007 | B14: FCU | C14: Fan Coil Unit | F14: EF | G14: =COUNTIF(B:B,"EF") -> 1
A15: FCU0008 | B15: FCU | C15: Fan Coil Unit | F15: KEF | G15: =COUNTIF(B:B,"KEF") -> 2
A16: FCU0009 | B16: FCU | C16: Fan Coil Unit | F16: TEF | G16: =COUNTIF(B:B,"TEF") -> 4
A17: FCU0010 | B17: FCU | C17: Fan Coil Unit | F17: GEF | G17: =COUNTIF(B:B,"GEF") -> 1
A18: FCU0011 | B18: FCU | C18: Fan Coil Unit | F18: Generator | G18: =COUNTIF(B:B,"Generator") -> 1
A19: VAV0001 | B19: VAV | C19: Variable Air Volume | F19: TOTAL | G19: =SUM(G7:G18) -> 170
A20: VAV0002 | B20: VAV | C20: Variable Air Volume
A21: VAV0003 | B21: VAV | C21: Variable Air Volume
A22: VAV0004 | B22: VAV | C22: Variable Air Volume
A23: VAV0005 | B23: VAV | C23: Variable Air Volume
A24: VAV0006 | B24: VAV | C24: Variable Air Volume
A25: VAV0007 | B25: VAV | C25: Variable Air Volume
A26: VAV0008 | B26: VAV | C26: Variable Air Volume | F26: # | G26: Equipment type | H26: Tag(s) in IO list | I26: Assumption
A27: VAV0009 | B27: VAV | C27: Variable Air Volume | F27: 1 | G27: DX Unit | H27: DX/B/11 | I27: This DX unit is not available in I/O (Local and SWS) but available in the drawings
A28: VAV0010 | B28: VAV | C28: Variable Air Volume | F28: 2 | G28: DX Unit | H28: DX/B/12 | I28: This DX unit is not available in I/O (Local and SWS) but available in the drawings
A29: VAV0011 | B29: VAV | C29: Variable Air Volume | F29: 3 | G29: DX Unit | H29: DX/B/13 | I29: This DX unit is not available in I/O (Local and SWS) but available in the drawings
A30: VAV0012 | B30: VAV | C30: Variable Air Volume | F30: 4 | G30: DX Unit | H30: DX/B/14 | I30: This DX unit is not available in I/O (Local and SWS) but available in the drawings
A31: VAV0013 | B31: VAV | C31: Variable Air Volume | F31: 5 | G31: DX Unit | H31: DX/B/15 | I31: This DX unit is not available in I/O (Local and SWS) but available in the drawings
A32: VAV0014 | B32: VAV | C32: Variable Air Volume | F32: 6 | G32: DX Unit | H32: DX/B/16 | I32: This DX unit is not available in I/O (Local and SWS) but available in the drawings
A33: VAV0015 | B33: VAV | C33: Variable Air Volume | F33: 7 | G33: DX Unit | H33: DX/1/01 | I33: This DX unit is not available in I/O (Local and SWS) but available in the drawings
A34: VAV0016 | B34: VAV | C34: Variable Air Volume | F34: 8 | G34: DX Unit | H34: DX/1/02 | I34: This DX unit is not available in I/O (Local and SWS) but available in the drawings
A35: VAV0017 | B35: VAV | C35: Variable Air Volume | F35: 9 | G35: DX Unit | H35: DX/1/03 | I35: This DX unit is not available in I/O (Local and SWS) but available in the drawings
A36: VAV0018 | B36: VAV | C36: Variable Air Volume
A37: VAV0019 | B37: VAV | C37: Variable Air Volume
A38: VAV0020 | B38: VAV | C38: Variable Air Volume
A39: VAV0021 | B39: VAV | C39: Variable Air Volume
A40: VAV0022 | B40: VAV | C40: Variable Air Volume
A41: VAV0023 | B41: VAV | C41: Variable Air Volume
A42: VAV0024 | B42: VAV | C42: Variable Air Volume
A43: VAV0025 | B43: VAV | C43: Variable Air Volume
A44: VAV0026 | B44: VAV | C44: Variable Air Volume
A45: VAV0027 | B45: VAV | C45: Variable Air Volume
A46: VAV0028 | B46: VAV | C46: Variable Air Volume
A47: VAV0029 | B47: VAV | C47: Variable Air Volume
... A172: REF0001 | B172: EF | C172: Extract Fan

Sheet RDC Asset Register
A1: EQUIPMENT ASSET REGISTER
A2: Tag No. | B2: Equipment Type | C2: Description | D2: Remarks
A3: NB_AHU8511 | B3: AHU | C3: Air Handling Unit
A4: NB_AHU8512 | B4: AHU | C4: Air Handling Unit
A5: NB_AHU8513 | B5: AHU | C5: Air Handling Unit
A6: NB_AHU8514 | B6: AHU | C6: Air Handling Unit | H6: EQUIPMENT COUNT SUMMARY
A7: NB_AHU8515 | B7: AHU | C7: Air Handling Unit | H7: AHU | I7: =COUNTIF(B:B,"AHU") -> 37
A8: NB_AHU8516 | B8: AHU | C8: Air Handling Unit | H8: ERU | I8: =COUNTIF(B:B,"ERU") -> 11
A9: NB_AHU8517 | B9: AHU | C9: Air Handling Unit | H9: FCU | I9: =COUNTIF(B:B,"FCU") -> 135
A10: NB_AHU8518 | B10: AHU | C10: Air Handling Unit | H10: CHW Pump | I10: =COUNTIF(B:B,"CHW Pump") -> 9
A11: NB_AHU8519 | B11: AHU | C11: Air Handling Unit | H11: Variable Air Volume | I11: =COUNTIF(B:B,"VAV") -> 739
A12: NB_AHU8520 | B12: AHU | C12: Air Handling Unit | H12: Constant Air Volume | I12: =COUNTIF(B:B,"CAV") -> 78
A13: NB_AHU8521 | B13: AHU | C13: Air Handling Unit | H13: FEV | I13: =COUNTIF(B:B,"FEV") -> 76
A14: RDC_NB_ERU8531 | B14: ERU | C14: ERU | H14: VEV | I14: =COUNTIF(B:B,"VEV") -> 44
A15: RDC_NB_ERU8532 | B15: ERU | C15: ERU | H15: EAV | I15: =COUNTIF(B:B,"EAV") -> 51
A16: RDC_NB_ERU8533 | B16: ERU | C16: ERU | H16: Heat Exchanger | I16: =COUNTIF(B:B,"HEX") -> 7
A17: RDC_NB_ERU8534 | B17: ERU | C17: ERU | H17: EF | I17: =COUNTIF(B:B,"EF") -> 38
A18: RDC_NB_ERU8535 | B18: ERU | C18: ERU | H18: Generator | I18: =COUNTIF(B:B,"Generator") -> 3
A19: RDC_NB_ERU8536 | B19: ERU | C19: ERU | H19: TOTAL | I19: =SUM(I7:I18) -> 1228
A20: RDC_NB_ERU8537 | B20: ERU | C20: ERU
A21: RDC_NB_ERU8538 | B21: ERU | C21: ERU
A22: RDC_NB_ERU8539 | B22: ERU | C22: ERU
A23: RDC_NB_ERU8540 | B23: ERU | C23: ERU
A24: RDC_NB_ERU8541 | B24: ERU | C24: ERU
A25: RDC_SB_AHU8011 | B25: AHU | C25: Air Handling Unit
A26: RDC_SB_AHU8012 | B26: AHU | C26: Air Handling Unit
A27: RDC_SB_AHU8021 | B27: AHU | C27: Air Handling Unit
A28: RDC_SB_AHU8022 | B28: AHU | C28: Air Handling Unit
A29: RDC_SB_AHU8023 | B29: AHU | C29: Air Handling Unit | H29: # | I29: Equipment type | J29: Tag(s) in IO list | K29: Assumption
A30: RDC_SB_AHU8024 | B30: AHU | C30: Air Handling Unit | H30: 1 | I30: DX Unit | J30: RDC_UB_AHU8603_DXUnit | K30: This is the DX coil/compressor of AHU8603
A31: RDC_SB_AHU8025 | B31: AHU | C31: Air Handling Unit | H31: 2 | I31: DX Unit | J31: RDC_UB_AHU8604_DXUnit | K31: This is the DX coil/compressor of AHU8604
A32: RDC_SB_AHU8026 | B32: AHU | C32: Air Handling Unit | H32: 3 | I32: DX Unit | J32: RDC_UB_AHU8605_DXUnit | K32: This is the DX coil/compressor of AHU8605
A33: RDC_SB_AHU8031 | B33: AHU | C33: Air Handling Unit | H33: 4 | I33: DX Unit | J33: RDC_UB_AHU8606_DXUnit | K33: This is the DX coil/compressor of AHU8606
A34: RDC_SB_AHU8032 | B34: AHU | C34: Air Handling Unit | H34: 5 | I34: DX Unit | J34: RDC_UB_AHU8607_DXUnit | K34: This is the DX coil/compressor of AHU8607
A35: RDC_SB_AHU8033 | B35: AHU | C35: Air Handling Unit | H35: 6 | I35: DX Unit | J35: RDC_UB_AHU8608_DXUnit | K35: This is the DX coil/compressor of AHU8608
A36: RDC_SB_AHU8034 | B36: AHU | C36: Air Handling Unit | H36: 7 | I36: DX Unit | J36: RDC_UB_AHU8609_DXUnit | K36: This is the DX coil/compressor of AHU8609
A37: RDC_SB_AHU8035 | B37: AHU | C37: Air Handling Unit | H37: 8 | I37: EF | J37: RDC_SB_BUS_EFA1 | K37: Extract fans serving the bus station
A38: RDC_SB_AHU8036 | B38: AHU | C38: Air Handling Unit | H38: 9 | I38: EF | J38: RDC_SB_BUS_EFA2 | K38: Extract fans serving the bus station
A39: RDC_SB_AHU8037 | B39: AHU | C39: Air Handling Unit | H39: 10 | I39: EF | J39: RDC_SB_BUS_EFA3 | K39: Extract fans serving the bus station
A40: RDC_SB_AHU8041 | B40: AHU | C40: Air Handling Unit | H40: 11 | I40: EF | J40: RDC_SB_BUS_EFA4 | K40: Extract fans serving the bus station
A41: RDC_SB_AHU8042 | B41: AHU | C41: Air Handling Unit | H41: 12 | I41: EF | J41: RDC_SB_BUS_EFA5 | K41: Extract fans serving the bus station
... A56: RDC_NB_EF8552 | B56: EF | C56: EF | H56: 27 | I56: EF | J56: RDC_SB_BUS_EFD2 | K56: Extract fans serving the bus station
A57: RDC_NB_EF8553 | B57: EF | C57: EF
A58: RDC_NB_EF8554 | B58: EF | C58: EF
A59: RDC_SB_EF8041 | B59: EF | C59: EF
A60: RDC_SB_EF8042 | B60: EF | C60: EF
A61: RDC_SB_EF8043 | B61: EF | C61: EF
A62: RDC_SB_EF8044 | B62: EF | C62: EF
A63: RDC_SB_BUS_EFA1 | B63: EF | C63: EF
A64: RDC_SB_BUS_EFA2 | B64: EF | C64: EF
A65: RDC_SB_BUS_EFA3 | B65: EF | C65: EF
A66: RDC_SB_BUS_EFA4 | B66: EF | C66: EF
A67: RDC_SB_BUS_EFA5 | B67: EF | C67: EF
A68: RDC_SB_BUS_EFA6 | B68: EF | C68: EF
... A1230: RDC_NB_GF_FEV7262 | B1230: FEV | C1230: FEV

Sheet Controllable Asset Registry
A1: Controllable Asset Registry
A2: Tag No. | B2: Equipment Type | C2: Inluded/ Not Inlcuded | D2: ROOM NAME AS PER DRAWINGS | H2: ROOM NAME PER VAV / FCU LIST (WHERE DIFFERENT)
A3: HQ
A4: AHU12_0001 | B4: AHU | C4: Not Included | D4: HQ RF | E4: entity:HQ_RF.001_ROOF
A5: AHU12_0002 | B5: AHU | C5: Included | D5: HQ RF | E5: entity:HQ_RF.001_ROOF
A6: AHU12_0003 | B6: AHU | C6: Included | D6: HQ RF | E6: entity:HQ_RF.001_ROOF
A7: AHU12_0004 | B7: AHU | C7: Not Included | D7: HQ RF | E7: entity:HQ_RF.001_ROOF
A8: AHU12_0006 | B8: AHU | C8: Not Included | D8: HQ RF | E8: entity:HQ_RF.001_ROOF
A9: AHU12_0007 | B9: AHU | C9: Not Included | D9: HQ RF | E9: entity:HQ_RF.001_ROOF
A10: AHU12_0008 | B10: AHU | C10: Not Included | D10: HQ RF | E10: entity:HQ_RF.001_ROOF
A11: AHU12_0009 | B11: AHU | C11: Not Included | D11: HQ RF | E11: entity:HQ_RF.001_ROOF
A12: AHU12_0010 | B12: AHU | C12: Not Included | D12: HQ RF | E12: entity:HQ_RF.001_ROOF
A13: AHU2_0001 | B13: AHU | C13: Not Included | D13: SPA PLANT ROOM 2.302 | E13: entity:HQ_2.302_SPA_PLANTROOM
A14: AHU5_0001 | B14: AHU | C14: Not Included | D14: PLANT ROOM 5.301 | E14: entity:HQ_5.301_PLANT_ROOM
A15: AHU5_0002 | B15: AHU | C15: Not Included | D15: PLANT ROOM 5.301 | E15: entity:HQ_5.301_PLANT_ROOM
... A30: FCU0001 | B30: FCU | C30: Not Included | D30: IDF ROOM B.512 | E30: entity:HQ_B1.512_IDF_ROOM
A31: FCU0002 | B31: FCU | C31: Not Included | D31: SECURITY CONTROL B.003 | E31: entity:HQ_B1.003_CONTROL_ROOM | H31: SECURITY CONTROL RM B.003
A32: FCU0003 | B32: FCU | C32: Included | D32: DOCK MASTER OFFICE B.107 | E32: entity:HQ_B1.107_DOCK_MASTER_OFFICE | H32: DOCKMASTER B.107
A33: FCU0004 | B33: FCU | C33: Not Included | D33: HH SECURITY B.113 | E33: entity:HQ_B1.113_SHEIKHA_LOBBY_SECURITY_ROOM | H33: HH SECURITY ROOM B.113
A34: FCU0005 | B34: FCU | C34: Not Included | D34: MALE TOILET B.401 | E34: entity:HQ_B1.401_MALE_TOILET | H34: SECURITY CONTROL RM B.003
A35: FCU0006 | B35: FCU | C35: Included | D35: ROOM B.122 | E35: entity:HQ_B1.122_SUPPORT_SPACE_FOOD_STORAGE | H35: FOOD STORAGE B.122
A36: FCU0007 | B36: FCU | C36: Included | D36: ROOM B.123 | E36: entity:HQ_B1.123_SUPPORT_SPACE_FOOD_STORAGE | H36: FOOD STORAGE B.123
A37: FCU0008 | B37: FCU | C37: Included | D37: ROOM B.014 | E37: entity:HQ_B1.014_SUPPORT_SPACE_DRY_WASTE_STORAGE | H37: SUPPORT SPACE LOADING B.015
A38: FCU0009 | B38: FCU | C38: Included | D38: ROOM B.014 | E38: entity:HQ_B1.014_SUPPORT_SPACE_DRY_WASTE_STORAGE | H38: DRY WASTE STORAGE B.014
A39: FCU0010 | B39: FCU | C39: Included | D39: ROOM B.124 | E39: entity:HQ_B1.015_SUPPORT_SPACE_LOADING | H39: WASTE BIN WASH UP B.124
A40: FCU0011 | B40: FCU | C40: Included | D40: CHAUFFEUR ROOM B.117 | E40: entity:HQ_B1.117_CHAUFFEUR_ROOM
A41: FCU0012 | B41: FCU | C41: Not Included | D41: IDF ROOM G.531 | E41: entity:HQ_G.531_IDF_ROOM
A42: FCU0013 | B42: FCU | C42: Not Included | D42: IDF ROOM G.531 | E42: entity:HQ_G.531_IDF_ROOM
A43: FCU0014 | B43: FCU | C43: Not Included | D43: IDF ROOM G.512 | E43: entity:HQ_G.512_IDF_ROOM
A44: FCU0015 | B44: FCU | C44: Not Included | D44: NURSERY CONSULT. G.031 | E44: entity:HQ_G.031_PR_&_MARKET_STAFF | H44: PRINT COPY ROOM G.031
A45: FCU0016 | B45: FCU | C45: Included | D45: COPY PRINT G.017 | E45: entity:HQ_G.017_COPY_PRINT | H45: PRINT COPY ROOM G.017
A46: FCU0017 | B46: FCU | C46: Not Included | D46: CONTROL CENTER G.005 | E46: entity:HQ_G.005_EMERGENCY_CONTROL_CENTER | H46: ESCAPE VESTIBULE 0.544
A47: FCU0018 | B47: FCU | C47: Not Included | D47: VESTIBULE G.511 | E47: entity:HQ_G.511_VESTIBULE | H47: ESCAPE VESTIBULE G.511
A48: FCU0019 | B48: FCU | C48: Not Included | D48: IDF ROOM 1.531 | E48: entity:HQ_1.531_IDF_ROOM
A49: FCU0020 | B49: FCU | C49: Not Included | D49: IDF ROOM 1.531 | E49: entity:HQ_1.531_IDF_ROOM
A50: FCU0021 | B50: FCU | C50: Not Included | D50: IDF ROOM 1.512 | E50: entity:HQ_1.512_IDF_ROOM
A51: FCU0022 | B51: FCU | C51: Included | D51: PRINT COPY 1.112 | E51: entity:HQ_1.112_PRINT_COPY | H51: PRINT COPY ROOM 1.112
A52: FCU0023 | B52: FCU | C52: Not Included | D52: IDF ROOM 2.531 | E52: entity:HQ_2.531_IDF_ROOM
A53: FCU0024 | B53: FCU | C53: Not Included | D53: IDF ROOM 2.531 | E53: entity:HQ_2.531_IDF_ROOM
A54: FCU0025 | B54: FCU | C54: Not Included | D54: TERRACE 2.701 | E54: entity:HQ_2.701_TERRACE | H54: BRIDGE BR-2 2.701
A55: FCU0026 | B55: FCU | C55: Not Included | D55: TERRACE 2.701 | E55: entity:HQ_2.701_TERRACE | H55: BRIDGE BR-2 2.701
A56: FCU0027 | B56: FCU | C56: Not Included | D56: TERRACE 2.701 | E56: entity:HQ_2.701_TERRACE | H56: BRIDGE BR-2 2.701
A57: FCU0028 | B57: FCU | C57: Included | D57: PRINT COPY 2.103 | E57: entity:HQ_2.103_PRINT_COPY | H57: PRINT COPY ROOM 2.103
A58: FCU0029 | B58: FCU | C58: Not Included | D58: SPA LOUNGE BAR 2.207 | E58: entity:HQ_2.207_SPA_LOUNGE_BAR | H58: LOUNGE 2.207
A59: FCU0030 | B59: FCU | C59: Not Included | D59: SPA LOUNGE BAR 2.207 | E59: entity:HQ_2.207_SPA_LOUNGE_BAR
A60: FCU0031 | B60: FCU | C60: Not Included | D60: SPA FITNESS STUDIO 2.208 | E60: entity:HQ_2.208_SPA_FITNESS_DTUDIO | H60: FITNESS STUDIO 2.208
A61: FCU0032 | B61: FCU | C61: Not Included | D61: SPA FITNESS STUDIO 2.208 | E61: entity:HQ_2.208_SPA_FITNESS_DTUDIO
A62: FCU0033 | B62: FCU | C62: Not Included | D62: SPA FITNESS STUDIO 2.208 | E62: entity:HQ_2.208_SPA_FITNESS_DTUDIO
A63: FCU0034 | B63: FCU | C63: Not Included | D63: SPA OFFICE 2.209 | E63: entity:HQ_2.209_SPA_OFFICE | H63: OFFICE 2.209
A64: FCU0035 | B64: FCU | C64: Not Included | D64: STAFF FEMALE WC 2.210 | E64: entity:HQ_2.21_SPA_STAFF_WAITING_AREA | H64: STAFF WAFTING ROOM 2.210
A65: FCU0036 | B65: FCU | C65: Not Included | D65: SPA. FM BEAUTY SALON 2.211 | E65: entity:HQ_2.211_SPA_FEMALE_BEAUTY_SALON | H65: BEAUTY SALON 2.211
A66: FCU0037 | B66: FCU | C66: Not Included | D66: SPA. FM BEAUTY SALON 2.211 | E66: entity:HQ_2.211_SPA_FEMALE_BEAUTY_SALON
A67: FCU0038 | B67: FCU | C67: Not Included | D67: SPA FM TREATMENT 2.212 | E67: entity:HQ_2.212_SPA_FM_TREATMENT_1 | H67: TREATMENT ROOM 2.212
A68: FCU0039 | B68: FCU | C68: Not Included | D68: SPA CHANGING ROOM 2.213 | E68: entity:HQ_2.213_SPA_CHANGING_ROOM | H68: CHANGING ROOM 2.213
A69: FCU0040 | B69: FCU | C69: Not Included | D69: SPA CHANGING ROOM 2.213 | E69: entity:HQ_2.213_SPA_CHANGING_ROOM
A70: FCU0041 | B70: FCU | C70: Not Included | D70: SPA FM TREATMENT 2.214 | E70: entity:HQ_2.214_SPA_FM_TREATMENT_2 | H70: TREATMENT ROOM 2.214
A71: FCU0042 | B71: FCU | C71: Not Included | D71: SPA FM TREATMENT 2.215 | E71: entity:HQ_2.215_SPA_FM_TREATMENT_3 | H71: TREATMENT ROOM 2.215
A72: FCU0043 | B72: FCU | C72: Not Included | D72: SPA FM RELAXATION 2.216 | E72: entity:HQ_2.216_SPA_FM_RELAXATION | H72: RELAXATION 2.216
A73: FCU0044 | B73: FCU | C73: Not Included | D73: SPA FM RELAXATION 2.216 | E73: entity:HQ_2.216_SPA_FM_RELAXATION
A74: FCU0045 | B74: FCU | C74: Not Included | D74: SPA MALE RELAXATION 2.201 | E74: entity:HQ_2.201_SPA_MALE_RELAXATION | H74: RELAXATION 2.201
A75: FCU0046 | B75: FCU | C75: Not Included | D75: SPA MALE RELAXATION 2.201 | E75: entity:HQ_2.201_SPA_MALE_RELAXATION
A76: FCU0047 | B76: FCU | C76: Not Included | D76: SPA MALE RELAXATION 2.201 | E76: entity:HQ_2.201_SPA_MALE_RELAXATION
A77: FCU0048 | B77: FCU | C77: Not Included | D77: SPA MALE TREATMENT 3 2.202 | E77: entity:HQ_2.202_SPA_MALE_TREATMENT_3 | H77: TREATMENT ROOM 2.202
A78: FCU0049 | B78: FCU | C78: Not Included | D78: SPA MALE TREATMENT 2 2.203 | E78: entity:HQ_2.203_SPA_MALE_TREATMENT_2 | H78: TREATMENT ROOM 2.203
A79: FCU0050 | B79: FCU | C79: Not Included | D79: SPA MALE TREATMENT 1 2.204 | E79: entity:HQ_2.204_SPA_MALE_TREATMENT_1 | H79: TREATMENT ROOM 2.204
A80: FCU0051 | B80: FCU | C80: Not Included | D80: MALE CHANGING ROOM 2.205 | E80: entity:HQ_2.205_SPA_MALE_CHANGING_ROOM | H80: CHANGING ROOM 2.205
A81: FCU0052 | B81: FCU | C81: Not Included | D81: MALE CHANGING ROOM 2.205 | E81: entity:HQ_2.205_SPA_MALE_CHANGING_ROOM
A82: FCU0053 | B82: FCU | C82: Not Included | D82: SPA ENTRANCE 2.206 | E82: entity:HQ_2.206_SPA_ENTRANCE | H82: ENTRANCE 2.206
A83: FCU0054 | B83: FCU | C83: Not Included | D83: SPA LOBBY 2.603 | E83: entity:HQ_2.603_SPA_LOBBY | H83: LOBBY 2.603
A84: FCU0055 | B84: FCU | C84: Not Included | D84: SPA LOBBY 2.603 | E84: entity:HQ_2.603_SPA_LOBBY
A85: FCU0056 | B85: FCU | C85: Not Included | D85: IDF ROOM 2.512 | E85: entity:HQ_2.512_MECHANICAL_ROOM
A86: FCU0057 | B86: FCU | C86: Not Included | D86: SPA PLANT ROOM 2.302 | E86: entity:HQ_2.302_SPA_PLANTROOM | H86: PLANT ROOM SE
A87: FCU0058 | B87: FCU | C87: Not Included | D87: SPA PLANT ROOM 2.302 | E87: entity:HQ_2.302_SPA_PLANTROOM | H87: PLANT ROOM SE
A88: FCU0059 | B88: FCU | C88: Not Included | D88: IDF ROOM 3.531 | E88: entity:HQ_3.531_IDF_ROOM
A89: FCU0060 | B89: FCU | C89: Not Included | D89: IDF ROOM 3.531 | E89: entity:HQ_3.531_IDF_ROOM
A90: FCU0061 | B90: FCU | C90: Not Included | D90: IDF ROOM 3.512 | E90: entity:HQ_3.512_IDF_ROOM
A91: FCU0062 | B91: FCU | C91: Included | D91: COPY/PRINT 3.203 | E91: entity:HQ_3.203_COPYPRINT | H91: PRINT COPY ROOM 3.203
A92: FCU0063 | B92: FCU | C92: Included | D92: PRINT COPY 3.103 | E92: entity:HQ_3.103_PRINT_COPY | H92: PRINT COPY ROOM 3.103
A93: FCU0064 | B93: FCU | C93: Not Included | D93: CORRIDOR BRIDGE 3.63 | E93: entity:HQ_3.603_CORRIDOR_BRIDGE | H93: BRIDGE BR-3B 3.63
A94: FCU0065 | B94: FCU | C94: Not Included | D94: CORRIDOR BRIDGE 3.63 | E94: entity:HQ_3.603_CORRIDOR_BRIDGE | H94: BRIDGE BR-3B 3.63
A95: FCU0066 | B95: FCU | C95: Not Included | D95: CORRIDOR BRIDGE 3.63 | E95: entity:HQ_3.603_CORRIDOR_BRIDGE | H95: BRIDGE BR-3B 3.63
A96: FCU0067 | B96: FCU | C96: Included | D96: NORTH EAST ZONE | E96: entity:HQ_5.602_BRIDGE | H96: BRIDGE BR-3
A97: FCU0068 | B97: FCU | C97: Included | D97: NORTH EAST ZONE | E97: entity:HQ_5.602_BRIDGE | H97: BRIDGE BR-3
A98: FCU0069 | B98: FCU | C98: Included | D98: NORTH EAST ZONE | E98: entity:HQ_5.602_BRIDGE | H98: BRIDGE BR-3
A99: FCU0070 | B99: FCU | C99: Included | D99: NORTH EAST ZONE | E99: entity:HQ_5.602_BRIDGE | H99: BRIDGE BR-3
A100: FCU0071 | B100: FCU | C100: Not Included | D100: IDF ROOM 04.531 | E100: entity:HQ_4.531_IDF_ROOM
A101: FCU0072 | B101: FCU | C101: Not Included | D101: IDF ROOM 04.531 | E101: entity:HQ_4.531_IDF_ROOM
A102: FCU0073 | B102: FCU | C102: Not Included | D102: IDF ROOM 04.512 | E102: entity:HQ_4.512_IDF_ROOM
A103: FCU0074 | B103: FCU | C103: Included | D103: PRINT COPY 05.202 | E103: entity:HQ_5.202_VP_EDU_MEMBERS_OF_EDU | H103: PRINT COPY ROOM 04.202
A104: FCU0075 | B104: FCU | C104: Not Included | D104: GSM ROOM 05.214 | E104: entity:HQ_5.214_GSM_ROOM | H104: GSM ROOM 04.214
A105: FCU0076 | B105: FCU | C105: Not Included | D105: GSM ROOM 05.214 | E105: entity:HQ_5.214_GSM_ROOM | H105: GSM ROOM 04.214
A106: FCU0077 | B106: FCU | C106: Included | D106: VP ADM TERRACE 04.701 | E106: entity:HQ_4.701_VP_ADM_TERRACE | H106: BRIDGE BR-5 04.701
A107: FCU0078 | B107: FCU | C107: Included | D107: VP ADM TERRACE 04.701 | E107: entity:HQ_4.701_VP_ADM_TERRACE | H107: BRIDGE BR-5 04.701
A108: FCU0079 | B108: FCU | C108: Included | D108: VP ADM TERRACE 04.701 | E108: entity:HQ_4.701_VP_ADM_TERRACE | H108: BRIDGE BR-5 04.701
A109: FCU0080 | B109: FCU | C109: Included | D109: VP ADM TERRACE 04.701 | E109: entity:HQ_4.701_VP_ADM_TERRACE | H109: BRIDGE BR-5 04.701
A110: FCU0081 | B110: FCU | C110: Not Included | D110: TERRACE 04.702 | E110: entity:HQ_4.702_TERRACE | H110: BRIDGE BR-4 04.702
A111: FCU0082 | B111: FCU | C111: Not Included | D111: TERRACE 04.703 | E111: entity:HQ_4.703_TERRACE | H111: BRIDGE BR-4 04.703
A112: FCU0083 | B112: FCU | C112: Not Included | D112: TERRACE 04.702 | E112: entity:HQ_4.702_TERRACE | H112: BRIDGE BR-4 04.702
A113: FCU0084 | B113: FCU | C113: Included | D113: PRINT COPY 04.110 | E113: entity:HQ_4.11_PRINT_COPY | H113: PRINT COPY ROOM 04.110
A114: FCU0085 | B114: FCU | C114: Not Included | D114: IDF ROOM 5.531 | E114: entity:HQ_5.531_IDF_ROOM
...

Sheet SSC Room Names with Equip.
A1: Name | B1: Number | C1: entity to use in Ontology | D1: Equipment located in Entity
A2: VENT PLANT | B2: B1.014 | C2: entity:SSC_B1_014_VENT_PLANT | D2: {=TRANSPOSE(_xlfn._xlws.FILTER('Controllable Asset Registry'!$A$1331:$A$1454,IFERROR('Controllable Asset Registry'!$E$1331:$E$1454=C2,FALSE),"No Equipment in entity"))} -> AHUB_0002 | E2: AHUB_0003
A3: CHILLED WATER | B3: B1.013 | C3: entity:SSC_B1_013_CHILLED_WATER | D3: {=TRANSPOSE(_xlfn._xlws.FILTER('Controllable Asset Registry'!$A$1331:$A$1454,IFERROR('Controllable Asset Registry'!$E$1331:$E$1454=C3,FALSE),"No Equipment in entity"))} -> AHUB_0001 | E3: AHUB_0005
A4: GENERATOR | B4: B1.012 | C4: entity:SSC_B1_012_GENERATOR | D4: {=TRANSPOSE(_xlfn._xlws.FILTER('Controllable Asset Registry'!$A$1331:$A$1454,IFERROR('Controllable Asset Registry'!$E$1331:$E$1454=C4,FALSE),"No Equipment in entity"))} -> No Equipment in entity
A5: STAIR-1 | B5: B1.ST-1 | C5: entity:SSC_B1_ST-1_STAIR-1 | D5: {=TRANSPOSE(_xlfn._xlws.FILTER('Controllable Asset Registry'!$A$1331:$A$1454,IFERROR('Controllable Asset Registry'!$E$1331:$E$1454=C5,FALSE),"No Equipment in entity"))} -> No Equipment in entity
A6: ENTRANCE | B6: B1.015 | C6: entity:SSC_B1_015_ENTRANCE | D6: {=TRANSPOSE(_xlfn._xlws.FILTER('Controllable Asset Registry'!$A$1331:$A$1454,IFERROR('Controllable Asset Registry'!$E$1331:$E$1454=C6,FALSE),"No Equipment in entity"))} -> VAV0001
A7: LIFT | B7: B1.P-1 | C7: entity:SSC_B1_P-1_P1 | D7: {=TRANSPOSE(_xlfn._xlws.FILTER('Controllable Asset Registry'!$A$1331:$A$1454,IFERROR('Controllable Asset Registry'!$E$1331:$E$1454=C7,FALSE),"No Equipment in entity"))} -> No Equipment in entity
A8: LIFT | B8: B1.P-2 | C8: entity:SSC_B1_P-2_P2 | D8: {=TRANSPOSE(_xlfn._xlws.FILTER('Controllable Asset Registry'!$A$1331:$A$1454,IFERROR('Controllable Asset Registry'!$E$1331:$E$1454=C8,FALSE),"No Equipment in entity"))} -> No Equipment in entity
A9: SPRINKLER & WATER | B9: B1.016 | C9: entity:SSC_B1_016_SPRINKLER_&_WATER | D9: {=TRANSPOSE(_xlfn._xlws.FILTER('Controllable Asset Registry'!$A$1331:$A$1454,IFERROR('Controllable Asset Registry'!$E$1331:$E$1454=C9,FALSE),"No Equipment in entity"))} -> FCU0001
A10: SER-2 | B10: B1.038 | C10: entity:SSC_B1_038_SER-2 | D10: {=TRANSPOSE(_xlfn._xlws.FILTER('Controllable Asset Registry'!$A$1331:$A$1454,IFERROR('Controllable Asset Registry'!$E$1331:$E$1454=C10,FALSE),"No Equipment in entity"))} -> No Equipment in entity
A11: MDF-2 | B11: B1.017 | C11: entity:SSC_B1_017_MDF-2 | D11: {=TRANSPOSE(_xlfn._xlws.FILTER('Controllable Asset Registry'!$A$1331:$A$1454,IFERROR('Controllable Asset Registry'!$E$1331:$E$1454=C11,FALSE),"No Equipment in entity"))} -> No Equipment in entity
A12: FM STORAGE | B12: B1.019 | C12: entity:SSC_B1_019_FM_STORAGE | D12: {=TRANSPOSE(_xlfn._xlws.FILTER('Controllable Asset Registry'!$A$1331:$A$1454,IFERROR('Controllable Asset Registry'!$E$1331:$E$1454=C12,FALSE),"No Equipment in entity"))} -> No Equipment in entity
A13: CONDENSER ROOM | B13: B1.018 | C13: entity:SSC_B1_018_CONDENSER_ROOM | D13: {=TRANSPOSE(_xlfn._xlws.FILTER('Controllable Asset Registry'!$A$1331:$A$1454,IFERROR('Controllable Asset Registry'!$E$1331:$E$1454=C13,FALSE),"No Equipment in entity"))} -> No Equipment in entity
A14: FILE STORAGE | B14: B1.028 | C14: entity:SSC_B1_028_FILE_STORAGE | D14: {=TRANSPOSE(_xlfn._xlws.FILTER('Controllable Asset Registry'!$A$1331:$A$1454,IFERROR('Controllable Asset Registry'!$E$1331:$E$1454=C14,FALSE),"No Equipment in entity"))} -> No Equipment in entity
A15: CORRIDOR | B15: B1.030 | C15: entity:SSC_B1_030_CORRIDOR | D15: {=TRANSPOSE(_xlfn._xlws.FILTER('Controllable Asset Registry'!$A$1331:$A$1454,IFERROR('Controllable Asset Registry'!$E$1331:$E$1454=C15,FALSE),"No Equipment in entity"))} -> No Equipment in entity
... A43: STAIR-9 | B43: 01.ST-9 | C43: entity:SSC_01_ST-9_STAIR-9 | D43: {=TRANSPOSE(_xlfn._xlws.FILTER('Controllable Asset Registry'!$A$1331:$A$1454,IFERROR('Controllable Asset Registry'!$E$1331:$E$1454=C43,FALSE),"No Equipment in entity"))} -> No Equipment in entity
A44: OUTDOOR AREA | B44: 1.037 | C44: entity:SSC_01_037_OUTDOOR_AREA | D44: {=TRANSPOSE(_xlfn._xlws.FILTER('Controllable Asset Registry'!$A$1331:$A$1454,IFERROR('Controllable Asset Registry'!$E$1331:$E$1454=C44,FALSE),"No Equipment in entity"))} -> No Equipment in entity
A45: SHELL SPACE | B45: 1.014 | C45: entity:SSC_01_014_SHELL_SPACE | D45: {=TRANSPOSE(_xlfn._xlws.FILTER('Controllable Asset Registry'!$A$1331:$A$1454,IFERROR('Controllable Asset Registry'!$E$1331:$E$1454=C45,FALSE),"No Equipment in entity"))} -> VAV0002 | E45: VAV0003 | F45: VAV0004
A46: STAIR-3 | B46: 01.ST-3 | C46: entity:SSC_01_ST-3_STAIR-3 | D46: {=TRANSPOSE(_xlfn._xlws.FILTER('Controllable Asset Registry'!$A$1331:$A$1454,IFERROR('Controllable Asset Registry'!$E$1331:$E$1454=C46,FALSE),"No Equipment in entity"))} -> No Equipment in entity
A47: SHELL SPACE | B47: 1.015 | C47: entity:SSC_01_015_SHELL_SPACE | D47: {=TRANSPOSE(_xlfn._xlws.FILTER('Controllable Asset Registry'!$A$1331:$A$1454,IFERROR('Controllable Asset Registry'!$E$1331:$E$1454=C47,FALSE),"No Equipment in entity"))} -> VAV0005 | E47: VAV0006 | F47: VAV0007
A48: STAIR-8 | B48: 01.ST-8 | C48: entity:SSC_01_ST-8_STAIR-8 | D48: {=TRANSPOSE(_xlfn._xlws.FILTER('Controllable Asset Registry'!$A$1331:$A$1454,IFERROR('Controllable Asset Registry'!$E$1331:$E$1454=C48,FALSE),"No Equipment in entity"))} -> No Equipment in entity
A49: SHELL SPACE | B49: 1.016 | C49: entity:SSC_01_016_SHELL_SPACE | D49: {=TRANSPOSE(_xlfn._xlws.FILTER('Controllable Asset Registry'!$A$1331:$A$1454,IFERROR('Controllable Asset Registry'!$E$1331:$E$1454=C49,FALSE),"No Equipment in entity"))} -> VAV0030
A50: STORAGE | B50: 1.041 | C50: entity:SSC_01_041_STORAGE_ROOM | D50: {=TRANSPOSE(_xlfn._xlws.FILTER('Controllable Asset Registry'!$A$1331:$A$1454,IFERROR('Controllable Asset Registry'!$E$1331:$E$1454=C50,FALSE),"No Equipment in entity"))} -> No Equipment in entity
A51: FEMALE TOILET | B51: 1.017 | C51: entity:SSC_01_017_FEMALE_TOILET | D51: {=TRANSPOSE(_xlfn._xlws.FILTER('Controllable Asset Registry'!$A$1331:$A$1454,IFERROR('Controllable Asset Registry'!$E$1331:$E$1454=C51,FALSE),"No Equipment in entity"))} -> No Equipment in entity
A52: CORRIDOR | B52: 1.018 | C52: entity:SSC_01_018_CORRIDOR | D52: {=TRANSPOSE(_xlfn._xlws.FILTER('Controllable Asset Registry'!$A$1331:$A$1454,IFERROR('Controllable Asset Registry'!$E$1331:$E$1454=C52,FALSE),"No Equipment in entity"))} -> VAV0032
A53: SHELL SPACE | B53: 1.002 | C53: entity:SSC_01_002_SHELL_SPACE | D53: {=TRANSPOSE(_xlfn._xlws.FILTER('Controllable Asset Registry'!$A$1331:$A$1454,IFERROR('Controllable Asset Registry'!$E$1331:$E$1454=C53,FALSE),"No Equipment in entity"))} -> VAV0025 | E53: VAV0026 | F53: VAV0027 | G53: VAV0028
A54: ABLUTION ROOM | B54: 1.022 | C54: entity:SSC_01_022_ABLUTION_ROOM | D54: {=TRANSPOSE(_xlfn._xlws.FILTER('Controllable Asset Registry'!$A$1331:$A$1454,IFERROR('Controllable Asset Registry'!$E$1331:$E$1454=C54,FALSE),"No Equipment in entity"))} -> VAV0036
A55: ABLUTION ROOM | B55: 1.021 | C55: entity:SSC_01_021_ABLUTION_ROOM | D55: {=TRANSPOSE(_xlfn._xlws.FILTER('Controllable Asset Registry'!$A$1331:$A$1454,IFERROR('Controllable Asset Registry'!$E$1331:$E$1454=C55,FALSE),"No Equipment in entity"))} -> No Equipment in entity
A56: CORRIDOR | B56: 1.023 | C56: entity:SSC_01_023_CORRIDOR | D56: {=TRANSPOSE(_xlfn._xlws.FILTER('Controllable Asset Registry'!$A$1331:$A$1454,IFERROR('Controllable Asset Registry'!$E$1331:$E$1454=C56,FALSE),"No Equipment in entity"))} -> No Equipment in entity
A57: CORRIDOR | B57: 1.02 | C57: entity:SSC_01_020_CORRIDOR | D57: {=TRANSPOSE(_xlfn._xlws.FILTER('Controllable Asset Registry'!$A$1331:$A$1454,IFERROR('Controllable Asset Registry'!$E$1331:$E$1454=C57,FALSE),"No Equipment in entity"))} -> No Equipment in entity
A58: CORRIDOR | B58: 1.024 | C58: entity:SSC_01_024_CORRIDOR | D58: {=TRANSPOSE(_xlfn._xlws.FILTER('Controllable Asset Registry'!$A$1331:$A$1454,IFERROR('Controllable Asset Registry'!$E$1331:$E$1454=C58,FALSE),"No Equipment in entity"))} -> VAV0008
A59: IDF - 2 | B59: 1.039 | C59: entity:SSC_01_039_IDF_2 | D59: {=TRANSPOSE(_xlfn._xlws.FILTER('Controllable Asset Registry'!$A$1331:$A$1454,IFERROR('Controllable Asset Registry'!$E$1331:$E$1454=C59,FALSE),"No Equipment in entity"))} -> FCU0007 | E59: FCU0008
A60: IDF - 1 | B60: 1.027 | C60: entity:SSC_01_027_IDF_1 | D60: {=TRANSPOSE(_xlfn._xlws.FILTER('Controllable Asset Registry'!$A$1331:$A$1454,IFERROR('Controllable Asset Registry'!$E$1331:$E$1454=C60,FALSE),"No Equipment in entity"))} -> FCU0005 | E60: FCU0006
A61: FURNITURE STORAGE | B61: 1.026 | C61: entity:SSC_01_026_STORAGE_ROOM | D61: {=TRANSPOSE(_xlfn._xlws.FILTER('Controllable Asset Registry'!$A$1331:$A$1454,IFERROR('Controllable Asset Registry'!$E$1331:$E$1454=C61,FALSE),"No Equipment in entity"))} -> No Equipment in entity
A62: MALE TOILET | B62: 1.025 | C62: entity:SSC_01_025_MALE_TOILET | D62: {=TRANSPOSE(_xlfn._xlws.FILTER('Controllable Asset Registry'!$A$1331:$A$1454,IFERROR('Controllable Asset Registry'!$E$1331:$E$1454=C62,FALSE),"No Equipment in entity"))} -> No Equipment in entity
A63: PRAYER ROOM | B63: 1.019 | C63: entity:SSC_01_019_PRAYER_ROOM | D63: {=TRANSPOSE(_xlfn._xlws.FILTER('Controllable Asset Registry'!$A$1331:$A$1454,IFERROR('Controllable Asset Registry'!$E$1331:$E$1454=C63,FALSE),"No Equipment in entity"))} -> VAV0009 | E63: VAV0010 | F63: VAV0011 | G63: VAV0012 | H63: VAV0013 | I63: VAV0014
A64: CORRIDOR | B64: 1.001 | C64: entity:SSC_01_001_CORRIDOR | D64: {=TRANSPOSE(_xlfn._xlws.FILTER('Controllable Asset Registry'!$A$1331:$A$1454,IFERROR('Controllable Asset Registry'!$E$1331:$E$1454=C64,FALSE),"No Equipment in entity"))} -> VAV0024 | E64: VAV0029 | F64: VAV0031
A65: OPEN SPACE | B65: 1.003 | C65: entity:SSC_01_003_OPEN_SPACE | D65: {=TRANSPOSE(_xlfn._xlws.FILTER('Controllable Asset Registry'!$A$1331:$A$1454,IFERROR('Controllable Asset Registry'!$E$1331:$E$1454=C65,FALSE),"No Equipment in entity"))} -> VAV0022 | E65: VAV0023 | F65: VAV0034 | G65: VAV0039
A66: SHELL SPACE | B66: 1.029 | C66: entity:SSC_01_029_ROOM_NO_42 | D66: {=TRANSPOSE(_xlfn._xlws.FILTER('Controllable Asset Registry'!$A$1331:$A$1454,IFERROR('Controllable Asset Registry'!$E$1331:$E$1454=C66,FALSE),"No Equipment in entity"))} -> VAV0015 | E66: VAV0016 | F66: VAV0017
A67: STORAGE | B67: 1.012 | C67: entity:SSC_01_012_STORAGE | D67: {=TRANSPOSE(_xlfn._xlws.FILTER('Controllable Asset Registry'!$A$1331:$A$1454,IFERROR('Controllable Asset Registry'!$E$1331:$E$1454=C67,FALSE),"No Equipment in entity"))} -> No Equipment in entity
A68: LIFT | B68: 01.P-2 | C68: entity:SSC_01_P-2_P-2 | D68: {=TRANSPOSE(_xlfn._xlws.FILTER('Controllable Asset Registry'!$A$1331:$A$1454,IFERROR('Controllable Asset Registry'!$E$1331:$E$1454=C68,FALSE),"No Equipment in entity"))} -> No Equipment in entity
A69: LIFT | B69: 01.P-1 | C69: entity:SSC_01_P-1_P-1 | D69: {=TRANSPOSE(_xlfn._xlws.FILTER('Controllable Asset Registry'!$A$1331:$A$1454,IFERROR('Controllable Asset Registry'!$E$1331:$E$1454=C69,FALSE),"No Equipment in entity"))} -> No Equipment in entity
A70: CORRIDOR | B70: 1.013 | C70: entity:SSC_01_013_CORRIDOR | D70: {=TRANSPOSE(_xlfn._xlws.FILTER('Controllable Asset Registry'!$A$1331:$A$1454,IFERROR('Controllable Asset Registry'!$E$1331:$E$1454=C70,FALSE),"No Equipment in entity"))} -> VAV0021
A71: STAIR-1 | B71: 01.ST-1 | C71: entity:SSC_01_ST-1_STAIR-1 | D71: {=TRANSPOSE(_xlfn._xlws.FILTER('Controllable Asset Registry'!$A$1331:$A$1454,IFERROR('Controllable Asset Registry'!$E$1331:$E$1454=C71,FALSE),"No Equipment in entity"))} -> No Equipment in entity
A72: AUDITORIUM MEETING ROOM | B72: 1.009 | C72: entity:SSC_01_009_AUDITORIUM | D72: {=TRANSPOSE(_xlfn._xlws.FILTER('Controllable Asset Registry'!$A$1331:$A$1454,IFERROR('Controllable Asset Registry'!$E$1331:$E$1454=C72,FALSE),"No Equipment in entity"))} -> No Equipment in entity
A73: STORAGE AREA | B73: 1.038 | C73: entity:SSC_01_038_STORAGE_AREA | D73: {=TRANSPOSE(_xlfn._xlws.FILTER('Controllable Asset Registry'!$A$1331:$A$1454,IFERROR('Controllable Asset Registry'!$E$1331:$E$1454=C73,FALSE),"No Equipment in entity"))} -> No Equipment in entity
A74: A / V ROOM | B74: 1.008 | C74: entity:SSC_01_008_AV_ROOM | D74: {=TRANSPOSE(_xlfn._xlws.FILTER('Controllable Asset Registry'!$A$1331:$A$1454,IFERROR('Controllable Asset Registry'!$E$1331:$E$1454=C74,FALSE),"No Equipment in entity"))} -> FCU0004 | E74: VAV0037
A75: FEMALE TOILET | B75: 1.007 | C75: entity:SSC_01_007_FEMALE_TOILET | D75: {=TRANSPOSE(_xlfn._xlws.FILTER('Controllable Asset Registry'!$A$1331:$A$1454,IFERROR('Controllable Asset Registry'!$E$1331:$E$1454=C75,FALSE),"No Equipment in entity"))} -> No Equipment in entity
A76: MALE TOILET | B76: 1.006 | C76: entity:SSC_01_006_MALE_TOILET | D76: {=TRANSPOSE(_xlfn._xlws.FILTER('Controllable Asset Registry'!$A$1331:$A$1454,IFERROR('Controllable Asset Registry'!$E$1331:$E$1454=C76,FALSE),"No Equipment in entity"))} -> No Equipment in entity
A77: KITCHEN | B77: 1.005 | C77: entity:SSC_01_005_KITCHEN | D77: {=TRANSPOSE(_xlfn._xlws.FILTER('Controllable Asset Registry'!$A$1331:$A$1454,IFERROR('Controllable Asset Registry'!$E$1331:$E$1454=C77,FALSE),"No Equipment in entity"))} -> No Equipment in entity
A78: CORRIDOR | B78: 1.004 | C78: entity:SSC_01_004_CORRIDOR | D78: {=TRANSPOSE(_xlfn._xlws.FILTER('Controllable Asset Registry'!$A$1331:$A$1454,IFERROR('Controllable Asset Registry'!$E$1331:$E$1454=C78,FALSE),"No Equipment in entity"))} -> No Equipment in entity
A79: STAIR-4 | B79: 01.ST-4 | C79: entity:SSC_01_ST-4_STAIR_4 | D79: {=TRANSPOSE(_xlfn._xlws.FILTER('Controllable Asset Registry'!$A$1331:$A$1454,IFERROR('Controllable Asset Registry'!$E$1331:$E$1454=C79,FALSE),"No Equipment in entity"))} -> VAV0038
A80: AIR LOCK | B80: 1.011 | C80: entity:SSC_01_011_AIR_LOCK | D80: {=TRANSPOSE(_xlfn._xlws.FILTER('Controllable Asset Registry'!$A$1331:$A$1454,IFERROR('Controllable Asset Registry'!$E$1331:$E$1454=C80,FALSE),"No Equipment in entity"))} -> No Equipment in entity
A81: CORRIDOR | B81: 1.01 | C81: entity:SSC_01_010_CORRIDOR | D81: {=TRANSPOSE(_xlfn._xlws.FILTER('Controllable Asset Registry'!$A$1331:$A$1454,IFERROR('Controllable Asset Registry'!$E$1331:$E$1454=C81,FALSE),"No Equipment in entity"))} -> FCU0010 | E81: VAV0035
A82: STAIR-5 | B82: 01.ST-5 | C82: entity:SSC_01_ST-5_STAIR-5 | D82: {=TRANSPOSE(_xlfn._xlws.FILTER('Controllable Asset Registry'!$A$1331:$A$1454,IFERROR('Controllable Asset Registry'!$E$1331:$E$1454=C82,FALSE),"No Equipment in entity"))} -> No Equipment in entity
A83: STORAGE | B83: 1.03 | C83: entity:SSC_01_030_STORAGE | D83: {=TRANSPOSE(_xlfn._xlws.FILTER('Controllable Asset Registry'!$A$1331:$A$1454,IFERROR('Controllable Asset Registry'!$E$1331:$E$1454=C83,FALSE),"No Equipment in entity"))} -> No Equipment in entity
A84: TOILET | B84: 1.031 | C84: entity:SSC_01_031_TOILET | D84: {=TRANSPOSE(_xlfn._xlws.FILTER('Controllable Asset Registry'!$A$1331:$A$1454,IFERROR('Controllable Asset Registry'!$E$1331:$E$1454=C84,FALSE),"No Equipment in entity"))} -> No Equipment in entity
A85: VESTIBULE | B85: 1.032 | C85: entity:SSC_01_032_VESTIBULE | D85: {=TRANSPOSE(_xlfn._xlws.FILTER('Controllable Asset Registry'!$A$1331:$A$1454,IFERROR('Controllable Asset Registry'!$E$1331:$E$1454=C85,FALSE),"No Equipment in entity"))} -> No Equipment in entity
A86: JANITORS CLOSET | B86: 1.033 | C86: entity:SSC_01_033_JANITORS_CLOSET | D86: {=TRANSPOSE(_xlfn._xlws.FILTER('Controllable Asset Registry'!$A$1331:$A$1454,IFERROR('Controllable Asset Registry'!$E$1331:$E$1454=C86,FALSE),"No Equipment in entity"))} -> No Equipment in entity
A87: CORRIDOR | B87: 1.035 | C87: entity:SSC_01_035_CORRIDOR | D87: {=TRANSPOSE(_xlfn._xlws.FILTER('Controllable Asset Registry'!$A$1331:$A$1454,IFERROR('Controllable Asset Registry'!$E$1331:$E$1454=C87,FALSE),"No Equipment in entity"))} -> No Equipment in entity
A88: AIR LOCK | B88: 1.034 | C88: entity:SSC_01_034_AIR_LOCK | D88: {=TRANSPOSE(_xlfn._xlws.FILTER('Controllable Asset Registry'!$A$1331:$A$1454,IFERROR('Controllable Asset Registry'!$E$1331:$E$1454=C88,FALSE),"No Equipment in entity"))} -> No Equipment in entity
A89: STAIR-10 | B89: ST-10 | C89: entity:SSC_ST-10_STAIR-10 | D89: {=TRANSPOSE(_xlfn._xlws.FILTER('Controllable Asset Registry'!$A$1331:$A$1454,IFERROR('Controllable Asset Registry'!$E$1331:$E$1454=C89,FALSE),"No Equipment in entity"))} -> No Equipment in entity
A90: OUTDOOR AREA | B90: 1.036 | C90: entity:SSC_01_036_OUTDOOR_AREA | D90: {=TRANSPOSE(_xlfn._xlws.FILTER('Controllable Asset Registry'!$A$1331:$A$1454,IFERROR('Controllable Asset Registry'!$E$1331:$E$1454=C90,FALSE),"No Equipment in entity"))} -> No Equipment in entity
A91: STAIR-2 | B91: 01.ST-2 | C91: entity:SSC_01_ST-2_STAIR-2 | D91: {=TRANSPOSE(_xlfn._xlws.FILTER('Controllable Asset Registry'!$A$1331:$A$1454,IFERROR('Controllable Asset Registry'!$E$1331:$E$1454=C91,FALSE),"No Equipment in entity"))} -> No Equipment in entity
A92: CORRIDOR | B92: 1.028 | C92: entity:SSC_01_028_CORRIDOR | D92: {=TRANSPOSE(_xlfn._xlws.FILTER('Controllable Asset Registry'!$A$1331:$A$1454,IFERROR('Controllable Asset Registry'!$E$1331:$E$1454=C92,FALSE),"No Equipment in entity"))} -> FCU0009 | E92: VAV0033
A93: RESEARCHER'S OFFICE | B93: 3.015 | C93: entity:SSC_03_015_RESEARCHERS_OFFICE | D93: {=TRANSPOSE(_xlfn._xlws.FILTER('Controllable Asset Registry'!$A$1331:$A$1454,IFERROR('Controllable Asset Registry'!$E$1331:$E$1454=C93,FALSE),"No Equipment in entity"))} -> VAV0053
A94: VISITOR'S CUBICLE | B94: 3.014 | C94: entity:SSC_03_014_VISITORS_CUBICLE | D94: {=TRANSPOSE(_xlfn._xlws.FILTER('Controllable Asset Registry'!$A$1331:$A$1454,IFERROR('Controllable Asset Registry'!$E$1331:$E$1454=C94,FALSE),"No Equipment in entity"))} -> VAV0054
A95: RESEARCHER'S OFFICE | B95: 3.013 | C95: entity:SSC_03_013_RESEARCHERS_OFFICE | D95: {=TRANSPOSE(_xlfn._xlws.FILTER('Controllable Asset Registry'!$A$1331:$A$1454,IFERROR('Controllable Asset Registry'!$E$1331:$E$1454=C95,FALSE),"No Equipment in entity"))} -> VAV0055
A96: RESEARCHER'S OFFICE | B96: 3.012 | C96: entity:SSC_03_012_RESEARCHERS_OFFICE | D96: {=TRANSPOSE(_xlfn._xlws.FILTER('Controllable Asset Registry'!$A$1331:$A$1454,IFERROR('Controllable Asset Registry'!$E$1331:$E$1454=C96,FALSE),"No Equipment in entity"))} -> VAV0056
A97: VISITOR'S CUBICLE | B97: 3.011 | C97: entity:SSC_03_011_VISITORS_CUBICLE | D97: {=TRANSPOSE(_xlfn._xlws.FILTER('Controllable Asset Registry'!$A$1331:$A$1454,IFERROR('Controllable Asset Registry'!$E$1331:$E$1454=C97,FALSE),"No Equipment in entity"))} -> VAV0057
A98: RESEARCHER'S OFFICE | B98: 3.01 | C98: entity:SSC_03_010_RESEARCHERS_OFFICE | D98: {=TRANSPOSE(_xlfn._xlws.FILTER('Controllable Asset Registry'!$A$1331:$A$1454,IFERROR('Controllable Asset Registry'!$E$1331:$E$1454=C98,FALSE),"No Equipment in entity"))} -> VAV0058
A99: RESEARCHER'S OFFICE | B99: 3.009 | C99: entity:SSC_03_009_RESEARCHERS_OFFICE | D99: {=TRANSPOSE(_xlfn._xlws.FILTER('Controllable Asset Registry'!$A$1331:$A$1454,IFERROR('Controllable Asset Registry'!$E$1331:$E$1454=C99,FALSE),"No Equipment in entity"))} -> VAV0059
A100: VISITOR'S CUBICLE | B100: 3.008 | C100: entity:SSC_03_008_VISITORS_CUBICLE | D100: {=TRANSPOSE(_xlfn._xlws.FILTER('Controllable Asset Registry'!$A$1331:$A$1454,IFERROR('Controllable Asset Registry'!$E$1331:$E$1454=C100,FALSE),"No Equipment in entity"))} -> VAV0060
A101: OPERATIONS MANAGER | B101: 3.007 | C101: entity:SSC_03_007_OPERATIONS_MANAGER | D101: {=TRANSPOSE(_xlfn._xlws.FILTER('Controllable Asset Registry'!$A$1331:$A$1454,IFERROR('Controllable Asset Registry'!$E$1331:$E$1454=C101,FALSE),"No Equipment in entity"))} -> VAV0061
A102: MEETING ROOM | B102: 3.006 | C102: entity:SSC_03_006_MEETING_ROOM | D102: {=TRANSPOSE(_xlfn._xlws.FILTER('Controllable Asset Registry'!$A$1331:$A$1454,IFERROR('Controllable Asset Registry'!$E$1331:$E$1454=C102,FALSE),"No Equipment in entity"))} -> VAV0062 | E102: VAV0064
A103: RESEARCHER'S OFFICE | B103: 3.005 | C103: entity:SSC_03_005_RESEARCHERS_OFFICE | D103: {=TRANSPOSE(_xlfn._xlws.FILTER('Controllable Asset Registry'!$A$1331:$A$1454,IFERROR('Controllable Asset Registry'!$E$1331:$E$1454=C103,FALSE),"No Equipment in entity"))} -> VAV0065
A104: VISITOR'S CUBICLE | B104: 3.004 | C104: entity:SSC_03_004_VISITORS_CUBICLE | D104: {=TRANSPOSE(_xlfn._xlws.FILTER('Controllable Asset Registry'!$A$1331:$A$1454,IFERROR('Controllable Asset Registry'!$E$1331:$E$1454=C104,FALSE),"No Equipment in entity"))} -> VAV0066
A105: RESEARCHER'S OFFICE | B105: 3.003 | C105: entity:SSC_03_003_RESEARCHERS_OFFICE | D105: {=TRANSPOSE(_xlfn._xlws.FILTER('Controllable Asset Registry'!$A$1331:$A$1454,IFERROR('Controllable Asset Registry'!$E$1331:$E$1454=C105,FALSE),"No Equipment in entity"))} -> VAV0067
A106: DIRECTOR'S MEETING ROOM | B106: 3.002 | C106: entity:SSC_03_002_DIRECTORS_MEETING_ROOM | D106: {=TRANSPOSE(_xlfn._xlws.FILTER('Controllable Asset Registry'!$A$1331:$A$1454,IFERROR('Controllable Asset Registry'!$E$1331:$E$1454=C106,FALSE),"No Equipment in entity"))} -> VAV0068 | E106: VAV0069 | F106: VAV0071 | G106: VAV0072 | H106: VAV0073 | I106: VAV0074 | J106: VAV0075 | K106: VAV0076 | L106: VAV0077 | M106: VAV0107 | N106: VAV0108
A107: DIRECTOR'S OFFICE | B107: 3.001 | C107: entity:SSC_03_001_DIRECTORS_OFFICE | D107: {=TRANSPOSE(_xlfn._xlws.FILTER('Controllable Asset Registry'!$A$1331:$A$1454,IFERROR('Controllable Asset Registry'!$E$1331:$E$1454=C107,FALSE),"No Equipment in entity"))} -> VAV0070
A108: RESEARCHER'S OFFICE | B108: 3.017 | C108: entity:SSC_03_017_RESEARCHERS_OFFICE | D108: {=TRANSPOSE(_xlfn._xlws.FILTER('Controllable Asset Registry'!$A$1331:$A$1454,IFERROR('Controllable Asset Registry'!$E$1331:$E$1454=C108,FALSE),"No Equipment in entity"))} -> VAV0095
A109: VISITOR'S CUBICLE | B109: 3.018 | C109: entity:SSC_03_018_VISITORS_CUBICLE | D109: {=TRANSPOSE(_xlfn._xlws.FILTER('Controllable Asset Registry'!$A$1331:$A$1454,IFERROR('Controllable Asset Registry'!$E$1331:$E$1454=C109,FALSE),"No Equipment in entity"))} -> VAV0094
A110: IT MANAGER'S OFFICE | B110: 3.019 | C110: entity:SSC_03_019_IT_MANAGERS_OFFICE | D110: {=TRANSPOSE(_xlfn._xlws.FILTER('Controllable Asset Registry'!$A$1331:$A$1454,IFERROR('Controllable Asset Registry'!$E$1331:$E$1454=C110,FALSE),"No Equipment in entity"))} -> VAV0093
A111: RESEARCHER'S OFFICE | B111: 3.02 | C111: entity:SSC_03_020_RESEARCHERS_OFFICE | D111: {=TRANSPOSE(_xlfn._xlws.FILTER('Controllable Asset Registry'!$A$1331:$A$1454,IFERROR('Controllable Asset Registry'!$E$1331:$E$1454=C111,FALSE),"No Equipment in entity"))} -> VAV0092
A112: VISITOR'S CUBICLE | B112: 3.021 | C112: entity:SSC_03_021_VISITORS_CUBICLE | D112: {=TRANSPOSE(_xlfn._xlws.FILTER('Controllable Asset Registry'!$A$1331:$A$1454,IFERROR('Controllable Asset Registry'!$E$1331:$E$1454=C112,FALSE),"No Equipment in entity"))} -> VAV0091
A113: RESEARCHER'S OFFICE | B113: 3.022 | C113: entity:SSC_03_022_RESEARCHERS_OFFICE | D113: {=TRANSPOSE(_xlfn._xlws.FILTER('Controllable Asset Registry'!$A$1331:$A$1454,IFERROR('Controllable Asset Registry'!$E$1331:$E$1454=C113,FALSE),"No Equipment in entity"))} -> VAV0090
A114: RESEARCHER'S OFFICE | B114: 3.023 | C114: entity:SSC_03_023_RESEARCHERS_OFFICE | D114: {=TRANSPOSE(_xlfn._xlws.FILTER('Controllable Asset Registry'!$A$1331:$A$1454,IFERROR('Controllable Asset Registry'!$E$1331:$E$1454=C114,FALSE),"No Equipment in entity"))} -> VAV0089
A115: VISITOR'S CUBICLE | B115: 3.024 | C115: entity:SSC_03_024_VISITORS_CUBICLE | D115: {=TRANSPOSE(_xlfn._xlws.FILTER('Controllable Asset Registry'!$A$1331:$A$1454,IFERROR('Controllable Asset Registry'!$E$1331:$E$1454=C115,FALSE),"No Equipment in entity"))} -> VAV0088
A116: SECRETARIAL AREA | B116: 3.025 | C116: entity:SSC_03_025_SECRETARIAL_AREA | D116: {=TRANSPOSE(_xlfn._xlws.FILTER('Controllable Asset Registry'!$A$1331:$A$1454,IFERROR('Controllable Asset Registry'!$E$1331:$E$1454=C116,FALSE),"No Equipment in entity"))} -> VAV0087
A117: MEETING ROOM | B117: 3.026 | C117: entity:SSC_03_026_MEETING_ROOM | D117: {=TRANSPOSE(_xlfn._xlws.FILTER('Controllable Asset Registry'!$A$1331:$A$1454,IFERROR('Controllable Asset Registry'!$E$1331:$E$1454=C117,FALSE),"No Equipment in entity"))} -> VAV0084 | E117: VAV0085 | F117: VAV0086
A118: RESEARCHER'S OFFICE | B118: 3.027 | C118: entity:SSC_03_027_RESEARCHERS_OFFICE | D118: {=TRANSPOSE(_xlfn._xlws.FILTER('Controllable Asset Registry'!$A$1331:$A$1454,IFERROR('Controllable Asset Registry'!$E$1331:$E$1454=C118,FALSE),"No Equipment in entity"))} -> VAV0083
A119: VISITOR'S CUBICLE | B119: 3.028 | C119: entity:SSC_03_028_VISITORS_CUBICLE | D119: {=TRANSPOSE(_xlfn._xlws.FILTER('Controllable Asset Registry'!$A$1331:$A$1454,IFERROR('Controllable Asset Registry'!$E$1331:$E$1454=C119,FALSE),"No Equipment in entity"))} -> VAV0082
A120: RESEARCHER'S OFFICE | B120: 3.029 | C120: entity:SSC_03_029_RESEARCHERS_OFFICE | D120: {=TRANSPOSE(_xlfn._xlws.FILTER('Controllable Asset Registry'!$A$1331:$A$1454,IFERROR('Controllable Asset Registry'!$E$1331:$E$1454=C120,FALSE),"No Equipment in entity"))} -> VAV0081
A121: ASSOC. DIRECTOR'S MEETING ROOM | B121: 3.03 | C121: entity:SSC_03_030_ASSOC_DIRECTORS_MEETING_ROOM | D121: {=TRANSPOSE(_xlfn._xlws.FILTER('Controllable Asset Registry'!$A$1331:$A$1454,IFERROR('Controllable Asset Registry'!$E$1331:$E$1454=C121,FALSE),"No Equipment in entity"))} -> No Equipment in entity
A122: ASSOC. DIRECTOR'S OFFICE | B122: 3.031 | C122: entity:SSC_03_031_ASSOC_DIRECTORS_OFFICE | D122: {=TRANSPOSE(_xlfn._xlws.FILTER('Controllable Asset Registry'!$A$1331:$A$1454,IFERROR('Controllable Asset Registry'!$E$1331:$E$1454=C122,FALSE),"No Equipment in entity"))} -> No Equipment in entity
A123: GENERAL OFFICE AREA | B123: 3.032 | C123: entity:SSC_03_032_GENERAL_OFFICE_AREA | D123: {=TRANSPOSE(_xlfn._xlws.FILTER('Controllable Asset Registry'!$A$1331:$A$1454,IFERROR('Controllable Asset Registry'!$E$1331:$E$1454=C123,FALSE),"No Equipment in entity"))} -> No Equipment in entity
A124: PRINTING | B124: 3.033 | C124: entity:SSC_03_033_PRINTING | D124: {=TRANSPOSE(_xlfn._xlws.FILTER('Controllable Asset Registry'!$A$1331:$A$1454,IFERROR('Controllable Asset Registry'!$E$1331:$E$1454=C124,FALSE),"No Equipment in entity"))} -> FCU0011
A125: STAIR-2 | B125: 03.ST-2 | C125: entity:SSC_03_ST-2_STAIR-2 | D125: {=TRANSPOSE(_xlfn._xlws.FILTER('Controllable Asset Registry'!$A$1331:$A$1454,IFERROR('Controllable Asset Registry'!$E$1331:$E$1454=C125,FALSE),"No Equipment in entity"))} -> No Equipment in entity
A126: STORAGE | B126: 3.046 | C126: entity:SSC_03_046_STORAGE | D126: {=TRANSPOSE(_xlfn._xlws.FILTER('Controllable Asset Registry'!$A$1331:$A$1454,IFERROR('Controllable Asset Registry'!$E$1331:$E$1454=C126,FALSE),"No Equipment in entity"))} -> No Equipment in entity
A127: JANITOR'S CLOSET | B127: 3.045 | C127: entity:SSC_03_045_JANITORS_CLOSET | D127: {=TRANSPOSE(_xlfn._xlws.FILTER('Controllable Asset Registry'!$A$1331:$A$1454,IFERROR('Controllable Asset Registry'!$E$1331:$E$1454=C127,FALSE),"No Equipment in entity"))} -> No Equipment in entity
...

Sheet HQ Room Names with Equip.
A1: Room Entity Name | B1: Room Number Used | C1: Room Space (cleaned) | N1: Equipment Match Audit
A2: entity:HQ_B1.606_SECURE_STORAGE | B2: B1.606 | C2: SECURE_STORAGE | D2: {=TRANSPOSE(_xlfn._xlws.FILTER('Controllable Asset Registry'!$A$4:$A$777,IFERROR('Controllable Asset Registry'!$E$4:$E$777=A2,FALSE),"No Equipment in entity"))} -> No Equipment in entity | N2: Rooms listed (col A) | O2: =COUNTA(A2:A1042) -> 1040
A3: entity:HQ_B1.001_AHU_4 | B3: B1.001 | C3: AHU_4 | D3: {=TRANSPOSE(_xlfn._xlws.FILTER('Controllable Asset Registry'!$A$4:$A$777,IFERROR('Controllable Asset Registry'!$E$4:$E$777=A3,FALSE),"No Equipment in entity"))} -> AHUB_0001 | E3: AHUB_0002 | F3: AHUB_0008 | N3: Equipment names returned | O3: =COUNTA(D2:L1042)-COUNTIF(D2:L1042,"No Equipment in entity") -> 772
A4: entity:HQ_B1.002_SECURITY_UPS_ROOM | B4: B1.002 | C4: SECURITY_UPS_ROOM | D4: {=TRANSPOSE(_xlfn._xlws.FILTER('Controllable Asset Registry'!$A$4:$A$777,IFERROR('Controllable Asset Registry'!$E$4:$E$777=A4,FALSE),"No Equipment in entity"))} -> No Equipment in entity | N4: Rooms with no equipment | O4: =COUNTIF(D2:L1042,"No Equipment in entity") -> 433
A5: entity:HQ_B1.003_CONTROL_ROOM | B5: B1.003 | C5: CONTROL_ROOM | D5: {=TRANSPOSE(_xlfn._xlws.FILTER('Controllable Asset Registry'!$A$4:$A$777,IFERROR('Controllable Asset Registry'!$E$4:$E$777=A5,FALSE),"No Equipment in entity"))} -> FCU0002 | N5: Equipment in source register | O5: =COUNTA('Controllable Asset Registry'!A4:A777) -> 774
A6: entity:HQ_B1.005_MDF_1_ROOM | B6: B1.005 | C6: MDF_1_ROOM | D6: {=TRANSPOSE(_xlfn._xlws.FILTER('Controllable Asset Registry'!$A$4:$A$777,IFERROR('Controllable Asset Registry'!$E$4:$E$777=A6,FALSE),"No Equipment in entity"))} -> No Equipment in entity | N6: Distinct equipment returned | O6: {=SUM(--(_xlfn.UNIQUE(_xlfn.TOCOL(D2:L1042,3))<>"No Equipment in entity"))} -> 772
A7: entity:HQ_B1.006_AHU_1 | B7: B1.006 | C7: AHU_1 | D7: {=TRANSPOSE(_xlfn._xlws.FILTER('Controllable Asset Registry'!$A$4:$A$777,IFERROR('Controllable Asset Registry'!$E$4:$E$777=A7,FALSE),"No Equipment in entity"))} -> AHUB_0003 | E7: AHUB_0004 | N7: Duplicate room entries (col A) | O7: {=SUMPRODUCT((A2:A1042<>"")*(COUNTIF(A2:A1042,A2:A1042)>1))} -> 0
A8: entity:HQ_B1.007_COOLING_EQUIPMENT | B8: B1.007 | C8: COOLING_EQUIPMENT | D8: {=TRANSPOSE(_xlfn._xlws.FILTER('Controllable Asset Registry'!$A$4:$A$777,IFERROR('Controllable Asset Registry'!$E$4:$E$777=A8,FALSE),"No Equipment in entity"))} -> No Equipment in entity | N8: Duplicated equipment returns (D:L) | O8: {=SUMPRODUCT((D2:L1042<>"")*(D2:L1042<>"No Equipment in entity")*(COUNTIF(D2:L1042,D2:L1042)>1))} -> 0
A9: entity:HQ_B1.008_FM_STORAGE | B9: B1.008 | C9: FM_STORAGE | D9: {=TRANSPOSE(_xlfn._xlws.FILTER('Controllable Asset Registry'!$A$4:$A$777,IFERROR('Controllable Asset Registry'!$E$4:$E$777=A9,FALSE),"No Equipment in entity"))} -> No Equipment in entity | N9: Unplaced (in register, not on a room) | O9: =O5-O6 -> 2
A10: entity:HQ_B1.009_MV_SWITCH_ROOM | B10: B1.009 | C10: MV_SWITCH_ROOM | D10: {=TRANSPOSE(_xlfn._xlws.FILTER('Controllable Asset Registry'!$A$4:$A$777,IFERROR('Controllable Asset Registry'!$E$4:$E$777=A10,FALSE),"No Equipment in entity"))} -> No Equipment in entity
A11: entity:HQ_B1.010_TRANSFORMER_SUBSTATION | B11: B1.010 | C11: TRANSFORMER_SUBSTATION | D11: {=TRANSPOSE(_xlfn._xlws.FILTER('Controllable Asset Registry'!$A$4:$A$777,IFERROR('Controllable Asset Registry'!$E$4:$E$777=A11,FALSE),"No Equipment in entity"))} -> No Equipment in entity
A12: entity:HQ_B1.011_HV_INTAKE | B12: B1.011 | C12: HV_INTAKE | D12: {=TRANSPOSE(_xlfn._xlws.FILTER('Controllable Asset Registry'!$A$4:$A$777,IFERROR('Controllable Asset Registry'!$E$4:$E$777=A12,FALSE),"No Equipment in entity"))} -> No Equipment in entity
A13: entity:HQ_B1.012_GENERATOR | B13: B1.012 | C13: GENERATOR | D13: {=TRANSPOSE(_xlfn._xlws.FILTER('Controllable Asset Registry'!$A$4:$A$777,IFERROR('Controllable Asset Registry'!$E$4:$E$777=A13,FALSE),"No Equipment in entity"))} -> No Equipment in entity
A14: entity:HQ_B1.013_Q-TEL_INCOMING | B14: B1.013 | C14: Q-TEL_INCOMING | D14: {=TRANSPOSE(_xlfn._xlws.FILTER('Controllable Asset Registry'!$A$4:$A$777,IFERROR('Controllable Asset Registry'!$E$4:$E$777=A14,FALSE),"No Equipment in entity"))} -> No Equipment in entity
A15: entity:HQ_B1.014_SUPPORT_SPACE_DRY_WASTE_STORAGE | B15: B1.014 | C15: SUPPORT_SPACE_DRY_WASTE_STORAGE | D15: {=TRANSPOSE(_xlfn._xlws.FILTER('Controllable Asset Registry'!$A$4:$A$777,IFERROR('Controllable Asset Registry'!$E$4:$E$777=A15,FALSE),"No Equipment in entity"))} -> FCU0008 | E15: FCU0009
A16: entity:HQ_B1.015_SUPPORT_SPACE_LOADING | B16: B1.015 | C16: SUPPORT_SPACE_LOADING | D16: {=TRANSPOSE(_xlfn._xlws.FILTER('Controllable Asset Registry'!$A$4:$A$777,IFERROR('Controllable Asset Registry'!$E$4:$E$777=A16,FALSE),"No Equipment in entity"))} -> FCU0010
A17: entity:HQ_B1.016_AHU_2 | B17: B1.016 | C17: AHU_2 | D17: {=TRANSPOSE(_xlfn._xlws.FILTER('Controllable Asset Registry'!$A$4:$A$777,IFERROR('Controllable Asset Registry'!$E$4:$E$777=A17,FALSE),"No Equipment in entity"))} -> AHUB_0005 | E17: AHUB_0006
A18: entity:HQ_B1.017_WATER_SERVICES | B18: B1.017 | C18: WATER_SERVICES | D18: {=TRANSPOSE(_xlfn._xlws.FILTER('Controllable Asset Registry'!$A$4:$A$777,IFERROR('Controllable Asset Registry'!$E$4:$E$777=A18,FALSE),"No Equipment in entity"))} -> No Equipment in entity
A19: entity:HQ_B1.018_PA_ROOM | B19: B1.018 | C19: PA_ROOM | D19: {=TRANSPOSE(_xlfn._xlws.FILTER('Controllable Asset Registry'!$A$4:$A$777,IFERROR('Controllable Asset Registry'!$E$4:$E$777=A19,FALSE),"No Equipment in entity"))} -> No Equipment in entity
A20: entity:HQ_B1.019_AHU | B20: B1.019 | C20: AHU | D20: {=TRANSPOSE(_xlfn._xlws.FILTER('Controllable Asset Registry'!$A$4:$A$777,IFERROR('Controllable Asset Registry'!$E$4:$E$777=A20,FALSE),"No Equipment in entity"))} -> AHUB_0009 | E20: AHUB_0010 | F20: AHUB_0011
A21: entity:HQ_B1.020_CHILLED_WATER | B21: B1.020 | C21: CHILLED_WATER | D21: {=TRANSPOSE(_xlfn._xlws.FILTER('Controllable Asset Registry'!$A$4:$A$777,IFERROR('Controllable Asset Registry'!$E$4:$E$777=A21,FALSE),"No Equipment in entity"))} -> No Equipment in entity
A22: entity:HQ_B1.021_FILING_STORAGE | B22: B1.021 | C22: FILING_STORAGE | D22: {=TRANSPOSE(_xlfn._xlws.FILTER('Controllable Asset Registry'!$A$4:$A$777,IFERROR('Controllable Asset Registry'!$E$4:$E$777=A22,FALSE),"No Equipment in entity"))} -> No Equipment in entity
A23: entity:HQ_B1.022_AHU_3 | B23: B1.022 | C23: AHU_3 | D23: {=TRANSPOSE(_xlfn._xlws.FILTER('Controllable Asset Registry'!$A$4:$A$777,IFERROR('Controllable Asset Registry'!$E$4:$E$777=A23,FALSE),"No Equipment in entity"))} -> AHUB_0007
A24: entity:HQ_B1.023_CBS_ROOM | B24: B1.023 | C24: CBS_ROOM | D24: {=TRANSPOSE(_xlfn._xlws.FILTER('Controllable Asset Registry'!$A$4:$A$777,IFERROR('Controllable Asset Registry'!$E$4:$E$777=A24,FALSE),"No Equipment in entity"))} -> No Equipment in entity
A25: entity:HQ_B1.024_SUPPORT_SPACE_WASTE_BIN_WASH_UP_AREA | B25: B1.024 | C25: SUPPORT_SPACE_WASTE_BIN_WASH_UP_AREA | D25: {=TRANSPOSE(_xlfn._xlws.FILTER('Controllable Asset Registry'!$A$4:$A$777,IFERROR('Controllable Asset Registry'!$E$4:$E$777=A25,FALSE),"No Equipment in entity"))} -> No Equipment in entity
A26: entity:HQ_B1.025_COOLING_EQUIPMENT_ROOM | B26: B1.025 | C26: COOLING_EQUIPMENT_ROOM | D26: {=TRANSPOSE(_xlfn._xlws.FILTER('Controllable Asset Registry'!$A$4:$A$777,IFERROR('Controllable Asset Registry'!$E$4:$E$777=A26,FALSE),"No Equipment in entity"))} -> No Equipment in entity
A27: entity:HQ_B1.026_UPS_ROOM | B27: B1.026 | C27: UPS_ROOM | D27: {=TRANSPOSE(_xlfn._xlws.FILTER('Controllable Asset Registry'!$A$4:$A$777,IFERROR('Controllable Asset Registry'!$E$4:$E$777=A27,FALSE),"No Equipment in entity"))} -> No Equipment in entity
A28: entity:HQ_B1.101_AUDITORIUM_BACKSTAGE | B28: B1.101 | C28: AUDITORIUM_BACKSTAGE | D28: {=TRANSPOSE(_xlfn._xlws.FILTER('Controllable Asset Registry'!$A$4:$A$777,IFERROR('Controllable Asset Registry'!$E$4:$E$777=A28,FALSE),"No Equipment in entity"))} -> No Equipment in entity
A29: entity:HQ_B1.102_SERVER_ROOM | B29: B1.102 | C29: SERVER_ROOM | D29: {=TRANSPOSE(_xlfn._xlws.FILTER('Controllable Asset Registry'!$A$4:$A$777,IFERROR('Controllable Asset Registry'!$E$4:$E$777=A29,FALSE),"No Equipment in entity"))} -> No Equipment in entity
A30: entity:HQ_B1.103_STAFF_LOBBY | B30: B1.103 | C30: STAFF_LOBBY | D30: {=TRANSPOSE(_xlfn._xlws.FILTER('Controllable Asset Registry'!$A$4:$A$777,IFERROR('Controllable Asset Registry'!$E$4:$E$777=A30,FALSE),"No Equipment in entity"))} -> VAV0002 | E30: VAV0003
A31: entity:HQ_B1.106_VVIP_PARKING_6_CAR_SPOTS | B31: B1.106 | C31: VVIP_PARKING_6_CAR_SPOTS | D31: {=TRANSPOSE(_xlfn._xlws.FILTER('Controllable Asset Registry'!$A$4:$A$777,IFERROR('Controllable Asset Registry'!$E$4:$E$777=A31,FALSE),"No Equipment in entity"))} -> No Equipment in entity
A32: entity:HQ_B1.107_DOCK_MASTER_OFFICE | B32: B1.107 | C32: DOCK_MASTER_OFFICE | D32: {=TRANSPOSE(_xlfn._xlws.FILTER('Controllable Asset Registry'!$A$4:$A$777,IFERROR('Controllable Asset Registry'!$E$4:$E$777=A32,FALSE),"No Equipment in entity"))} -> FCU0003
A33: entity:HQ_B1.108_SUPPORT_SPACE_WET_WASTE_STORAGE | B33: B1.108 | C33: SUPPORT_SPACE_WET_WASTE_STORAGE | D33: {=TRANSPOSE(_xlfn._xlws.FILTER('Controllable Asset Registry'!$A$4:$A$777,IFERROR('Controllable Asset Registry'!$E$4:$E$777=A33,FALSE),"No Equipment in entity"))} -> No Equipment in entity
A34: entity:HQ_B1.110_SUPPORT_SPACE_MAIL_ROOM | B34: B1.110 | C34: SUPPORT_SPACE_MAIL_ROOM | D34: {=TRANSPOSE(_xlfn._xlws.FILTER('Controllable Asset Registry'!$A$4:$A$777,IFERROR('Controllable Asset Registry'!$E$4:$E$777=A34,FALSE),"No Equipment in entity"))} -> VAV0004
A35: entity:HQ_B1.111_CHANGING_ROOM | B35: B1.111 | C35: CHANGING_ROOM | D35: {=TRANSPOSE(_xlfn._xlws.FILTER('Controllable Asset Registry'!$A$4:$A$777,IFERROR('Controllable Asset Registry'!$E$4:$E$777=A35,FALSE),"No Equipment in entity"))} -> No Equipment in entity
A36: entity:HQ_B1.112_CHANGING_ROOM | B36: B1.112 | C36: CHANGING_ROOM | D36: {=TRANSPOSE(_xlfn._xlws.FILTER('Controllable Asset Registry'!$A$4:$A$777,IFERROR('Controllable Asset Registry'!$E$4:$E$777=A36,FALSE),"No Equipment in entity"))} -> No Equipment in entity
A37: entity:HQ_B1.113_SHEIKHA_LOBBY_SECURITY_ROOM | B37: B1.113 | C37: SHEIKHA_LOBBY_SECURITY_ROOM | D37: {=TRANSPOSE(_xlfn._xlws.FILTER('Controllable Asset Registry'!$A$4:$A$777,IFERROR('Controllable Asset Registry'!$E$4:$E$777=A37,FALSE),"No Equipment in entity"))} -> FCU0004
A38: entity:HQ_B1.114_FILING_STORAGE | B38: B1.114 | C38: FILING_STORAGE | D38: {=TRANSPOSE(_xlfn._xlws.FILTER('Controllable Asset Registry'!$A$4:$A$777,IFERROR('Controllable Asset Registry'!$E$4:$E$777=A38,FALSE),"No Equipment in entity"))} -> No Equipment in entity
A39: entity:HQ_B1.115_VVIP_PARKING_4_CAR_SPOTS | B39: B1.115 | C39: VVIP_PARKING_4_CAR_SPOTS | D39: {=TRANSPOSE(_xlfn._xlws.FILTER('Controllable Asset Registry'!$A$4:$A$777,IFERROR('Controllable Asset Registry'!$E$4:$E$777=A39,FALSE),"No Equipment in entity"))} -> No Equipment in entity
A40: entity:HQ_B1.116_SHEIKHA_LOBBY | B40: B1.116 | C40: SHEIKHA_LOBBY | D40: {=TRANSPOSE(_xlfn._xlws.FILTER('Controllable Asset Registry'!$A$4:$A$777,IFERROR('Controllable Asset Registry'!$E$4:$E$777=A40,FALSE),"No Equipment in entity"))} -> VAV0005 | E40: VAV0006
A41: entity:HQ_B1.117_CHAUFFEUR_ROOM | B41: B1.117 | C41: CHAUFFEUR_ROOM | D41: {=TRANSPOSE(_xlfn._xlws.FILTER('Controllable Asset Registry'!$A$4:$A$777,IFERROR('Controllable Asset Registry'!$E$4:$E$777=A41,FALSE),"No Equipment in entity"))} -> FCU0011
A42: entity:HQ_B1.118_SHEIKHA_LOBBY_PANTRYRG_LOUNGE | B42: B1.118 | C42: SHEIKHA_LOBBY_PANTRYRG_LOUNGE | D42: {=TRANSPOSE(_xlfn._xlws.FILTER('Controllable Asset Registry'!$A$4:$A$777,IFERROR('Controllable Asset Registry'!$E$4:$E$777=A42,FALSE),"No Equipment in entity"))} -> No Equipment in entity
A43: entity:HQ_B1.119_ELECTRICAL_CABINET | B43: B1.119 | C43: ELECTRICAL_CABINET | D43: {=TRANSPOSE(_xlfn._xlws.FILTER('Controllable Asset Registry'!$A$4:$A$777,IFERROR('Controllable Asset Registry'!$E$4:$E$777=A43,FALSE),"No Equipment in entity"))} -> No Equipment in entity
A44: entity:HQ_B1.120_MDF_2_ROOM | B44: B1.120 | C44: MDF_2_ROOM | D44: {=TRANSPOSE(_xlfn._xlws.FILTER('Controllable Asset Registry'!$A$4:$A$777,IFERROR('Controllable Asset Registry'!$E$4:$E$777=A44,FALSE),"No Equipment in entity"))} -> No Equipment in entity
A45: entity:HQ_B1.121_MAINTENANCE_ROOM | B45: B1.121 | C45: MAINTENANCE_ROOM | D45: {=TRANSPOSE(_xlfn._xlws.FILTER('Controllable Asset Registry'!$A$4:$A$777,IFERROR('Controllable Asset Registry'!$E$4:$E$777=A45,FALSE),"No Equipment in entity"))} -> No Equipment in entity
A46: entity:HQ_B1.122_SUPPORT_SPACE_FOOD_STORAGE | B46: B1.122 | C46: SUPPORT_SPACE_FOOD_STORAGE | D46: {=TRANSPOSE(_xlfn._xlws.FILTER('Controllable Asset Registry'!$A$4:$A$777,IFERROR('Controllable Asset Registry'!$E$4:$E$777=A46,FALSE),"No Equipment in entity"))} -> FCU0006
A47: entity:HQ_B1.123_SUPPORT_SPACE_FOOD_STORAGE | B47: B1.123 | C47: SUPPORT_SPACE_FOOD_STORAGE | D47: {=TRANSPOSE(_xlfn._xlws.FILTER('Controllable Asset Registry'!$A$4:$A$777,IFERROR('Controllable Asset Registry'!$E$4:$E$777=A47,FALSE),"No Equipment in entity"))} -> FCU0007
A48: entity:HQ_B1.401_MALE_TOILET | B48: B1.401 | C48: MALE_TOILET | D48: {=TRANSPOSE(_xlfn._xlws.FILTER('Controllable Asset Registry'!$A$4:$A$777,IFERROR('Controllable Asset Registry'!$E$4:$E$777=A48,FALSE),"No Equipment in entity"))} -> FCU0005
A49: entity:HQ_B1.402_FEMALE_TOILET | B49: B1.402 | C49: FEMALE_TOILET | D49: {=TRANSPOSE(_xlfn._xlws.FILTER('Controllable Asset Registry'!$A$4:$A$777,IFERROR('Controllable Asset Registry'!$E$4:$E$777=A49,FALSE),"No Equipment in entity"))} -> No Equipment in entity
A50: entity:HQ_B1.403_TOILET | B50: B1.403 | C50: TOILET | D50: {=TRANSPOSE(_xlfn._xlws.FILTER('Controllable Asset Registry'!$A$4:$A$777,IFERROR('Controllable Asset Registry'!$E$4:$E$777=A50,FALSE),"No Equipment in entity"))} -> No Equipment in entity
A51: entity:HQ_B1.511_VESTIBULE | B51: B1.511 | C51: VESTIBULE | D51: {=TRANSPOSE(_xlfn._xlws.FILTER('Controllable Asset Registry'!$A$4:$A$777,IFERROR('Controllable Asset Registry'!$E$4:$E$777=A51,FALSE),"No Equipment in entity"))} -> No Equipment in entity
A52: entity:HQ_B1.512_IDF_ROOM | B52: B1.512 | C52: IDF_ROOM | D52: {=TRANSPOSE(_xlfn._xlws.FILTER('Controllable Asset Registry'!$A$4:$A$777,IFERROR('Controllable Asset Registry'!$E$4:$E$777=A52,FALSE),"No Equipment in entity"))} -> FCU0001
... A98: entity:HQ_G.028_PR_&_MARKET_DIRECTOR_ENSUIT | B98: G.028 | C98: PR_&_MARKET_DIRECTOR_ENSUIT | D98: {=TRANSPOSE(_xlfn._xlws.FILTER('Controllable Asset Registry'!$A$4:$A$777,IFERROR('Controllable Asset Registry'!$E$4:$E$777=A98,FALSE),"No Equipment in entity"))} -> VAV0042
A99: entity:HQ_G.029_PR_&_MARKET_STAFF | B99: G.029 | C99: PR_&_MARKET_STAFF | D99: {=TRANSPOSE(_xlfn._xlws.FILTER('Controllable Asset Registry'!$A$4:$A$777,IFERROR('Controllable Asset Registry'!$E$4:$E$777=A99,FALSE),"No Equipment in entity"))} -> VAV0040 | E99: VAV0041
A100: entity:HQ_G.03_PR_&_MARKET_STAFF | B100: G.03 | C100: PR_&_MARKET_STAFF | D100: {=TRANSPOSE(_xlfn._xlws.FILTER('Controllable Asset Registry'!$A$4:$A$777,IFERROR('Controllable Asset Registry'!$E$4:$E$777=A100,FALSE),"No Equipment in entity"))} -> No Equipment in entity
A101: entity:HQ_G.031_PR_&_MARKET_STAFF | B101: G.031 | C101: PR_&_MARKET_STAFF | D101: {=TRANSPOSE(_xlfn._xlws.FILTER('Controllable Asset Registry'!$A$4:$A$777,IFERROR('Controllable Asset Registry'!$E$4:$E$777=A101,FALSE),"No Equipment in entity"))} -> FCU0015
A102: entity:HQ_G.032_PR_&_MARKET_STAFF | B102: G.032 | C102: PR_&_MARKET_STAFF | D102: {=TRANSPOSE(_xlfn._xlws.FILTER('Controllable Asset Registry'!$A$4:$A$777,IFERROR('Controllable Asset Registry'!$E$4:$E$777=A102,FALSE),"No Equipment in entity"))} -> VAV0038
A103: entity:HQ_G.033_PR_&_MARKET_STAFF | B103: G.033 | C103: PR_&_MARKET_STAFF | D103: {=TRANSPOSE(_xlfn._xlws.FILTER('Controllable Asset Registry'!$A$4:$A$777,IFERROR('Controllable Asset Registry'!$E$4:$E$777=A103,FALSE),"No Equipment in entity"))} -> VAV0037
A104: entity:HQ_G.034_PR_&_MARKET_STAFF | B104: G.034 | C104: PR_&_MARKET_STAFF | D104: {=TRANSPOSE(_xlfn._xlws.FILTER('Controllable Asset Registry'!$A$4:$A$777,IFERROR('Controllable Asset Registry'!$E$4:$E$777=A104,FALSE),"No Equipment in entity"))} -> VAV0036
A105: entity:HQ_G.035_PR_&_MARKET_STAFF | B105: G.035 | C105: PR_&_MARKET_STAFF | D105: {=TRANSPOSE(_xlfn._xlws.FILTER('Controllable Asset Registry'!$A$4:$A$777,IFERROR('Controllable Asset Registry'!$E$4:$E$777=A105,FALSE),"No Equipment in entity"))} -> VAV0035
A106: entity:HQ_G.036_PR_&_MARKET_STAFF | B106: G.036 | C106: PR_&_MARKET_STAFF | D106: {=TRANSPOSE(_xlfn._xlws.FILTER('Controllable Asset Registry'!$A$4:$A$777,IFERROR('Controllable Asset Registry'!$E$4:$E$777=A106,FALSE),"No Equipment in entity"))} -> VAV0034
A107: entity:HQ_G.037_PR_&_MARKET_STAFF | B107: G.037 | C107: PR_&_MARKET_STAFF | D107: {=TRANSPOSE(_xlfn._xlws.FILTER('Controllable Asset Registry'!$A$4:$A$777,IFERROR('Controllable Asset Registry'!$E$4:$E$777=A107,FALSE),"No Equipment in entity"))} -> VAV0033
A108: entity:HQ_G.038_PR_&_MARKET_STAFF | B108: G.038 | C108: PR_&_MARKET_STAFF | D108: {=TRANSPOSE(_xlfn._xlws.FILTER('Controllable Asset Registry'!$A$4:$A$777,IFERROR('Controllable Asset Registry'!$E$4:$E$777=A108,FALSE),"No Equipment in entity"))} -> VAV0032
A109: entity:HQ_G.039_PR_&_MARKET_STAFF | B109: G.039 | C109: PR_&_MARKET_STAFF | D109: {=TRANSPOSE(_xlfn._xlws.FILTER('Controllable Asset Registry'!$A$4:$A$777,IFERROR('Controllable Asset Registry'!$E$4:$E$777=A109,FALSE),"No Equipment in entity"))} -> No Equipment in entity
A110: entity:HQ_G.101_CONFERENCE_ROOM | B110: G.101 | C110: CONFERENCE_ROOM | D110: {=TRANSPOSE(_xlfn._xlws.FILTER('Controllable Asset Registry'!$A$4:$A$777,IFERROR('Controllable Asset Registry'!$E$4:$E$777=A110,FALSE),"No Equipment in entity"))} -> VAV0048 | E110: VAV0049 | F110: VAV0050 | G110: VAV0051
A111: entity:HQ_G.102_AUDITORIUM | B111: G.102 | C111: AUDITORIUM | D111: {=TRANSPOSE(_xlfn._xlws.FILTER('Controllable Asset Registry'!$A$4:$A$777,IFERROR('Controllable Asset Registry'!$E$4:$E$777=A111,FALSE),"No Equipment in entity"))} -> No Equipment in entity
A112: entity:HQ_G.103_BMS | B112: G.103 | C112: BMS | D112: {=TRANSPOSE(_xlfn._xlws.FILTER('Controllable Asset Registry'!$A$4:$A$777,IFERROR('Controllable Asset Registry'!$E$4:$E$777=A112,FALSE),"No Equipment in entity"))} -> VAV0026
A113: entity:HQ_G.104_LOBBY | B113: G.104 | C113: LOBBY | D113: {=TRANSPOSE(_xlfn._xlws.FILTER('Controllable Asset Registry'!$A$4:$A$777,IFERROR('Controllable Asset Registry'!$E$4:$E$777=A113,FALSE),"No Equipment in entity"))} -> VAV0024 | E113: VAV0025 | F113: VAV0103 | G113: VAV0104 | H113: VAV0105 | I113: VAV0106
A114: entity:HQ_G.105_SHOP | B114: G.105 | C114: SHOP | D114: {=TRANSPOSE(_xlfn._xlws.FILTER('Controllable Asset Registry'!$A$4:$A$777,IFERROR('Controllable Asset Registry'!$E$4:$E$777=A114,FALSE),"No Equipment in entity"))} -> VAV0023
A115: entity:HQ_G.106_STORAGE_ROOM | B115: G.106 | C115: STORAGE_ROOM | D115: {=TRANSPOSE(_xlfn._xlws.FILTER('Controllable Asset Registry'!$A$4:$A$777,IFERROR('Controllable Asset Registry'!$E$4:$E$777=A115,FALSE),"No Equipment in entity"))} -> No Equipment in entity
A116: entity:HQ_G.107_E-TOWER_LOBBY | B116: G.107 | C116: E-TOWER_LOBBY | D116: {=TRANSPOSE(_xlfn._xlws.FILTER('Controllable Asset Registry'!$A$4:$A$777,IFERROR('Controllable Asset Registry'!$E$4:$E$777=A116,FALSE),"No Equipment in entity"))} -> VAV0045
A117: entity:HQ_G.108_CONSULTANT_SPACE_TRAINEES | B117: G.108 | C117: CONSULTANT_SPACE_TRAINEES | D117: {=TRANSPOSE(_xlfn._xlws.FILTER('Controllable Asset Registry'!$A$4:$A$777,IFERROR('Controllable Asset Registry'!$E$4:$E$777=A117,FALSE),"No Equipment in entity"))} -> VAV0052 | E117: VAV0053
A118: entity:HQ_G.11_STORAGE_ROOM | B118: G.11 | C118: STORAGE_ROOM | D118: {=TRANSPOSE(_xlfn._xlws.FILTER('Controllable Asset Registry'!$A$4:$A$777,IFERROR('Controllable Asset Registry'!$E$4:$E$777=A118,FALSE),"No Equipment in entity"))} -> No Equipment in entity
A119: entity:HQ_G.401_FEMALE_TOILET | B119: G.401 | C119: FEMALE_TOILET | D119: {=TRANSPOSE(_xlfn._xlws.FILTER('Controllable Asset Registry'!$A$4:$A$777,IFERROR('Controllable Asset Registry'!$E$4:$E$777=A119,FALSE),"No Equipment in entity"))} -> No Equipment in entity
A120: entity:HQ_G.402_MALE_TOILET | B120: G.402 | C120: MALE_TOILET | D120: {=TRANSPOSE(_xlfn._xlws.FILTER('Controllable Asset Registry'!$A$4:$A$777,IFERROR('Controllable Asset Registry'!$E$4:$E$777=A120,FALSE),"No Equipment in entity"))} -> No Equipment in entity
A121: entity:HQ_G.403_FEM_FEMALE_TOILET | B121: G.403_FEM | C121: FEMALE_TOILET | D121: {=TRANSPOSE(_xlfn._xlws.FILTER('Controllable Asset Registry'!$A$4:$A$777,IFERROR('Controllable Asset Registry'!$E$4:$E$777=A121,FALSE),"No Equipment in entity"))} -> No Equipment in entity
A122: entity:HQ_G.403_MAL_MALE_TOILET | B122: G.403_MAL | C122: MALE_TOILET | D122: {=TRANSPOSE(_xlfn._xlws.FILTER('Controllable Asset Registry'!$A$4:$A$777,IFERROR('Controllable Asset Registry'!$E$4:$E$777=A122,FALSE),"No Equipment in entity"))} -> No Equipment in entity
A123: entity:HQ_G.405_TOILET | B123: G.405 | C123: TOILET | D123: {=TRANSPOSE(_xlfn._xlws.FILTER('Controllable Asset Registry'!$A$4:$A$777,IFERROR('Controllable Asset Registry'!$E$4:$E$777=A123,FALSE),"No Equipment in entity"))} -> VAV0608
A124: entity:HQ_G.511_VESTIBULE | B124: G.511 | C124: VESTIBULE | D124: {=TRANSPOSE(_xlfn._xlws.FILTER('Controllable Asset Registry'!$A$4:$A$777,IFERROR('Controllable Asset Registry'!$E$4:$E$777=A124,FALSE),"No Equipment in entity"))} -> FCU0018
A125: entity:HQ_G.512_IDF_ROOM | B125: G.512 | C125: IDF_ROOM | D125: {=TRANSPOSE(_xlfn._xlws.FILTER('Controllable Asset Registry'!$A$4:$A$777,IFERROR('Controllable Asset Registry'!$E$4:$E$777=A125,FALSE),"No Equipment in entity"))} -> FCU0014 | E125: FCU0111
A126: entity:HQ_G.521_STAIR_VESTIBULE | B126: G.521 | C126: STAIR_VESTIBULE | D126: {=TRANSPOSE(_xlfn._xlws.FILTER('Controllable Asset Registry'!$A$4:$A$777,IFERROR('Controllable Asset Registry'!$E$4:$E$777=A126,FALSE),"No Equipment in entity"))} -> No Equipment in entity
A127: entity:HQ_G.531_IDF_ROOM | B127: G.531 | C127: IDF_ROOM | D127: {=TRANSPOSE(_xlfn._xlws.FILTER('Controllable Asset Registry'!$A$4:$A$777,IFERROR('Controllable Asset Registry'!$E$4:$E$777=A127,FALSE),"No Equipment in entity"))} -> FCU0012 | E127: FCU0013
A128: entity:HQ_G.532_ELECTRICAL_CLOSET_1 | B128: G.532 | C128: ELECTRICAL_CLOSET_1 | D128: {=TRANSPOSE(_xlfn._xlws.FILTER('Controllable Asset Registry'!$A$4:$A$777,IFERROR('Controllable Asset Registry'!$E$4:$E$777=A128,FALSE),"No Equipment in entity"))} -> No Equipment in entity
A129: entity:HQ_G.533_ELECTRICAL_CLOSET_2 | B129: G.533 | C129: ELECTRICAL_CLOSET_2 | D129: {=TRANSPOSE(_xlfn._xlws.FILTER('Controllable Asset Registry'!$A$4:$A$777,IFERROR('Controllable Asset Registry'!$E$4:$E$777=A129,FALSE),"No Equipment in entity"))} -> No Equipment in entity
A130: entity:HQ_G.541_STAIR_VESTIBULES | B130: G.541 | C130: STAIR_VESTIBULES | D130: {=TRANSPOSE(_xlfn._xlws.FILTER('Controllable Asset Registry'!$A$4:$A$777,IFERROR('Controllable Asset Registry'!$E$4:$E$777=A130,FALSE),"No Equipment in entity"))} -> No Equipment in entity
A131: entity:HQ_G.542_STAIR_VESTIBULE | B131: G.542 | C131: STAIR_VESTIBULE | D131: {=TRANSPOSE(_xlfn._xlws.FILTER('Controllable Asset Registry'!$A$4:$A$777,IFERROR('Controllable Asset Registry'!$E$4:$E$777=A131,FALSE),"No Equipment in entity"))} -> No Equipment in entity
A132: entity:HQ_G.544_VESTIBULE | B132: G.544 | C132: VESTIBULE | D132: {=TRANSPOSE(_xlfn._xlws.FILTER('Controllable Asset Registry'!$A$4:$A$777,IFERROR('Controllable Asset Registry'!$E$4:$E$777=A132,FALSE),"No Equipment in entity"))} -> No Equipment in entity
A133: entity:HQ_G.601_CORRIDOR | B133: G.601 | C133: CORRIDOR | D133: {=TRANSPOSE(_xlfn._xlws.FILTER('Controllable Asset Registry'!$A$4:$A$777,IFERROR('Controllable Asset Registry'!$E$4:$E$777=A133,FALSE),"No Equipment in entity"))} -> VAV0021 | E133: VAV0022
A134: entity:HQ_G.FF-1_FF-1 | B134: G.FF-1 | C134: FF-1 | D134: {=TRANSPOSE(_xlfn._xlws.FILTER('Controllable Asset Registry'!$A$4:$A$777,IFERROR('Controllable Asset Registry'!$E$4:$E$777=A134,FALSE),"No Equipment in entity"))} -> No Equipment in entity
A135: entity:HQ_G.P-1_P-1 | B135: G.P-1 | C135: P-1 | D135: {=TRANSPOSE(_xlfn._xlws.FILTER('Controllable Asset Registry'!$A$4:$A$777,IFERROR('Controllable Asset Registry'!$E$4:$E$777=A135,FALSE),"No Equipment in entity"))} -> No Equipment in entity
A136: entity:HQ_G.P-2_P-2 | B136: G.P-2 | C136: P-2 | D136: {=TRANSPOSE(_xlfn._xlws.FILTER('Controllable Asset Registry'!$A$4:$A$777,IFERROR('Controllable Asset Registry'!$E$4:$E$777=A136,FALSE),"No Equipment in entity"))} -> No Equipment in entity
A137: entity:HQ_G.P-3_P-3 | B137: G.P-3 | C137: P-3 | D137: {=TRANSPOSE(_xlfn._xlws.FILTER('Controllable Asset Registry'!$A$4:$A$777,IFERROR('Controllable Asset Registry'!$E$4:$E$777=A137,FALSE),"No Equipment in entity"))} -> No Equipment in entity
A138: entity:HQ_G.P-4_P-4 | B138: G.P-4 | C138: P-4 | D138: {=TRANSPOSE(_xlfn._xlws.FILTER('Controllable Asset Registry'!$A$4:$A$777,IFERROR('Controllable Asset Registry'!$E$4:$E$777=A138,FALSE),"No Equipment in entity"))} -> No Equipment in entity
A139: entity:HQ_G.P-5_P-5 | B139: G.P-5 | C139: P-5 | D139: {=TRANSPOSE(_xlfn._xlws.FILTER('Controllable Asset Registry'!$A$4:$A$777,IFERROR('Controllable Asset Registry'!$E$4:$E$777=A139,FALSE),"No Equipment in entity"))} -> No Equipment in entity
A140: entity:HQ_G.P-6_P-6 | B140: G.P-6 | C140: P-6 | D140: {=TRANSPOSE(_xlfn._xlws.FILTER('Controllable Asset Registry'!$A$4:$A$777,IFERROR('Controllable Asset Registry'!$E$4:$E$777=A140,FALSE),"No Equipment in entity"))} -> No Equipment in entity
A141: entity:HQ_G.S-1_S-1 | B141: G.S-1 | C141: S-1 | D141: {=TRANSPOSE(_xlfn._xlws.FILTER('Controllable Asset Registry'!$A$4:$A$777,IFERROR('Controllable Asset Registry'!$E$4:$E$777=A141,FALSE),"No Equipment in entity"))} -> No Equipment in entity
A142: entity:HQ_G.ST-1_ST-1 | B142: G.ST-1 | C142: ST-1 | D142: {=TRANSPOSE(_xlfn._xlws.FILTER('Controllable Asset Registry'!$A$4:$A$777,IFERROR('Controllable Asset Registry'!$E$4:$E$777=A142,FALSE),"No Equipment in entity"))} -> No Equipment in entity
A143: entity:HQ_G.ST-2_ST-2 | B143: G.ST-2 | C143: ST-2 | D143: {=TRANSPOSE(_xlfn._xlws.FILTER('Controllable Asset Registry'!$A$4:$A$777,IFERROR('Controllable Asset Registry'!$E$4:$E$777=A143,FALSE),"No Equipment in entity"))} -> No Equipment in entity
A144: entity:HQ_G.ST-3_ST-3 | B144: G.ST-3 | C144: ST-3 | D144: {=TRANSPOSE(_xlfn._xlws.FILTER('Controllable Asset Registry'!$A$4:$A$777,IFERROR('Controllable Asset Registry'!$E$4:$E$777=A144,FALSE),"No Equipment in entity"))} -> No Equipment in entity
A145: entity:HQ_G.ST-4_ST-4 | B145: G.ST-4 | C145: ST-4 | D145: {=TRANSPOSE(_xlfn._xlws.FILTER('Controllable Asset Registry'!$A$4:$A$777,IFERROR('Controllable Asset Registry'!$E$4:$E$777=A145,FALSE),"No Equipment in entity"))} -> No Equipment in entity
...

Sheet QNL Room Names with Equip.
A1: Room Entity Name | B1: Room Number | C1: Room Name
A2: ="entity:QNL_"&B2&"_"&C2 -> entity:QNL_B_228_M1_HVAC_SHAFT | B2: B_228 | C2: M1_HVAC_SHAFT | D2: {=TRANSPOSE(_xlfn._xlws.FILTER('Controllable Asset Registry'!$A$779:$A$1329,IFERROR('Controllable Asset Registry'!$E$779:$E$1329=A2,FALSE),"No Equipment in entity"))} -> No Equipment in entity
A3: ="entity:QNL_"&B3&"_"&C3 -> entity:QNL_B_229_E1_ELEC_SHAFT | B3: B_229 | C3: E1_ELEC_SHAFT | D3: {=TRANSPOSE(_xlfn._xlws.FILTER('Controllable Asset Registry'!$A$779:$A$1329,IFERROR('Controllable Asset Registry'!$E$779:$E$1329=A3,FALSE),"No Equipment in entity"))} -> No Equipment in entity
A4: ="entity:QNL_"&B4&"_"&C4 -> entity:QNL_B_230_REFR_STORE | B4: B_230 | C4: REFR_STORE | D4: {=TRANSPOSE(_xlfn._xlws.FILTER('Controllable Asset Registry'!$A$779:$A$1329,IFERROR('Controllable Asset Registry'!$E$779:$E$1329=A4,FALSE),"No Equipment in entity"))} -> No Equipment in entity
A5: ="entity:QNL_"&B5&"_"&C5 -> entity:QNL_B_231_DISH_WASING | B5: B_231 | C5: DISH_WASING | D5: {=TRANSPOSE(_xlfn._xlws.FILTER('Controllable Asset Registry'!$A$779:$A$1329,IFERROR('Controllable Asset Registry'!$E$779:$E$1329=A5,FALSE),"No Equipment in entity"))} -> No Equipment in entity
A6: ="entity:QNL_"&B6&"_"&C6 -> entity:QNL_B_232_DRY_STORE | B6: B_232 | C6: DRY_STORE | D6: {=TRANSPOSE(_xlfn._xlws.FILTER('Controllable Asset Registry'!$A$779:$A$1329,IFERROR('Controllable Asset Registry'!$E$779:$E$1329=A6,FALSE),"No Equipment in entity"))} -> No Equipment in entity
A7: ="entity:QNL_"&B7&"_"&C7 -> entity:QNL_B_233_WC5_RISER | B7: B_233 | C7: WC5_RISER | D7: {=TRANSPOSE(_xlfn._xlws.FILTER('Controllable Asset Registry'!$A$779:$A$1329,IFERROR('Controllable Asset Registry'!$E$779:$E$1329=A7,FALSE),"No Equipment in entity"))} -> No Equipment in entity
A8: ="entity:QNL_"&B8&"_"&C8 -> entity:QNL_B_234_E3_ELEC_SHAFT | B8: B_234 | C8: E3_ELEC_SHAFT | D8: {=TRANSPOSE(_xlfn._xlws.FILTER('Controllable Asset Registry'!$A$779:$A$1329,IFERROR('Controllable Asset Registry'!$E$779:$E$1329=A8,FALSE),"No Equipment in entity"))} -> No Equipment in entity
A9: ="entity:QNL_"&B9&"_"&C9 -> entity:QNL_B_235_M2_HVAC_SHAFT_ABOVE | B9: B_235 | C9: M2_HVAC_SHAFT_ABOVE | D9: {=TRANSPOSE(_xlfn._xlws.FILTER('Controllable Asset Registry'!$A$779:$A$1329,IFERROR('Controllable Asset Registry'!$E$779:$E$1329=A9,FALSE),"No Equipment in entity"))} -> No Equipment in entity
A10: ="entity:QNL_"&B10&"_"&C10 -> entity:QNL_B_236_WC1_RISER | B10: B_236 | C10: WC1_RISER | D10: {=TRANSPOSE(_xlfn._xlws.FILTER('Controllable Asset Registry'!$A$779:$A$1329,IFERROR('Controllable Asset Registry'!$E$779:$E$1329=A10,FALSE),"No Equipment in entity"))} -> No Equipment in entity
A11: ="entity:QNL_"&B11&"_"&C11 -> entity:QNL_B_237_CORRIDOR | B11: B_237 | C11: CORRIDOR | D11: {=TRANSPOSE(_xlfn._xlws.FILTER('Controllable Asset Registry'!$A$779:$A$1329,IFERROR('Controllable Asset Registry'!$E$779:$E$1329=A11,FALSE),"No Equipment in entity"))} -> No Equipment in entity
A12: ="entity:QNL_"&B12&"_"&C12 -> entity:QNL_B_238_M3_HVAC_SHAFT | B12: B_238 | C12: M3_HVAC_SHAFT | D12: {=TRANSPOSE(_xlfn._xlws.FILTER('Controllable Asset Registry'!$A$779:$A$1329,IFERROR('Controllable Asset Registry'!$E$779:$E$1329=A12,FALSE),"No Equipment in entity"))} -> No Equipment in entity
A13: ="entity:QNL_"&B13&"_"&C13 -> entity:QNL_B_001_TECH_SERVICES_AND_COLLECTIONS_OFFICE | B13: B_001 | C13: TECH_SERVICES_AND_COLLECTIONS_OFFICE | D13: {=TRANSPOSE(_xlfn._xlws.FILTER('Controllable Asset Registry'!$A$779:$A$1329,IFERROR('Controllable Asset Registry'!$E$779:$E$1329=A13,FALSE),"No Equipment in entity"))} -> VAV_B_S11_003 | E13: VAV_B_S11_004 | F13: VAV_B_S11_005 | G13: VAV_B_S11_006 | H13: VAV_B_S11_007 | I13: VAV_B_S11_008 | J13: VAV_B_S11_009 | K13: VAV_B_S11_010 | L13: VAV_B_S11_013 | M13: VAV_B_S11_014 | N13: VAV_B_S11_015 | O13: VAV_B_S11_016 | P13: VAV_B_S11_017 | Q13: VAV_B_S11_018 | R13: VAV_B_S11_019 | S13: VAV_B_S11_020
A14: ="entity:QNL_"&B14&"_"&C14 -> entity:QNL_B_002_KITCHEN | B14: B_002 | C14: KITCHEN | D14: {=TRANSPOSE(_xlfn._xlws.FILTER('Controllable Asset Registry'!$A$779:$A$1329,IFERROR('Controllable Asset Registry'!$E$779:$E$1329=A14,FALSE),"No Equipment in entity"))} -> VAV_B_S11_024
A15: ="entity:QNL_"&B15&"_"&C15 -> entity:QNL_B_003_FINANCE_COORDINATOR_&_BUSINESS_SUPPORT_OFCR | B15: B_003 | C15: FINANCE_COORDINATOR_&_BUSINESS_SUPPORT_OFCR | D15: {=TRANSPOSE(_xlfn._xlws.FILTER('Controllable Asset Registry'!$A$779:$A$1329,IFERROR('Controllable Asset Registry'!$E$779:$E$1329=A15,FALSE),"No Equipment in entity"))} -> VAV_B_S11_026 | E15: VAV_B_S11_027
A16: ="entity:QNL_"&B16&"_"&C16 -> entity:QNL_B_004_ANALOG_RESOURCES | B16: B_004 | C16: ANALOG_RESOURCES | D16: {=TRANSPOSE(_xlfn._xlws.FILTER('Controllable Asset Registry'!$A$779:$A$1329,IFERROR('Controllable Asset Registry'!$E$779:$E$1329=A16,FALSE),"No Equipment in entity"))} -> VAV_B_S11_028
A17: ="entity:QNL_"&B17&"_"&C17 -> entity:QNL_B_005_DIGITAL_RESOURCES | B17: B_005 | C17: DIGITAL_RESOURCES | D17: {=TRANSPOSE(_xlfn._xlws.FILTER('Controllable Asset Registry'!$A$779:$A$1329,IFERROR('Controllable Asset Registry'!$E$779:$E$1329=A17,FALSE),"No Equipment in entity"))} -> VAV_B_S11_029
A18: ="entity:QNL_"&B18&"_"&C18 -> entity:QNL_B_006_BUDGET_&_PAYMENT_1 | B18: B_006 | C18: BUDGET_&_PAYMENT_1 | D18: {=TRANSPOSE(_xlfn._xlws.FILTER('Controllable Asset Registry'!$A$779:$A$1329,IFERROR('Controllable Asset Registry'!$E$779:$E$1329=A18,FALSE),"No Equipment in entity"))} -> VAV_B_S11_030
A19: ="entity:QNL_"&B19&"_"&C19 -> entity:QNL_B_007_BUDGET_&_PAYMENT_2 | B19: B_007 | C19: BUDGET_&_PAYMENT_2 | D19: {=TRANSPOSE(_xlfn._xlws.FILTER('Controllable Asset Registry'!$A$779:$A$1329,IFERROR('Controllable Asset Registry'!$E$779:$E$1329=A19,FALSE),"No Equipment in entity"))} -> VAV_B_S11_031
A20: ="entity:QNL_"&B20&"_"&C20 -> entity:QNL_B_008_RECEIVING_AREA | B20: B_008 | C20: RECEIVING_AREA | D20: {=TRANSPOSE(_xlfn._xlws.FILTER('Controllable Asset Registry'!$A$779:$A$1329,IFERROR('Controllable Asset Registry'!$E$779:$E$1329=A20,FALSE),"No Equipment in entity"))} -> VAV_B_S11_043 | E20: VAV_B_S11_044 | F20: VAV_B_S11_045 | G20: VAV_B_S11_046
A21: ="entity:QNL_"&B21&"_"&C21 -> entity:QNL_B_009_RECEPTION_&_LOUNGE | B21: B_009 | C21: RECEPTION_&_LOUNGE | D21: {=TRANSPOSE(_xlfn._xlws.FILTER('Controllable Asset Registry'!$A$779:$A$1329,IFERROR('Controllable Asset Registry'!$E$779:$E$1329=A21,FALSE),"No Equipment in entity"))} -> VAV_B_S11_021 | E21: VAV_B_S11_022 | F21: VAV_B_S11_023
A22: ="entity:QNL_"&B22&"_"&C22 -> entity:QNL_B_010_PATIO_GARDEN | B22: B_010 | C22: PATIO_GARDEN | D22: {=TRANSPOSE(_xlfn._xlws.FILTER('Controllable Asset Registry'!$A$779:$A$1329,IFERROR('Controllable Asset Registry'!$E$779:$E$1329=A22,FALSE),"No Equipment in entity"))} -> No Equipment in entity
A23: ="entity:QNL_"&B23&"_"&C23 -> entity:QNL_B_020_ENGINEERING | B23: B_020 | C23: ENGINEERING | D23: {=TRANSPOSE(_xlfn._xlws.FILTER('Controllable Asset Registry'!$A$779:$A$1329,IFERROR('Controllable Asset Registry'!$E$779:$E$1329=A23,FALSE),"No Equipment in entity"))} -> VAV_B_S11_034
A24: ="entity:QNL_"&B24&"_"&C24 -> entity:QNL_B_021_ARABIC_STUDIES | B24: B_021 | C24: ARABIC_STUDIES | D24: {=TRANSPOSE(_xlfn._xlws.FILTER('Controllable Asset Registry'!$A$779:$A$1329,IFERROR('Controllable Asset Registry'!$E$779:$E$1329=A24,FALSE),"No Equipment in entity"))} -> VAV_B_S11_035
A25: ="entity:QNL_"&B25&"_"&C25 -> entity:QNL_B_022_LICENSING_EXPERT | B25: B_022 | C25: LICENSING_EXPERT | D25: {=TRANSPOSE(_xlfn._xlws.FILTER('Controllable Asset Registry'!$A$779:$A$1329,IFERROR('Controllable Asset Registry'!$E$779:$E$1329=A25,FALSE),"No Equipment in entity"))} -> VAV_B_S11_036
A26: ="entity:QNL_"&B26&"_"&C26 -> entity:QNL_B_023_ARTS_&_HUMANITIES | B26: B_023 | C26: ARTS_&_HUMANITIES | D26: {=TRANSPOSE(_xlfn._xlws.FILTER('Controllable Asset Registry'!$A$779:$A$1329,IFERROR('Controllable Asset Registry'!$E$779:$E$1329=A26,FALSE),"No Equipment in entity"))} -> VAV_B_S11_037
A27: ="entity:QNL_"&B27&"_"&C27 -> entity:QNL_B_024_AD_COLLECTIONS | B27: B_024 | C27: AD_COLLECTIONS | D27: {=TRANSPOSE(_xlfn._xlws.FILTER('Controllable Asset Registry'!$A$779:$A$1329,IFERROR('Controllable Asset Registry'!$E$779:$E$1329=A27,FALSE),"No Equipment in entity"))} -> VAV_B_S11_032 | E27: VAV_B_S11_033
A28: ="entity:QNL_"&B28&"_"&C28 -> entity:QNL_B_025_SOCIAL_SCIENCES | B28: B_025 | C28: SOCIAL_SCIENCES | D28: {=TRANSPOSE(_xlfn._xlws.FILTER('Controllable Asset Registry'!$A$779:$A$1329,IFERROR('Controllable Asset Registry'!$E$779:$E$1329=A28,FALSE),"No Equipment in entity"))} -> VAV_B_S11_040
A29: ="entity:QNL_"&B29&"_"&C29 -> entity:QNL_B_026_BUSINESS_&_COMPUTING | B29: B_026 | C29: BUSINESS_&_COMPUTING | D29: {=TRANSPOSE(_xlfn._xlws.FILTER('Controllable Asset Registry'!$A$779:$A$1329,IFERROR('Controllable Asset Registry'!$E$779:$E$1329=A29,FALSE),"No Equipment in entity"))} -> VAV_B_S11_039
A30: ="entity:QNL_"&B30&"_"&C30 -> entity:QNL_B_027_PROCUREMENT_SPC_PROCUREMENT_OFCR | B30: B_027 | C30: PROCUREMENT_SPC_PROCUREMENT_OFCR | D30: {=TRANSPOSE(_xlfn._xlws.FILTER('Controllable Asset Registry'!$A$779:$A$1329,IFERROR('Controllable Asset Registry'!$E$779:$E$1329=A30,FALSE),"No Equipment in entity"))} -> VAV_B_S11_038
A31: ="entity:QNL_"&B31&"_"&C31 -> entity:QNL_B_028_STORAGE | B31: B_028 | C31: STORAGE | D31: {=TRANSPOSE(_xlfn._xlws.FILTER('Controllable Asset Registry'!$A$779:$A$1329,IFERROR('Controllable Asset Registry'!$E$779:$E$1329=A31,FALSE),"No Equipment in entity"))} -> VAV_B_S11_025
A32: ="entity:QNL_"&B32&"_"&C32 -> entity:QNL_B_029_LITERATURE_&_ANGUAGE | B32: B_029 | C32: LITERATURE_&_ANGUAGE | D32: {=TRANSPOSE(_xlfn._xlws.FILTER('Controllable Asset Registry'!$A$779:$A$1329,IFERROR('Controllable Asset Registry'!$E$779:$E$1329=A32,FALSE),"No Equipment in entity"))} -> VAV_B_S11_041
A33: ="entity:QNL_"&B33&"_"&C33 -> entity:QNL_B_030_SNR_P_COORDINATOR_&_P_COORDINATOR | B33: B_030 | C33: SNR_P_COORDINATOR_&_P_COORDINATOR | D33: {=TRANSPOSE(_xlfn._xlws.FILTER('Controllable Asset Registry'!$A$779:$A$1329,IFERROR('Controllable Asset Registry'!$E$779:$E$1329=A33,FALSE),"No Equipment in entity"))} -> VAV_B_S11_042
A34: ="entity:QNL_"&B34&"_"&C34 -> entity:QNL_B_031_JANITORS_ROOM | B34: B_031 | C34: JANITORS_ROOM | D34: {=TRANSPOSE(_xlfn._xlws.FILTER('Controllable Asset Registry'!$A$779:$A$1329,IFERROR('Controllable Asset Registry'!$E$779:$E$1329=A34,FALSE),"No Equipment in entity"))} -> No Equipment in entity
A35: ="entity:QNL_"&B35&"_"&C35 -> entity:QNL_B_032_REST_ROOM_MEN | B35: B_032 | C35: REST_ROOM_MEN | D35: {=TRANSPOSE(_xlfn._xlws.FILTER('Controllable Asset Registry'!$A$779:$A$1329,IFERROR('Controllable Asset Registry'!$E$779:$E$1329=A35,FALSE),"No Equipment in entity"))} -> No Equipment in entity
A36: ="entity:QNL_"&B36&"_"&C36 -> entity:QNL_B_034_MEETING_ROOM | B36: B_034 | C36: MEETING_ROOM | D36: {=TRANSPOSE(_xlfn._xlws.FILTER('Controllable Asset Registry'!$A$779:$A$1329,IFERROR('Controllable Asset Registry'!$E$779:$E$1329=A36,FALSE),"No Equipment in entity"))} -> VAV_B_S13_001 | E36: VAV_B_S13_002
A37: ="entity:QNL_"&B37&"_"&C37 -> entity:QNL_B036_REST_REST_ROOM_WOMEN | B37: B036_REST | C37: REST_ROOM_WOMEN | D37: {=TRANSPOSE(_xlfn._xlws.FILTER('Controllable Asset Registry'!$A$779:$A$1329,IFERROR('Controllable Asset Registry'!$E$779:$E$1329=A37,FALSE),"No Equipment in entity"))} -> No Equipment in entity
A38: ="entity:QNL_"&B38&"_"&C38 -> entity:QNL_B036_COR_CORRIDOR_4A | B38: B036_COR | C38: CORRIDOR_4A | D38: {=TRANSPOSE(_xlfn._xlws.FILTER('Controllable Asset Registry'!$A$779:$A$1329,IFERROR('Controllable Asset Registry'!$E$779:$E$1329=A38,FALSE),"No Equipment in entity"))} -> No Equipment in entity
A39: ="entity:QNL_"&B39&"_"&C39 -> entity:QNL_B_040_OFFICE | B39: B_040 | C39: OFFICE | D39: {=TRANSPOSE(_xlfn._xlws.FILTER('Controllable Asset Registry'!$A$779:$A$1329,IFERROR('Controllable Asset Registry'!$E$779:$E$1329=A39,FALSE),"No Equipment in entity"))} -> VAV_B_S14_001
A40: ="entity:QNL_"&B40&"_"&C40 -> entity:QNL_B_041_DIGITIZATION_ROOM | B40: B_041 | C40: DIGITIZATION_ROOM | D40: {=TRANSPOSE(_xlfn._xlws.FILTER('Controllable Asset Registry'!$A$779:$A$1329,IFERROR('Controllable Asset Registry'!$E$779:$E$1329=A40,FALSE),"No Equipment in entity"))} -> VAV_B_S14_004 | E40: VAV_B_S14_005 | F40: VAV_B_S14_006 | G40: VAV_B_S14_009 | H40: VAV_B_S14_010 | I40: VAV_B_S14_011 | J40: VAV_B_S14_012 | K40: VAV_B_S14_015 | L40: VAV_B_S14_016
A41: ="entity:QNL_"&B41&"_"&C41 -> entity:QNL_B_042_RECEPTION_&_LOUNGE | B41: B_042 | C41: RECEPTION_&_LOUNGE | D41: {=TRANSPOSE(_xlfn._xlws.FILTER('Controllable Asset Registry'!$A$779:$A$1329,IFERROR('Controllable Asset Registry'!$E$779:$E$1329=A41,FALSE),"No Equipment in entity"))} -> No Equipment in entity
A42: ="entity:QNL_"&B42&"_"&C42 -> entity:QNL_B_043_BINDING_&_PRESERVATION_SPACE | B42: B_043 | C42: BINDING_&_PRESERVATION_SPACE | D42: {=TRANSPOSE(_xlfn._xlws.FILTER('Controllable Asset Registry'!$A$779:$A$1329,IFERROR('Controllable Asset Registry'!$E$779:$E$1329=A42,FALSE),"No Equipment in entity"))} -> VAV_B_S14_042 | E42: VAV_B_S14_043 | F42: VAV_B_S14_044 | G42: VAV_B_S14_045 | H42: VAV_B_S14_046 | I42: VAV_B_S14_048 | J42: VAV_B_S14_049 | K42: VAV_B_S14_050 | L42: VAV_B_S14_051
A43: ="entity:QNL_"&B43&"_"&C43 -> entity:QNL_B044_BOH_B_O_H_KITCHEN | B43: B044_BOH | C43: B_O_H_KITCHEN | D43: {=TRANSPOSE(_xlfn._xlws.FILTER('Controllable Asset Registry'!$A$779:$A$1329,IFERROR('Controllable Asset Registry'!$E$779:$E$1329=A43,FALSE),"No Equipment in entity"))} -> No Equipment in entity
A44: ="entity:QNL_"&B44&"_"&C44 -> entity:QNL_B044_FIN_FINE_BINDING | B44: B044_FIN | C44: FINE_BINDING | D44: {=TRANSPOSE(_xlfn._xlws.FILTER('Controllable Asset Registry'!$A$779:$A$1329,IFERROR('Controllable Asset Registry'!$E$779:$E$1329=A44,FALSE),"No Equipment in entity"))} -> No Equipment in entity
A45: ="entity:QNL_"&B45&"_"&C45 -> entity:QNL_B046_RES_REST_ROOM_MEN | B45: B046_RES | C45: REST_ROOM_MEN | D45: {=TRANSPOSE(_xlfn._xlws.FILTER('Controllable Asset Registry'!$A$779:$A$1329,IFERROR('Controllable Asset Registry'!$E$779:$E$1329=A45,FALSE),"No Equipment in entity"))} -> No Equipment in entity
A46: ="entity:QNL_"&B46&"_"&C46 -> entity:QNL_B046_ITT_ITTIGATION_CONTROL_ROOM | B46: B046_ITT | C46: ITTIGATION_CONTROL_ROOM | D46: {=TRANSPOSE(_xlfn._xlws.FILTER('Controllable Asset Registry'!$A$779:$A$1329,IFERROR('Controllable Asset Registry'!$E$779:$E$1329=A46,FALSE),"No Equipment in entity"))} -> DX_B11
A47: ="entity:QNL_"&B47&"_"&C47 -> entity:QNL_B_047_REST_ROOM_WOMEN | B47: B_047 | C47: REST_ROOM_WOMEN | D47: {=TRANSPOSE(_xlfn._xlws.FILTER('Controllable Asset Registry'!$A$779:$A$1329,IFERROR('Controllable Asset Registry'!$E$779:$E$1329=A47,FALSE),"No Equipment in entity"))} -> No Equipment in entity
A48: ="entity:QNL_"&B48&"_"&C48 -> entity:QNL_B_048_QTEL_ROOM | B48: B_048 | C48: QTEL_ROOM | D48: {=TRANSPOSE(_xlfn._xlws.FILTER('Controllable Asset Registry'!$A$779:$A$1329,IFERROR('Controllable Asset Registry'!$E$779:$E$1329=A48,FALSE),"No Equipment in entity"))} -> CCU_B01 | E48: CCU_B02
A49: ="entity:QNL_"&B49&"_"&C49 -> entity:QNL_B_049_MEP_KITCHEN | B49: B_049 | C49: MEP_KITCHEN | D49: {=TRANSPOSE(_xlfn._xlws.FILTER('Controllable Asset Registry'!$A$779:$A$1329,IFERROR('Controllable Asset Registry'!$E$779:$E$1329=A49,FALSE),"No Equipment in entity"))} -> KEF_B019
A50: ="entity:QNL_"&B50&"_"&C50 -> entity:QNL_B-04B_ST-04B | B50: B-04B | C50: ST-04B | D50: {=TRANSPOSE(_xlfn._xlws.FILTER('Controllable Asset Registry'!$A$779:$A$1329,IFERROR('Controllable Asset Registry'!$E$779:$E$1329=A50,FALSE),"No Equipment in entity"))} -> No Equipment in entity
A51: ="entity:QNL_"&B51&"_"&C51 -> entity:QNL_B_050_TELECOM_ROOM | B51: B_050 | C51: TELECOM_ROOM | D51: {=TRANSPOSE(_xlfn._xlws.FILTER('Controllable Asset Registry'!$A$779:$A$1329,IFERROR('Controllable Asset Registry'!$E$779:$E$1329=A51,FALSE),"No Equipment in entity"))} -> CCU_B03 | E51: CCU_B04
A52: ="entity:QNL_"&B52&"_"&C52 -> entity:QNL_B_051_STORAGE | B52: B_051 | C52: STORAGE | D52: {=TRANSPOSE(_xlfn._xlws.FILTER('Controllable Asset Registry'!$A$779:$A$1329,IFERROR('Controllable Asset Registry'!$E$779:$E$1329=A52,FALSE),"No Equipment in entity"))} -> CAV_B_S14_001
A53: ="entity:QNL_"&B53&"_"&C53 -> entity:QNL_B_053_CORRIDORS | B53: B_053 | C53: CORRIDORS | D53: {=TRANSPOSE(_xlfn._xlws.FILTER('Controllable Asset Registry'!$A$779:$A$1329,IFERROR('Controllable Asset Registry'!$E$779:$E$1329=A53,FALSE),"No Equipment in entity"))} -> No Equipment in entity
A54: ="entity:QNL_"&B54&"_"&C54 -> entity:QNL_B_054_PATIO_GARDEN | B54: B_054 | C54: PATIO_GARDEN | D54: {=TRANSPOSE(_xlfn._xlws.FILTER('Controllable Asset Registry'!$A$779:$A$1329,IFERROR('Controllable Asset Registry'!$E$779:$E$1329=A54,FALSE),"No Equipment in entity"))} -> No Equipment in entity
A55: ="entity:QNL_"&B55&"_"&C55 -> entity:QNL_B057_DIG_OFFICE_DIG_INIT | B55: B057_DIG | C55: OFFICE_DIG_INIT | D55: {=TRANSPOSE(_xlfn._xlws.FILTER('Controllable Asset Registry'!$A$779:$A$1329,IFERROR('Controllable Asset Registry'!$E$779:$E$1329=A55,FALSE),"No Equipment in entity"))} -> No Equipment in entity
A56: ="entity:QNL_"&B56&"_"&C56 -> entity:QNL_B057_AD_OFFICE_AD_FOR_LIT | B56: B057_AD | C56: OFFICE_AD_FOR_LIT | D56: {=TRANSPOSE(_xlfn._xlws.FILTER('Controllable Asset Registry'!$A$779:$A$1329,IFERROR('Controllable Asset Registry'!$E$779:$E$1329=A56,FALSE),"No Equipment in entity"))} -> No Equipment in entity
A57: ="entity:QNL_"&B57&"_"&C57 -> entity:QNL_B_058_SHELL_SPACE | B57: B_058 | C57: SHELL_SPACE | D57: {=TRANSPOSE(_xlfn._xlws.FILTER('Controllable Asset Registry'!$A$779:$A$1329,IFERROR('Controllable Asset Registry'!$E$779:$E$1329=A57,FALSE),"No Equipment in entity"))} -> VAV_B_S14_007 | E57: VAV_B_S14_013
A58: ="entity:QNL_"&B58&"_"&C58 -> entity:QNL_B_060_MAINTENANCE | B58: B_060 | C58: MAINTENANCE | D58: {=TRANSPOSE(_xlfn._xlws.FILTER('Controllable Asset Registry'!$A$779:$A$1329,IFERROR('Controllable Asset Registry'!$E$779:$E$1329=A58,FALSE),"No Equipment in entity"))} -> No Equipment in entity
A59: ="entity:QNL_"&B59&"_"&C59 -> entity:QNL_B_062_IDF_CORRIDOR | B59: B_062 | C59: IDF_CORRIDOR | D59: {=TRANSPOSE(_xlfn._xlws.FILTER('Controllable Asset Registry'!$A$779:$A$1329,IFERROR('Controllable Asset Registry'!$E$779:$E$1329=A59,FALSE),"No Equipment in entity"))} -> FCU_B_003
A60: ="entity:QNL_"&B60&"_"&C60 -> entity:QNL_B_063_PLANT_ROOM_01 | B60: B_063 | C60: PLANT_ROOM_01 | D60: {=TRANSPOSE(_xlfn._xlws.FILTER('Controllable Asset Registry'!$A$779:$A$1329,IFERROR('Controllable Asset Registry'!$E$779:$E$1329=A60,FALSE),"No Equipment in entity"))} -> AHUB002 | E60: AHUB011 | F60: AHUB012 | G60: FCU_B_011 | H60: FCU_B_012 | I60: CAV_B_S12_002 | J60: CAV_B_S12_003 | K60: CAV_B_S15_001 | L60: CAV_B_S15_002 | M60: CAV_B_S15_003
A61: ="entity:QNL_"&B61&"_"&C61 -> entity:QNL_B_065_VENTLATON | B61: B_065 | C61: VENTLATON | D61: {=TRANSPOSE(_xlfn._xlws.FILTER('Controllable Asset Registry'!$A$779:$A$1329,IFERROR('Controllable Asset Registry'!$E$779:$E$1329=A61,FALSE),"No Equipment in entity"))} -> No Equipment in entity
A62: ="entity:QNL_"&B62&"_"&C62 -> entity:QNL_B_066_CORRIDOR | B62: B_066 | C62: CORRIDOR | D62: {=TRANSPOSE(_xlfn._xlws.FILTER('Controllable Asset Registry'!$A$779:$A$1329,IFERROR('Controllable Asset Registry'!$E$779:$E$1329=A62,FALSE),"No Equipment in entity"))} -> No Equipment in entity
A63: ="entity:QNL_"&B63&"_"&C63 -> entity:QNL_B_067_VENTLATON | B63: B_067 | C63: VENTLATON | D63: {=TRANSPOSE(_xlfn._xlws.FILTER('Controllable Asset Registry'!$A$779:$A$1329,IFERROR('Controllable Asset Registry'!$E$779:$E$1329=A63,FALSE),"No Equipment in entity"))} -> No Equipment in entity
A64: ="entity:QNL_"&B64&"_"&C64 -> entity:QNL_B_068_CORRIDOR | B64: B_068 | C64: CORRIDOR | D64: {=TRANSPOSE(_xlfn._xlws.FILTER('Controllable Asset Registry'!$A$779:$A$1329,IFERROR('Controllable Asset Registry'!$E$779:$E$1329=A64,FALSE),"No Equipment in entity"))} -> No Equipment in entity
A65: ="entity:QNL_"&B65&"_"&C65 -> entity:QNL_B_070_PLANT_ROOM_02 | B65: B_070 | C65: PLANT_ROOM_02 | D65: {=TRANSPOSE(_xlfn._xlws.FILTER('Controllable Asset Registry'!$A$779:$A$1329,IFERROR('Controllable Asset Registry'!$E$779:$E$1329=A65,FALSE),"No Equipment in entity"))} -> AHUB003 | E65: AHUB010 | F65: AHUB013 | G65: FCU_B_013 | H65: FCU_B_014 | I65: CAV_B_S13_010 | J65: CAV_B_S13_011 | K65: EF_BBV01 | L65: EF_BBV02 | M65: TEF_B02A | N65: TEF_B02B
A66: ="entity:QNL_"&B66&"_"&C66 -> entity:QNL_B_071_FIRE_COMMAND_ROOM | B66: B_071 | C66: FIRE_COMMAND_ROOM | D66: {=TRANSPOSE(_xlfn._xlws.FILTER('Controllable Asset Registry'!$A$779:$A$1329,IFERROR('Controllable Asset Registry'!$E$779:$E$1329=A66,FALSE),"No Equipment in entity"))} -> FCU_B_006 | E66: CAV_B_S13_012 | F66: EF_B14
A67: ="entity:QNL_"&B67&"_"&C67 -> entity:QNL_B_072_SPRIMKLERS_PUMPS_&_ZONES_VALVES | B67: B_072 | C67: SPRIMKLERS_PUMPS_&_ZONES_VALVES | D67: {=TRANSPOSE(_xlfn._xlws.FILTER('Controllable Asset Registry'!$A$779:$A$1329,IFERROR('Controllable Asset Registry'!$E$779:$E$1329=A67,FALSE),"No Equipment in entity"))} -> FCU_B_007 | E67: CAV_B_S13_021 | F67: EF_B13
A68: ="entity:QNL_"&B68&"_"&C68 -> entity:QNL_B_080_GENERATOR | B68: B_080 | C68: GENERATOR | D68: {=TRANSPOSE(_xlfn._xlws.FILTER('Controllable Asset Registry'!$A$779:$A$1329,IFERROR('Controllable Asset Registry'!$E$779:$E$1329=A68,FALSE),"No Equipment in entity"))} -> EF_B09 | E68: ELEC_Gen
A69: ="entity:QNL_"&B69&"_"&C69 -> entity:QNL_B_081_MV_ROOM | B69: B_081 | C69: MV_ROOM | D69: {=TRANSPOSE(_xlfn._xlws.FILTER('Controllable Asset Registry'!$A$779:$A$1329,IFERROR('Controllable Asset Registry'!$E$779:$E$1329=A69,FALSE),"No Equipment in entity"))} -> DX_B01 | E69: DX_B02
A70: ="entity:QNL_"&B70&"_"&C70 -> entity:QNL_B_082_TRANSFORMER_ROOM | B70: B_082 | C70: TRANSFORMER_ROOM | D70: {=TRANSPOSE(_xlfn._xlws.FILTER('Controllable Asset Registry'!$A$779:$A$1329,IFERROR('Controllable Asset Registry'!$E$779:$E$1329=A70,FALSE),"No Equipment in entity"))} -> DX_B03 | E70: DX_B04 | F70: DX_B14
A71: ="entity:QNL_"&B71&"_"&C71 -> entity:QNL_B_084_UPS_BATTERY_ROOM | B71: B_084 | C71: UPS_BATTERY_ROOM | D71: {=TRANSPOSE(_xlfn._xlws.FILTER('Controllable Asset Registry'!$A$779:$A$1329,IFERROR('Controllable Asset Registry'!$E$779:$E$1329=A71,FALSE),"No Equipment in entity"))} -> CAV_B_S13_020 | E71: DX_B08 | F71: DX_B09
A72: ="entity:QNL_"&B72&"_"&C72 -> entity:QNL_B_085_FUMIGATION_ROOM | B72: B_085 | C72: FUMIGATION_ROOM | D72: {=TRANSPOSE(_xlfn._xlws.FILTER('Controllable Asset Registry'!$A$779:$A$1329,IFERROR('Controllable Asset Registry'!$E$779:$E$1329=A72,FALSE),"No Equipment in entity"))} -> FCU_B_002 | E72: VAV_B_S13_006 | F72: EF_B05
A73: ="entity:QNL_"&B73&"_"&C73 -> entity:QNL_B_086_FREEZE_AREA | B73: B_086 | C73: FREEZE_AREA | D73: {=TRANSPOSE(_xlfn._xlws.FILTER('Controllable Asset Registry'!$A$779:$A$1329,IFERROR('Controllable Asset Registry'!$E$779:$E$1329=A73,FALSE),"No Equipment in entity"))} -> No Equipment in entity
A74: ="entity:QNL_"&B74&"_"&C74 -> entity:QNL_B_087_GAS_SUPPRESSION_ROOM | B74: B_087 | C74: GAS_SUPPRESSION_ROOM | D74: {=TRANSPOSE(_xlfn._xlws.FILTER('Controllable Asset Registry'!$A$779:$A$1329,IFERROR('Controllable Asset Registry'!$E$779:$E$1329=A74,FALSE),"No Equipment in entity"))} -> FCU_B_008 | E74: CAV_B_S13_013
A75: ="entity:QNL_"&B75&"_"&C75 -> entity:QNL_B_088_PEOPLE_MOVER_PLANT | B75: B_088 | C75: PEOPLE_MOVER_PLANT | D75: {=TRANSPOSE(_xlfn._xlws.FILTER('Controllable Asset Registry'!$A$779:$A$1329,IFERROR('Controllable Asset Registry'!$E$779:$E$1329=A75,FALSE),"No Equipment in entity"))} -> FCU_B_009 | E75: CAV_B_S13_014
A76: ="entity:QNL_"&B76&"_"&C76 -> entity:QNL_B_089_SERVER_ROOM | B76: B_089 | C76: SERVER_ROOM | D76: {=TRANSPOSE(_xlfn._xlws.FILTER('Controllable Asset Registry'!$A$779:$A$1329,IFERROR('Controllable Asset Registry'!$E$779:$E$1329=A76,FALSE),"No Equipment in entity"))} -> CAV_B_S13_015 | E76: CCU_B05 | F76: CCU_B06 | G76: CCU_B07
A77: ="entity:QNL_"&B77&"_"&C77 -> entity:QNL_B_091_FUEL_ROOM | B77: B_091 | C77: FUEL_ROOM | D77: {=TRANSPOSE(_xlfn._xlws.FILTER('Controllable Asset Registry'!$A$779:$A$1329,IFERROR('Controllable Asset Registry'!$E$779:$E$1329=A77,FALSE),"No Equipment in entity"))} -> EF_B11
A78: ="entity:QNL_"&B78&"_"&C78 -> entity:QNL_B_092_STORAGE | B78: B_092 | C78: STORAGE | D78: {=TRANSPOSE(_xlfn._xlws.FILTER('Controllable Asset Registry'!$A$779:$A$1329,IFERROR('Controllable Asset Registry'!$E$779:$E$1329=A78,FALSE),"No Equipment in entity"))} -> DX_B20
A79: ="entity:QNL_"&B79&"_"&C79 -> entity:QNL_B_0924_FUEL_TANK_CHERRY_PICKER_PANKING | B79: B_0924 | C79: FUEL_TANK_CHERRY_PICKER_PANKING | D79: {=TRANSPOSE(_xlfn._xlws.FILTER('Controllable Asset Registry'!$A$779:$A$1329,IFERROR('Controllable Asset Registry'!$E$779:$E$1329=A79,FALSE),"No Equipment in entity"))} -> No Equipment in entity
A80: ="entity:QNL_"&B80&"_"&C80 -> entity:QNL_B_093_TRANSH_CHAMBER | B80: B_093 | C80: TRANSH_CHAMBER | D80: {=TRANSPOSE(_xlfn._xlws.FILTER('Controllable Asset Registry'!$A$779:$A$1329,IFERROR('Controllable Asset Registry'!$E$779:$E$1329=A80,FALSE),"No Equipment in entity"))} -> DX_B13 | E80: DX_B15 | F80: EF_B10
A81: ="entity:QNL_"&B81&"_"&C81 -> entity:QNL_B_095_EMERGENCY_LIGHTING_BATTERY_ROOM | B81: B_095 | C81: EMERGENCY_LIGHTING_BATTERY_ROOM | D81: {=TRANSPOSE(_xlfn._xlws.FILTER('Controllable Asset Registry'!$A$779:$A$1329,IFERROR('Controllable Asset Registry'!$E$779:$E$1329=A81,FALSE),"No Equipment in entity"))} -> DX_B07 | E81: DX_B16
A82: ="entity:QNL_"&B82&"_"&C82 -> entity:QNL_B_100_LOADING_DOCK | B82: B_100 | C82: LOADING_DOCK | D82: {=TRANSPOSE(_xlfn._xlws.FILTER('Controllable Asset Registry'!$A$779:$A$1329,IFERROR('Controllable Asset Registry'!$E$779:$E$1329=A82,FALSE),"No Equipment in entity"))} -> No Equipment in entity
A83: ="entity:QNL_"&B83&"_"&C83 -> entity:QNL_B_101_SHIPPING_CLERK | B83: B_101 | C83: SHIPPING_CLERK | D83: {=TRANSPOSE(_xlfn._xlws.FILTER('Controllable Asset Registry'!$A$779:$A$1329,IFERROR('Controllable Asset Registry'!$E$779:$E$1329=A83,FALSE),"No Equipment in entity"))} -> VAV_B_S13_007
A84: ="entity:QNL_"&B84&"_"&C84 -> entity:QNL_B_102_SECURITY_&_BMS | B84: B_102 | C84: SECURITY_&_BMS | D84: {=TRANSPOSE(_xlfn._xlws.FILTER('Controllable Asset Registry'!$A$779:$A$1329,IFERROR('Controllable Asset Registry'!$E$779:$E$1329=A84,FALSE),"No Equipment in entity"))} -> DX_B10
A85: ="entity:QNL_"&B85&"_"&C85 -> entity:QNL_B_103_PROCESSING_ROOM | B85: B_103 | C85: PROCESSING_ROOM | D85: {=TRANSPOSE(_xlfn._xlws.FILTER('Controllable Asset Registry'!$A$779:$A$1329,IFERROR('Controllable Asset Registry'!$E$779:$E$1329=A85,FALSE),"No Equipment in entity"))} -> VAV_B_S13_003 | E85: VAV_B_S13_004
A86: ="entity:QNL_"&B86&"_"&C86 -> entity:QNL_B_104_STORAGE | B86: B_104 | C86: STORAGE | D86: {=TRANSPOSE(_xlfn._xlws.FILTER('Controllable Asset Registry'!$A$779:$A$1329,IFERROR('Controllable Asset Registry'!$E$779:$E$1329=A86,FALSE),"No Equipment in entity"))} -> CAV_B_S13_009
A87: ="entity:QNL_"&B87&"_"&C87 -> entity:QNL_B106_RES_REST_ROOM_SECURITY | B87: B106_RES | C87: REST_ROOM_SECURITY | D87: {=TRANSPOSE(_xlfn._xlws.FILTER('Controllable Asset Registry'!$A$779:$A$1329,IFERROR('Controllable Asset Registry'!$E$779:$E$1329=A87,FALSE),"No Equipment in entity"))} -> DX_B22
A88: ="entity:QNL_"&B88&"_"&C88 -> entity:QNL_B106_SEC_SECURITY_STORES_SECURITY_UPS | B88: B106_SEC | C88: SECURITY_STORES_SECURITY_UPS | D88: {=TRANSPOSE(_xlfn._xlws.FILTER('Controllable Asset Registry'!$A$779:$A$1329,IFERROR('Controllable Asset Registry'!$E$779:$E$1329=A88,FALSE),"No Equipment in entity"))} -> No Equipment in entity
A89: ="entity:QNL_"&B89&"_"&C89 -> entity:QNL_B_107_SECURITY_EQUIPMENT_ROOM | B89: B_107 | C89: SECURITY_EQUIPMENT_ROOM | D89: {=TRANSPOSE(_xlfn._xlws.FILTER('Controllable Asset Registry'!$A$779:$A$1329,IFERROR('Controllable Asset Registry'!$E$779:$E$1329=A89,FALSE),"No Equipment in entity"))} -> DX_B12 | E89: DX_B23
A90: ="entity:QNL_"&B90&"_"&C90 -> entity:QNL_B_108_TOILET | B90: B_108 | C90: TOILET | D90: {=TRANSPOSE(_xlfn._xlws.FILTER('Controllable Asset Registry'!$A$779:$A$1329,IFERROR('Controllable Asset Registry'!$E$779:$E$1329=A90,FALSE),"No Equipment in entity"))} -> No Equipment in entity
A91: ="entity:QNL_"&B91&"_"&C91 -> entity:QNL_B_109_LOADING_AREA | B91: B_109 | C91: LOADING_AREA | D91: {=TRANSPOSE(_xlfn._xlws.FILTER('Controllable Asset Registry'!$A$779:$A$1329,IFERROR('Controllable Asset Registry'!$E$779:$E$1329=A91,FALSE),"No Equipment in entity"))} -> EF_B07 | E91: EF_B08 | F91: EF_B15 | G91: EF_B16
A92: ="entity:QNL_"&B92&"_"&C92 -> entity:QNL_B_110_PLANT_ROOM_03 | B92: B_110 | C92: PLANT_ROOM_03 | D92: {=TRANSPOSE(_xlfn._xlws.FILTER('Controllable Asset Registry'!$A$779:$A$1329,IFERROR('Controllable Asset Registry'!$E$779:$E$1329=A92,FALSE),"No Equipment in entity"))} -> AHUB004 | E92: AHUB009 | F92: AHUB014 | G92: AHUB015 | H92: FCU_B_015 | I92: FCU_B_016 | J92: FCU_B_017 | K92: CAV_B_S14_003 | L92: CAV_B_S14_004 | M92: CAV_B_S14_005 | N92: TEF_B01A | O92: TEF_B01B
A93: ="entity:QNL_"&B93&"_"&C93 -> entity:QNL_B_111_STORAGE | B93: B_111 | C93: STORAGE | D93: {=TRANSPOSE(_xlfn._xlws.FILTER('Controllable Asset Registry'!$A$779:$A$1329,IFERROR('Controllable Asset Registry'!$E$779:$E$1329=A93,FALSE),"No Equipment in entity"))} -> No Equipment in entity
A94: ="entity:QNL_"&B94&"_"&C94 -> entity:QNL_B_112_CORRIDOR | B94: B_112 | C94: CORRIDOR | D94: {=TRANSPOSE(_xlfn._xlws.FILTER('Controllable Asset Registry'!$A$779:$A$1329,IFERROR('Controllable Asset Registry'!$E$779:$E$1329=A94,FALSE),"No Equipment in entity"))} -> No Equipment in entity
A95: ="entity:QNL_"&B95&"_"&C95 -> entity:QNL_B_113_MAINTENANCE | B95: B_113 | C95: MAINTENANCE | D95: {=TRANSPOSE(_xlfn._xlws.FILTER('Controllable Asset Registry'!$A$779:$A$1329,IFERROR('Controllable Asset Registry'!$E$779:$E$1329=A95,FALSE),"No Equipment in entity"))} -> No Equipment in entity
A96: ="entity:QNL_"&B96&"_"&C96 -> entity:QNL_B_114_VENTLATON | B96: B_114 | C96: VENTLATON | D96: {=TRANSPOSE(_xlfn._xlws.FILTER('Controllable Asset Registry'!$A$779:$A$1329,IFERROR('Controllable Asset Registry'!$E$779:$E$1329=A96,FALSE),"No Equipment in entity"))} -> No Equipment in entity
A97: ="entity:QNL_"&B97&"_"&C97 -> entity:QNL_B_115_CORRIDOR | B97: B_115 | C97: CORRIDOR | D97: {=TRANSPOSE(_xlfn._xlws.FILTER('Controllable Asset Registry'!$A$779:$A$1329,IFERROR('Controllable Asset Registry'!$E$779:$E$1329=A97,FALSE),"No Equipment in entity"))} -> No Equipment in entity
A98: ="entity:QNL_"&B98&"_"&C98 -> entity:QNL_B_116_VENTLATON | B98: B_116 | C98: VENTLATON | D98: {=TRANSPOSE(_xlfn._xlws.FILTER('Controllable Asset Registry'!$A$779:$A$1329,IFERROR('Controllable Asset Registry'!$E$779:$E$1329=A98,FALSE),"No Equipment in entity"))} -> No Equipment in entity
A99: ="entity:QNL_"&B99&"_"&C99 -> entity:QNL_B_120_COMPACT_SHELVING_-MAIN_COLLECTION | B99: B_120 | C99: COMPACT_SHELVING_-MAIN_COLLECTION | D99: {=TRANSPOSE(_xlfn._xlws.FILTER('Controllable Asset Registry'!$A$779:$A$1329,IFERROR('Controllable Asset Registry'!$E$779:$E$1329=A99,FALSE),"No Equipment in entity"))} -> TEF_B03A | E99: TEF_B03B
A100: ="entity:QNL_"&B100&"_"&C100 -> entity:QNL_B_121_SORTING_SHELVING_ROOM | B100: B_121 | C100: SORTING_SHELVING_ROOM | D100: {=TRANSPOSE(_xlfn._xlws.FILTER('Controllable Asset Registry'!$A$779:$A$1329,IFERROR('Controllable Asset Registry'!$E$779:$E$1329=A100,FALSE),"No Equipment in entity"))} -> FCU_B_027 | E100: FCU_B_028
...
