Workbook

Sheet Claude Log
A1: Turn # | B1: Date | C1: User Request | D1: Action Taken | E1: Details | F1: Outcome
A2: 1 | B2: 46244 | C2: Provided full transcript from previous session (classifying HQ VAV/FCU tags as Included/Not Included in column D by room type across Ground Floor–Level 11). New session; selection at D1174. | D2: Loaded prior context; set up Claude Log sheet; inspected the registry section around D1174. | E2: Row 1170 = AHUB_0005; FCU numbering restarts at FCU0001 on row 1171 — this is a separate building/section where column D holds room descriptions (e.g. 'SPRINKLER AND WATER','B.M.S'), not Included/Not Included marks. AHUs (rows 4-28) still unmarked pending direction. | F2: Awaiting user direction on next step (new floor, AHU handling, or final excluded-room verification).
A3: 3 | B3: 46244 | C3: Clarified: wants room names (rooms served by each equipment tag) filled for the HQ block, rows 3–763, in column E (keeping the Included/Not Included marks in column D). | D3: Confirmed target column E via question; checked E is empty apart from a legend at E3/E4. Explained I cannot view the previous session's drawing images and my prior notes are not a clean per-row room map. | E3: Room names must be exact; prior notes grouped multiple tags per room label. Requested the floor drawings be resent one at a time to fill column E accurately, floor by floor. | F3: Awaiting user to resend the first HQ floor drawing to begin populating column E.
A4: 4 | B4: 46244 | C4: Said they will send the floor drawings later tonight. | D4: Acknowledged; no workbook changes made. Confirmed the floor-by-floor workflow to populate column E with room names once drawings arrive. | E4: No cells written to Controllable Asset Registry this turn. | F4: On hold — awaiting HQ floor drawings from user (expected tonight).
A5: 5 | B5: 46244 | C5: Sent HQ Roof Top (Level 12) drawing; asked me to start filling room names in column E for that floor. | D5: Wrote FCU room names to E155:E160 (FCU0126/0127 → 12.002 MCC Closet; FCU0128/0129 → 12.003 MCC Closet; FCU0130 → 12.004 MCC Closet; FCU0131 → roof plant/walkway near CSRR-0008). Verified by re-reading A155:E160. | E5: Roof VAV/12/01-13 units are NOT in the tag list (all VAV0001-0607 already assigned to Ground-L11; HQ block ends row 763, QNL starts 764). AHU/12/01-10 (rows 4-12) left blank — parked per earlier decision and AHUs don't serve a single room. | F5: Level 12 FCUs done. Flagged: SE 12.001 Electrical Closet sits beside 12.002 MCC Closet — could not confirm if one FCU serves 12.001 instead; FCU0131 has no room number on the drawing.
A6: 6 | B6: 46245 | C6: Sent the 3rd image pair — new: South Building L0 Section A1.3; old: North Building L0 Section A2.3. Asked me to continue the established workflow (map the new floor, extract standalone tags from the old floor). | D6: Filled 3 blank FCU rows (FCU6987 row 2118, SB FCU0001 row 2159, SB FCU2001 row 2168). Appended 33 new rows (2365-2397): 5 A1.3 South Building AT tags, 24 A2.3 North Building AT tags, 4 A2.3 standalone EV valves. Flagged 7 uncertain rows yellow in C:D. | E6: Duplicate avoidance: skipped AT-0006 (already row 2262 from B1.1) and all A2.3 numbers already embedded in existing VAV rows (5000/5002, 5001/5003, 5010/5011, 5015/5016, 5030/5031, 5040/5041, 5045/5046, 5395, 5400, 5405, 5410/5411, 6000/6001, 6010/6011, 6025/6026, 6240/6241, 6300, 6305, 6310, 6315/6316). Appended only valves with no VAV row: EV-5021, EV-5035, EV-6016, EV-6127. Equipment type = each tag's own prefix (AT/EV) per the standing rule. NB FCU5982/5991/5992/6985/6986 were already populated from an earlier session and matched A2.3, so left untouched. | F6: 3rd pair complete and verified (rows 2118, 2159, 2168, 2365-2397 re-read; no gaps). Next append row = 2398. Flagged yellow: AT-0002, AT-0005, AT-2001, AT-5030, AT-5045, EV-5035, EV-6127. Open note: A2.3 right-hand area is labelled RECEPTION AREA N-0169, which duplicates the left-side EXP. OFFICE N-0169 label - no tag sits there so no row was written.
A7: 7 | B7: 46245 | C7: Sent the 4th image pair — new: South Building L0 Section A1.2; old: North Building L0 Section B2.1. Continue the established workflow. | D7: Filled SB FCU2002-2005 (rows 2169-2172). Mapped 45 of 46 blank VAV rows for A1.2 (C/D 1738:1783 = VAV2002-VAV2047). Appended 112 rows (2398-2509): 45 A1.2 AT-20xx, 8 A1.2 standalone 0-series AT, 43 B2.1 AT, 15 B2.1 valves, FCU6997. Corrected AT-2001 (row 2369). Flagged 39 uncertain rows yellow, then fixed 14 misplaced flags. | E7: A1.2 turned out to be a map-the-rooms floor: VAV2002-VAV2047 existed but were blank, and AT numbers correspond 1:1 to VAV numbers. There is no VAV2001 row and no VAV rows for the 0115-0124 series, so those 9 tags were appended only. VAV2005 (row 1741) left blank - AT-2005 does not appear on A1.2. Self-caught error: skipping AT-2005 in the append shifted my flag row offsets by one, so 7 flags landed on confident rows (AT-2010/2014/2017/2018/2026/2034/2036) and 7 uncertain rows were unflagged; cleared and re-applied correctly. AT-2001 moved from Vestibule S-0202 (per A1.3) to High-Density Room S-0206 (per A1.2, box sits inside the room outline) - still flagged. | F7: 4th pair complete and verified (rows 2169-2172, 2369, 1738-1783, 2398-2510 re-read; no gaps; flag colours confirmed on C:D). Next append row = 2510. DEFERRED / NEEDS USER DECISION: (1) 21 blank NB VAV rows discovered - 1468 (VAV6295), 1473-1490 (VAV6320-6410), 1543-1544 (VAV7385/7390) - not filled because two existing rows conflict with the drawing, so a bulk same-number fill is unsafe. (2) Conflict A: registry row 1465 VAV6220 = Conf N-0331 and row 1463 VAV6205 = Emergency Elec. N-0333, but B2.1 shows AT-6220 at Emergency Elec. N-0333 and AT-6205 at Conference N-0331 (appears swapped). (3) Conflict B: registry row 1485 VAV6380 = Office N-0376, but B2.1 shows AT-6370 at Office N-0376 and AT-6380 at Workstation N-0378 (possible off-by-one, same pattern as the A2.2 fix).
A8: 8 | B8: 46245 | C8: Sent the 5th image pair — new: South Building L0 Section A1.1; old: North Building L0 Section B2.2. Continue the established workflow. | D8: A1.1: filled VAV3001-3007 (rows 1784-1790) and FCU3001 (row 2173); appended 45 tags (2510-2554) = 32 AT-30xx plus 13 of the 2301-AT-01xx BACnet points. B2.2: appended 77 rows (2555-2631) = 51 AT (incl. the AT-7090/7105/7120 multi-node sensors), 8 standalone EV, 17 lab valves, FCU7993. Flagged 34 rows yellow across both. | E8: B2.2's VAV rows mostly already existed with rooms, so the AT twins inherited the registry room (consistent with the A2.1/A2.2 approach) rather than my read of the drawing; the five places where the drawing disagrees were flagged instead of overwritten. Multi-node tags (AT-7090-N1/N2, AT-7105-N1/N2, AT-7120-N1..N9) have no VAV rows and were mapped from the drawing to N-0412/0412A, N-0415/0415A, N-0418/0418A and N-0430A..N-0430F - all flagged. Skipped every valve already embedded in a VAV row name (VEV7031, VEV7051, VEV7061, CEV7221, VEV7231, VEV7241A, VEV7251/7261/7271/7281/7291/7311/7321/7331/7341/7351/7361/7371, EV7126/7141/7186/7216/7495). FEV-7232 appears twice on the drawing - appended once and flagged. | F8: 5th pair complete and verified (rows 1784-1790, 2173, 2510-2632 re-read; 122 appended rows with no gaps; flag colours spot-checked against tag names). Next append row = 2632. NEW CONFLICTS FLAGGED, NOT OVERWRITTEN: (1) FCU rows 2119/2120/2121 (FCU7981 = Stair 5 N-0STO5, FCU7982 and FCU7983 = Service Corridor N-0344) disagree with B2.2, which shows FCU-7993 at Stair 5, FCU-7981 at IDF N-0419 and FCU-7982 near Mech/FPC N-0434. (2) Row 2085 FCU7790 is tagged NB_1F but B2.2 (Level 0) shows FCU-7790 at Stair 6 N-0ST06. (3) Registry rows 1517/1518 give both VAV7145 and VAV7155 the same room (Office N-0427) - drawing suggests 7145 = N-0425. (4) Row 1519 VAV7165 = N-0428 vs drawing N-0429. (5) Row 1523 VAV7185 = Office N-0426 vs drawing Emer. Elec. Room N-0433, and row 1526 VAV7215 = Emergency Elec. N-0433 vs drawing Office N-0438. STILL OPEN from turn 7: the 21 blank NB VAV rows (1468, 1473-1490, 1543-1544) and the VAV6205/6220 and VAV6380 conflicts.
A9: 9 | B9: 46245 | C9: Sent the 6th image pair — new: South Building Level 1 Section B1.2; old: North Building Level 01 Section A2.1. First pair on Level 1 rather than Level 0. | D9: B1.2: filled 45 blank VAV rows (C/D across 1595:1645) and FCU1503 (row 2132); appended 49 AT tags (2632-2680). A2.1 L01: appended 28 rows (2681-2708) = 8 AT twins, 19 valves, FCU2004. Flagged 5 rows yellow after correcting 2 that landed one row off. | E9: Both drawings are Level 1, so writes went to the SB_1F and NB_1F blocks (not GF). SB VAV15xx occupies rows 1590-1645 but the series is not contiguous - VAV1504, 1535, 1537, 1538 and 1541 have no rows, so AT-1504/1535/1537 were appended only. NB_1F registry rooms for VAV4660-4745 matched my reading of the drawing exactly (N-1227 through N-1244), so those 8 AT twins needed no flags. NB_1F FCU4910/4915/4916/4917 were already correctly populated and match A2.1, so left untouched. Skipped valves already embedded in VAV row names (VEV4621, VEV4631, VEV4051/4061/4091, the VAV4070-4083 high-bay pairs) and VEV-4041 which was already appended at row 2253. | F9: 6th pair complete and verified (rows 1590-1645, 2132, 2632-2709 re-read; 77 appended rows with no gaps; flag cells checked against tag names). Next append row = 2709. Flagged: AT-1504 (corridor position), AT-1533 and AT-1536 (sit between an electrical room and an office), AT-1537, CEV-4502, FCU2004. Still-blank SB L1 VAV rows with no tag on this drawing: 1590-1594 (VAV1501-1503, 1505, 1506), 1624-1625 (VAV1539/1540), 1627-1629 (VAV1543-1545), 1631 (VAV1547) - likely on the B1.1 half of Level 1. STILL OPEN: the 21 blank NB GF VAV rows (1468, 1473-1490, 1543-1544) and the registry conflicts at rows 1463/1465, 1485, 1517/1518, 1519, 1523/1526, 2085, 2119-2121.
A10: 10 | B10: 46245 | C10: Sent the 7th image pair — new: South Building Level 1 Section B1.1; old: North Building Level 1 Section A2.2. | D10: B1.1: filled 34 blank VAV rows (1566-1594, 1624-1631) + FCU1501/1502 (2130-2131); appended 46 AT tags (2709-2754). A2.2: filled FCU5986 (2076) and VAV4650 (1842); appended 67 rows (2755-2821) = 42 AT, 7 EV, 18 lab valves. Flagged 12 rows yellow. | E10: ERROR MADE AND CORRECTED: I wrote to FCU5983 (row 2073) and FCU5984 (row 2074) without reading them first - they already held 'Not Included / JC N-1139' and 'Included / Corridor N-1138'. I overwrote both with my own reading of the drawing (IDF N-1140 / JC N-1139), then restored the original values from the pre-write snapshot and flagged all three rows instead. Only FCU5986 was genuinely blank and kept a new value. Lesson: read FCU rows before writing, as several were populated in earlier sessions. Otherwise: NB_1F VAV5650-5940 rooms already matched the drawing closely, so those 38 AT twins inherited the registry room. Skipped valves embedded in VAV row names (VEV5601/5611/5622/5623/5631/5771/5781/5793/5795A/5801, EV5656/5716/5731/5736/5741/5761/5836). Unnumbered 'TAG 0.0' boxes on A2.2 could not be appended. | F10: 7th pair complete and verified (rows 1566-1645, 1842, 2073-2076, 2130-2132, 2709-2822 re-read; 113 appended rows with no gaps; all 12 flag cells checked against tag names). Next append row = 2822. South Building Level 1 is now fully mapped except VAV0509 (row 1569) - no AT-0509 appears on either B1.1 or B1.2. Flagged: AT-0504, AT-0505, AT-0515, AT-0534, AT-0529, AT-5685 (registry calls N-1126 an Office, drawing calls it Corridor), AT-5840 and AT-5905 (registry gives both Office N-1163), EV-5686, VEV-5581 (label appears twice on drawing), VEV-5821, FCU1503 (row 2132 - B1.2 shows it at Stair 1, B1.1 shows it near FPC S-1108/UPS S-1107D), FCU5983/5984/5986. STILL OPEN: 21 blank NB GF VAV rows (1468, 1473-1490, 1543-1544) and conflicts at rows 1463/1465, 1485, 1517/1518, 1519, 1523/1526, 2085, 2119-2121.
A11: 11 | B11: 46245 | C11: Sent the 8th image pair — new: South Building Level 1 Section A1.3; old: North Building Level 1 Section A2.3. Both are sparse core/lobby sections. | D11: A1.3: filled VAV2501 (row 1646, Lobby S-1201), FCU0501 (2127, Stair 2 S-1ST02) and FCU2501 (2133, Stair 3 S-1ST03); appended 2 AT tags (2822-2823 = AT-2501 Lobby S-1201, AT-2507 Female S-1204); corrected AT-0503 and AT-0505 rooms. A2.3: NO rows written - see details. Flagged 4 rows. | E11: Pre-read all three fill targets before writing this turn (lesson from turn 10) - all were genuinely blank. AT-0503 changed from NCIR Office S-1115 to Women S-1106B and AT-0505 from UPS S-1107D to Emergency Elec. S-1107B: A1.3 is the section that actually contains the S-1105/S-1106B/S-1107B core, AT-0502 already matched Vestibule S-1105, and 0502/0503/0505 form a clean sequence onto those three rooms. A2.3 yielded nothing appendable: every sensor box on it is an unnumbered 'TAG' with no tag ID, so there is nothing to key a registry row on. Separately, FCU-2004 appears SIX times on A2.3 (Stair 3 N-1ST03, Stair 4 N-1ST04, Normal Elec. N-1310, IDF N-1311, Mech/FPC N-1353A, Reception N-1355) all reading 25.3 C - one BMS point bound to six graphic boxes, so no new rows could be derived; flagged row 2708 instead. | F11: 8th pair complete and verified (rows 1646, 2127, 2133, 2708, 2711-2713, 2822-2824 re-read; flag fills confirmed). Next append row = 2824. OPEN QUESTION raised: moving AT-0503 to Women S-1106B leaves NCIR Office S-1115 with no sensor and VAV0509 (row 1569) still blank - the B1.1 tag I read as AT-0503 in that office may actually be AT-0509. Needs user confirmation before writing. Flagged: AT-0503, AT-0505, AT-2501, FCU2004. STILL OPEN from earlier turns: 21 blank NB GF VAV rows (1468, 1473-1490, 1543-1544) and conflicts at rows 1463/1465, 1485, 1517/1518, 1519, 1523/1526, 2085, 2119-2121, 1889, 1910/1923, 2132, 2073/2074.
A12: 12 | B12: 46245 | C12: Sent the 9th image pair — new: South Building Level 1 Section A1.2; old: North Building Level 1 Section B2.1. | D12: A1.2: filled 50 blank VAV rows (C/D 1647:1696 = VAV2502-VAV2553) and 4 FCU rows (2134-2137); appended 51 AT tags (2824-2874). B2.1: appended 79 rows (2875-2953) = 40 AT, 8 EV, 31 lab valves. 130 appended rows total. Flagged 22 rows yellow. | E12: Pre-read all 54 fill targets before writing - all confirmed blank, no overwrite. Verified fill alignment by spot-checking VAV2511=Office S-1212, VAV2536=Normal Elec. S-1251, VAV2553=Male Prayer S-1278 after the block write. B2.1 registry rooms matched the drawing throughout (VAV6650-6725 = N-1319 to N-1336, VAV6900-6970 = N-1357 to N-1371, VAV7865 = N-1461A), so those 34 AT twins inherited the registry room with no flags. VAV6630B/6631B were checked and already populated (Bio-Med Chem Lab 1 N-1316L) so were skipped, as were FCU6988/6989 which already read Service Corridor N-1337 and match the drawing. Corridor-run valves EV-6936/6961/6969 were assigned by the EV-pairs-with-VAV convention (Workstation N-1363/N-1368/N-1371) and flagged, since the dotted corridor they sit on carries no room number on this drawing. | F12: 9th pair complete and verified (rows 1647-1696, 2080-2081, 2134-2137, 2824-2954 re-read; 130 appended rows with no gaps; all 22 flag cells checked against tag names). Next append row = 2954. Flagged: AT-2502/2503/2505/2506 and VAV2502/2503/2505/2506 (four lobby-band sensors with no room label of their own - all assigned Lobby S-1202), AT-2552/VAV2552 (label appears twice on A1.2), AT-4260 (4000-series tag on a South Building drawing, assigned Men S-1254), FCU2502-2505, AT-7500, EV-7501, EV-6936/6961/6969, CEV-6581, FEV-6731. STILL OPEN: 21 blank NB GF VAV rows (1468, 1473-1490, 1543-1544); conflicts at rows 1463/1465, 1485, 1517/1518, 1519, 1523/1526, 2085, 2119-2121, 1889, 1910/1923, 2132, 2073/2074; and the AT-0503/AT-0509 vs NCIR Office S-1115 question (row 1569 still blank).
A13: 13 | B13: 46245 | C13: Sent the 10th image pair — new: South Building Level 1 Section A1.1; old: North Building Level 1 Section B2.2. | D13: A1.1: filled 20 blank VAV rows (C/D 1697:1717 = VAV3504-VAV3524, leaving VAV3519 blank) and FCU3501 (row 2138, Stair S-1ST104); appended 28 AT tags (2954-2981). B2.2: appended 58 rows (2982-3039) = 42 AT, 8 EV, 8 lab valves. 86 appended rows total. Flagged 15 rows yellow. | E13: Pre-read all 22 fill targets and aborted-on-conflict guard was in the code; all were blank so nothing was overwritten. Verified alignment after the block write (VAV3504=Open Plan S-1229, VAV3514=Office S-1294, VAV3519 blank, VAV3524=Normal Elec. S-1238). VAV3519 left blank - no AT-3519 on the drawing. There are no VAV rows for AT-3501/3502/3503 or for the 2301-AT-02xx BACnet points, so those were appended only. B2.2 registry rooms matched the drawing throughout (VAV7620-7710 = N-1415 to N-1442, VAV7840-7960 = N-1458 to N-1480, and the N-1404x / N-1450x lab series), so all 42 AT twins inherited the registry room. RESOLVED an earlier flag: row 2085 FCU7790 was flagged in turn 8 because it carries the NB_1F tag but appeared on a Level 0 drawing - B2.2 (Level 1) now shows FCU-7790 at Stair 6 N-1ST06, matching the registry, so the NB_1F assignment looks correct and the Level 0 sighting was a graphic repeat. All seven NB_1F FCU rows (2085-2091) were already populated and match B2.2, so none were touched. | F13: 10th pair complete and verified (rows 1697-1717, 2085-2091, 2138, 2954-3040 re-read; 86 appended rows with no gaps; all 15 flag cells checked against tag names). Next append row = 3040. Flagged: AT-3501 (sits under Lobby S-0294 which is a Level 0 room number on a Level 1 drawing), AT-3502, AT-3511/VAV3511, AT-3514/VAV3514 and AT-3520/VAV3520 (drawing carries TWO rooms labelled OFFICE S-1294 - one bottom-centre, one right of the stair), AT-0207/AT-0208, AT-7705 (registry room is just 'Expansion (Office)' with no number), EV-7663, EV-7712, CEV-7761, CEV-7791. NEW pre-existing issue spotted: rows 2034 and 2036 both give Flow Cyto N-1450C (VEV7751 and VEV7781) but the drawing puts VEV-7781 in iPS-TC N-1450F. STILL OPEN: 21 blank NB GF VAV rows (1468, 1473-1490, 1543-1544); conflicts at rows 1463/1465, 1485, 1517/1518, 1519, 1523/1526, 2119-2121, 1889, 1910/1923, 2132, 2073/2074, 2034/2036; and the AT-0503/AT-0509 vs NCIR Office S-1115 question (row 1569 still blank).
... A59: 55 | B59: 46261 | C59: User asked to re-run the validation of the QNL room/equipment mapping. | D59: Re-audited 'Controllable Asset Registry' A779:A1329 against column D of 'QNL Room Names with Equip.'. Read-only; no changes made. | E59: Source range in the column D TRANSPOSE(FILTER(...)) formulas has widened since the earlier audit, from A779:A1229 to A779:A1329, and now carries an if_empty argument returning "No Equipment in entity". Rooms in column A run to row 353 (352 entities) with matching formulas in D2:D353. Audited against the widened range: 551 asset tags, 537 with a non-blank column E entity. Also checked CAR rows below 1329 - 271 further assets exist but all carry SSC_ prefixed entities (different building), so ending the range at 1329 is correct and no QNL assets are excluded. | F59: Clean. 537 of 537 eligible assets placed in the correct room row; 0 unplaced, 0 misplaced, 0 orphans, 0 spill errors, no duplicate tags or duplicate room entities. 14 blank-entity assets correctly excluded with no leakage. 154 rooms legitimately show "No Equipment in entity".

Sheet HQ Asset Register
A1: EQUIPMENT ASSET REGISTER
A2: Tag No. | B2: Equipment Type | C2: Description | D2: Remarks
A3: AHU12_0001 | B3: AHU | C3: Air Handling Unit
A4: AHU12_0002 | B4: AHU | C4: Air Handling Unit
A5: AHU12_0003 | B5: AHU | C5: Air Handling Unit
A6: AHU12_0004 | B6: AHU | C6: Air Handling Unit | F6: EQUIPMENT COUNT SUMMARY
A7: AHU12_0006 | B7: AHU | C7: Air Handling Unit | F7: AHU | G7: =COUNTIF(B:B,"AHU") -> 26
A8: AHU12_0007 | B8: AHU | C8: Air Handling Unit | F8: FCU | G8: =COUNTIF(B:B,"FCU") -> 133
A9: AHU12_0008 | B9: AHU | C9: Air Handling Unit | F9: CHW Pump | G9: =COUNTIF(B:B,"CHW Pump") -> 4
A10: AHU12_0009 | B10: AHU | C10: Air Handling Unit | F10: Variable Air Volume | G10: =COUNTIF(B:B,"VAV") -> 602
A11: AHU12_0010 | B11: AHU | C11: Air Handling Unit | F11: DX Unit | G11: =COUNTIF(B:B,"DX Unit") -> 24
A12: AHU2_0001 | B12: AHU | C12: Air Handling Unit | F12: Heat Exchanger | G12: =COUNTIF(B:B,"HEX") -> 5
A13: AHU5_0001 | B13: AHU | C13: Air Handling Unit | F13: CCU | G13: =COUNTIF(B:B,"CCU") -> 11
A14: AHU5_0002 | B14: AHU | C14: Air Handling Unit | F14: EF | G14: =COUNTIF(B:B,"EF") -> 12
A15: AHU9_0001 | B15: AHU | C15: Air Handling Unit | F15: GEF | G15: =COUNTIF(B:B,"GEF") -> 13
A16: AHU9_0002 | B16: AHU | C16: Air Handling Unit | F16: TEF | G16: =COUNTIF(B:B,"TEF") -> 4
A17: AHU9_0003 | B17: AHU | C17: Air Handling Unit | F17: CEF | G17: =COUNTIF(B:B,"CEF") -> 60
A18: AHUB_0001 | B18: AHU | C18: Air Handling Unit | F18: SF | G18: =COUNTIF(B:B,"SF") -> 16
A19: AHUB_0002 | B19: AHU | C19: Air Handling Unit | F19: Generator | G19: =COUNTIF(B:B,"Generator") -> 2
A20: AHUB_0003 | B20: AHU | C20: Air Handling Unit | F20: TOTAL | G20: =SUM(G7:G19) -> 912
A21: AHUB_0004 | B21: AHU | C21: Air Handling Unit
A22: AHUB_0005 | B22: AHU | C22: Air Handling Unit
A23: AHUB_0006 | B23: AHU | C23: Air Handling Unit
A24: AHUB_0007 | B24: AHU | C24: Air Handling Unit
A25: AHUB_0008 | B25: AHU | C25: Air Handling Unit
A26: AHUB_0009 | B26: AHU | C26: Air Handling Unit
A27: AHUB_0010 | B27: AHU | C27: Air Handling Unit | F27: # | G27: Equipment type | H27: Tag(s) in IO list | I27: Assumption
A28: AHUB_0011 | B28: AHU | C28: Air Handling Unit | F28: 1 | G28: AHU | H28: AHU12_0010 | I28: These two tags refer to the same physical unit
A29: DX_B0001 | B29: DX Unit | C29: DX Unit - Interior | H29: AHU12_10
A30: DX_B0002 | B30: DX Unit | C30: DX Unit - Interior | F30: 2 | G30: AHU | H30: AHUB01_02 | I30: These two tags refer to the same physical unit
A31: DX_B0003 | B31: DX Unit | C31: DX Unit - Interior | H31: AHUB_0002
A32: DX_B0004 | B32: DX Unit | C32: DX Unit - Interior | F32: 3 | G32: AHU | H32: AHUB03_04 | I32: These two tags refer to the same physical unit
A33: DX_B0005 | B33: DX Unit | C33: DX Unit - Interior | H33: AHUB_0004
A34: DX_B0006 | B34: DX Unit | C34: DX Unit - Interior | F34: 4 | G34: AHU | H34: AHUB05_06 | I34: These two tags refer to the same physical unit
A35: DX_B0007 | B35: DX Unit | C35: DX Unit - Interior | H35: AHUB_0006
A36: DX_B0008 | B36: DX Unit | C36: DX Unit - Interior | F36: 5 | G36: AHU | H36: AHUB07 | I36: These two tags refer to the same physical unit
A37: DX_B0009 | B37: DX Unit | C37: DX Unit - Interior | H37: AHUB_0007
A38: DX_B0010 | B38: DX Unit | C38: DX Unit - Interior | F38: 6 | G38: AHU | H38: AHUB08 | I38: These two tags refer to the same physical unit
A39: DX_B0011 | B39: DX Unit | C39: DX Unit - Interior | H39: AHUB_0008
A40: DX_B0012 | B40: DX Unit | C40: DX Unit - Interior | F40: 7 | G40: AHU | H40: AHUB10 | I40: These two tags refer to the same physical unit
A41: DX_B0013 | B41: DX Unit | C41: DX Unit - Interior | H41: AHUB_0010
A42: DX_B0014 | B42: DX Unit | C42: DX Unit - Interior | F42: 8 | G42: AHU | H42: AHUB11 | I42: These two tags refer to the same physical unit
A43: DX_B0015 | B43: DX Unit | C43: DX Unit - Interior | H43: AHUB_0011
A44: DX_B0016 | B44: DX Unit | C44: DX Unit - Interior | F44: 9 | G44: DX Unit | H44: DX_ODSB0101 | I44: This DX unit was added later and not reflected in the HVAC Drawing
A45: DX_CP_0001 | B45: DX Unit | C45: DX Unit - Interior | F45: 10 | G45: DX Unit | H45: DX_ODSB0102 | I45: This DX unit was added later and not reflected in the HVAC Drawing
A46: DX_G0001 | B46: DX Unit | C46: DX Unit - Interior | F46: 11 | G46: DX Unit | H46: DX_ODSB0201 | I46: This DX unit was added later and not reflected in the HVAC Drawing
A47: DX_G0002 | B47: DX Unit | C47: DX Unit - Interior | F47: 12 | G47: DX Unit | H47: DX_ODSB0202 | I47: This DX unit was added later and not reflected in the HVAC Drawing
A48: DX_G0003 | B48: DX Unit | C48: DX Unit - Interior | F48: 13 | G48: DX Unit | H48: DX_CP_0001 | I48: This DX unit was added later and not reflected in the HVAC Drawing
A49: DX_ODSB0101 | B49: DX Unit | C49: DX Unit - Exterior
A50: DX_ODSB0102 | B50: DX Unit | C50: DX Unit - Exterior
A51: DX_ODSB0201 | B51: DX Unit | C51: DX Unit - Exterior
A52: DX_ODSB0202 | B52: DX Unit | C52: DX Unit - Exterior
A53: FCU0001 | B53: FCU | C53: Fan Coil Unit
A54: FCU0002 | B54: FCU | C54: Fan Coil Unit
A55: FCU0003 | B55: FCU | C55: Fan Coil Unit
A56: FCU0004 | B56: FCU | C56: Fan Coil Unit
A57: FCU0005 | B57: FCU | C57: Fan Coil Unit
A58: FCU0006 | B58: FCU | C58: Fan Coil Unit
A59: FCU0007 | B59: FCU | C59: Fan Coil Unit
A60: FCU0008 | B60: FCU | C60: Fan Coil Unit
... A914: ELEC_Gen3 | B914: Generator | C914: Generator

Sheet QNL Asset Register
A1: EQUIPMENT ASSET REGISTER
A2: Tag No. | B2: Equipment Type | C2: Description | D2: Remarks
A3: AHUB001 | B3: AHU | C3: Air Handling Unit
A4: AHUB002 | B4: AHU | C4: Air Handling Unit
A5: AHUB003 | B5: AHU | C5: Air Handling Unit
A6: AHUB004 | B6: AHU | C6: Air Handling Unit | H6: EQUIPMENT COUNT SUMMARY
A7: AHUB005 | B7: AHU | C7: Air Handling Unit | H7: AHU | I7: =COUNTIF(B:B,"AHU") -> 15
A8: AHUB006 | B8: AHU | C8: Air Handling Unit | H8: FCU | I8: =COUNTIF(B:B,"FCU") -> 137
A9: AHUB007 | B9: AHU | C9: Air Handling Unit | H9: CHW Pump | I9: =COUNTIF(B:B,"CHW Pump") -> 6
A10: AHUB008 | B10: AHU | C10: Air Handling Unit | H10: Variable Air Volume | I10: =COUNTIF(B:B,"VAV") -> 248
A11: AHUB009 | B11: AHU | C11: Air Handling Unit | H11: Constant Air Volume | I11: =COUNTIF(B:B,"CAV") -> 51
A12: AHUB010 | B12: AHU | C12: Air Handling Unit | H12: DX Unit | I12: =COUNTIF(B:B,"DX Unit") -> 24
A13: AHUB011 | B13: AHU | C13: Air Handling Unit | H13: Heat Exchanger | I13: =COUNTIF(B:B,"HEX") -> 5
A14: AHUB012 | B14: AHU | C14: Air Handling Unit | H14: CCU | I14: =COUNTIF(B:B,"CCU") -> 22
A15: AHUB013 | B15: AHU | C15: Air Handling Unit | H15: EF | I15: =COUNTIF(B:B,"EF") -> 18
A16: AHUB014 | B16: AHU | C16: Air Handling Unit | H16: SEF | I16: =COUNTIF(B:B,"SEF") -> 12
A17: AHUB015 | B17: AHU | C17: Air Handling Unit | H17: TEF | I17: =COUNTIF(B:B,"TEF") -> 8
A18: DX_B01 | B18: DX Unit | C18: DX Unit | H18: KEF | I18: =COUNTIF(B:B,"KEF") -> 4
A19: DX_B02 | B19: DX Unit | C19: DX Unit | H19: Generator | I19: =COUNTIF(B:B,"Generator") -> 1
A20: DX_B03 | B20: DX Unit | C20: DX Unit | H20: TOTAL | I20: =SUM(I7:I18) -> 550
A21: DX_B04 | B21: DX Unit | C21: DX Unit
A22: DX_B05 | B22: DX Unit | C22: DX Unit
A23: DX_B06 | B23: DX Unit | C23: DX Unit
A24: DX_B07 | B24: DX Unit | C24: DX Unit | H24: # | I24: Equipment type | J24: Tag(s) in IO list | K24: Assumption
A25: DX_B08 | B25: DX Unit | C25: DX Unit | H25: 1 | I25: EF | J25: EF_RP001 | K25: This is the same asset as : EF_RP01
A26: DX_B09 | B26: DX Unit | C26: DX Unit | H26: 2 | I26: EF | J26: EF_RP002 | K26: This is the same asset as : EF_RP02
A27: DX_B10 | B27: DX Unit | C27: DX Unit | H27: 3 | I27: EF | J27: EF_RP003 | K27: This is the same asset as : EF_RP03
A28: DX_B11 | B28: DX Unit | C28: DX Unit | H28: 4 | I28: EF | J28: EF_B009 | K28: This is the same asset as : EF_B09
A29: DX_B12 | B29: DX Unit | C29: DX Unit | H29: 5 | I29: EF | J29: EF_B011 | K29: This is the same asset as : EF_B11
A30: DX_B13 | B30: DX Unit | C30: DX Unit | H30: 6 | I30: DX Unit | J30: DX_B0010 | K30: This is the same asset as : DX_B10
A31: DX_B14 | B31: DX Unit | C31: DX Unit | H31: 7 | I31: DX Unit | J31: DX_B0011 | K31: This is the same asset as : DX_B11
A32: DX_B15 | B32: DX Unit | C32: DX Unit | H32: 8 | I32: DX Unit | J32: DX_B0012 | K32: This is the same asset as : DX_B12
A33: DX_B16 | B33: DX Unit | C33: DX Unit | H33: 9 | I33: DX Unit | J33: DX_B0020 | K33: This is the same asset as : DX_B20
A34: DX_B17 | B34: DX Unit | C34: DX Unit | H34: 10 | I34: DX Unit | J34: DX_B022 | K34: This is the same asset as : DX_B21
A35: DX_B18 | B35: DX Unit | C35: DX Unit | H35: 11 | I35: DX Unit | J35: DX_B023 | K35: This is the same asset as : DX_B22
A36: DX_B19 | B36: DX Unit | C36: DX Unit | H36: 12 | I36: DX Unit | J36: DX_B22 | K36: This DX unit was added later and not reflected in the HVAC Drawing
... A38: DX_B21 | B38: DX Unit | C38: DX Unit | H38: 14 | I38: DX Unit | J38: DX_B24 | K38: This DX unit was added later and not reflected in the HVAC Drawing
A39: DX_B22 | B39: DX Unit | C39: DX Unit | D39: This asset is available in the Local and SWS SCADA but not in the HVAC Drawings | H39: 15 | I39: HEX | J39: HEX05 | K39: This Heat Exchanger was added later and not reflecteed in the HVAC Drawing
A40: DX_B23 | B40: DX Unit | C40: DX Unit | D40: This asset is available in the Local and SWS SCADA but not in the HVAC Drawings | H40: 16 | I40: CCU | J40: CCU_AVServer_Rm | K40: This CCU is available in the Local SCADA but not configures in the SWS
A41: DX_B24 | B41: DX Unit | C41: DX Unit | D41: This asset is available in the Local and SWS SCADA but not in the HVAC Drawings
A42: FCU_1F_001 | B42: FCU | C42: Fan Coil Unit
A43: FCU_1F_002 | B43: FCU | C43: Fan Coil Unit
A44: FCU_1F_003 | B44: FCU | C44: Fan Coil Unit
A45: FCU_1F_004 | B45: FCU | C45: Fan Coil Unit
A46: FCU_1F_005 | B46: FCU | C46: Fan Coil Unit
A47: FCU_1F_006 | B47: FCU | C47: Fan Coil Unit
A48: FCU_1F_007 | B48: FCU | C48: Fan Coil Unit
A49: FCU_1F_008 | B49: FCU | C49: Fan Coil Unit
A50: FCU_1F_009 | B50: FCU | C50: Fan Coil Unit
A51: FCU_1F_010 | B51: FCU | C51: Fan Coil Unit
A52: FCU_1F_011 | B52: FCU | C52: Fan Coil Unit
A53: FCU_1F_012 | B53: FCU | C53: Fan Coil Unit
... A182: HEX04 | B182: HEX | C182: Heat Exchanger
A183: HEX05 | B183: HEX | C183: Heat Exchanger | D183: This asset is available in the Local and SWS SCADA but not in the HVAC Drawings
A184: VAV0001 | B184: VAV | C184: Variable Air Volume
A185: VAV_1F_S11_001 | B185: VAV | C185: Variable Air Volume
A186: VAV_1F_S11_002 | B186: VAV | C186: Variable Air Volume
A187: VAV_1F_S11_003 | B187: VAV | C187: Variable Air Volume
A188: VAV_1F_S11_004 | B188: VAV | C188: Variable Air Volume
A189: VAV_1F_S11_005 | B189: VAV | C189: Variable Air Volume
A190: VAV_1F_S11_006 | B190: VAV | C190: Variable Air Volume
A191: VAV_1F_S11_007 | B191: VAV | C191: Variable Air Volume
A192: VAV_1F_S11_008 | B192: VAV | C192: Variable Air Volume
A193: VAV_1F_S11_009 | B193: VAV | C193: Variable Air Volume
A194: VAV_1F_S11_010 | B194: VAV | C194: Variable Air Volume
A195: VAV_1F_S11_011 | B195: VAV | C195: Variable Air Volume
... A544: CCU_Server_Rm | B544: CCU | C544: CCU
A545: CCU_AVServer_Rm | B545: CCU | C545: CCU | D545: This Asset is available in Local SCADA but not in SWS (Historian)
A546: CCU_HeritageVault | B546: CCU | C546: CCU
A547: CHW_P01 | B547: CHW Pump | C547: Primary CHW Pumps
A548: CHW_P02 | B548: CHW Pump | C548: Primary CHW Pumps
A549: CHW_P03 | B549: CHW Pump | C549: Primary CHW Pumps
A550: CHW_P04 | B550: CHW Pump | C550: Primary CHW Pumps
A551: CHWPU_P01 | B551: CHW Pump | C551: Chilled Water Pressurization Unit Pump
A552: CHWPU_P02 | B552: CHW Pump | C552: Chilled Water Pressurization Unit Pump
A553: ELEC_Gen | B553: Generator | C553: Generator

Sheet SSC Asset Register
A1: EQUIPMENT ASSET REGISTER
A2: Tag No. | B2: Equipment Type | C2: Description | D2: Remarks
A3: AHUB_0001 | B3: AHU | C3: Air Handling Unit
A4: AHUB_0002 | B4: AHU | C4: Air Handling Unit
A5: AHUB_0003 | B5: AHU | C5: Air Handling Unit
A6: AHUB_0004 | B6: AHU | C6: Air Handling Unit | F6: EQUIPMENT COUNT SUMMARY
A7: AHUB_0005 | B7: AHU | C7: Air Handling Unit | F7: AHU | G7: =COUNTIF(B:B,"AHU") -> 5
A8: FCU0001 | B8: FCU | C8: Fan Coil Unit | F8: FCU | G8: =COUNTIF(B:B,"FCU") -> 11
A9: FCU0002 | B9: FCU | C9: Fan Coil Unit | F9: CHW Pump | G9: =COUNTIF(B:B,"CHW Pump") -> 8
A10: FCU0003 | B10: FCU | C10: Fan Coil Unit | F10: Variable Air Volume | G10: =COUNTIF(B:B,"VAV") -> 108
A11: FCU0004 | B11: FCU | C11: Fan Coil Unit | F11: DX Unit | G11: =COUNTIF(B:B,"DX Unit") -> 10
A12: FCU0005 | B12: FCU | C12: Fan Coil Unit | F12: Heat Exchanger | G12: =COUNTIF(B:B,"HEX") -> 5
A13: FCU0006 | B13: FCU | C13: Fan Coil Unit | F13: CCU | G13: =COUNTIF(B:B,"CCU") -> 14
A14: FCU0007 | B14: FCU | C14: Fan Coil Unit | F14: EF | G14: =COUNTIF(B:B,"EF") -> 1
A15: FCU0008 | B15: FCU | C15: Fan Coil Unit | F15: KEF | G15: =COUNTIF(B:B,"KEF") -> 2
A16: FCU0009 | B16: FCU | C16: Fan Coil Unit | F16: TEF | G16: =COUNTIF(B:B,"TEF") -> 4
A17: FCU0010 | B17: FCU | C17: Fan Coil Unit | F17: GEF | G17: =COUNTIF(B:B,"GEF") -> 1
A18: FCU0011 | B18: FCU | C18: Fan Coil Unit | F18: Generator | G18: =COUNTIF(B:B,"Generator") -> 1
A19: VAV0001 | B19: VAV | C19: Variable Air Volume | F19: TOTAL | G19: =SUM(G7:G18) -> 170
A20: VAV0002 | B20: VAV | C20: Variable Air Volume
A21: VAV0003 | B21: VAV | C21: Variable Air Volume
A22: VAV0004 | B22: VAV | C22: Variable Air Volume
A23: VAV0005 | B23: VAV | C23: Variable Air Volume
A24: VAV0006 | B24: VAV | C24: Variable Air Volume
A25: VAV0007 | B25: VAV | C25: Variable Air Volume
A26: VAV0008 | B26: VAV | C26: Variable Air Volume | F26: # | G26: Equipment type | H26: Tag(s) in IO list | I26: Assumption
A27: VAV0009 | B27: VAV | C27: Variable Air Volume | F27: 1 | G27: DX Unit | H27: DX/B/11 | I27: This DX unit is not available in I/O (Local and SWS) but available in the drawings
A28: VAV0010 | B28: VAV | C28: Variable Air Volume | F28: 2 | G28: DX Unit | H28: DX/B/12 | I28: This DX unit is not available in I/O (Local and SWS) but available in the drawings
A29: VAV0011 | B29: VAV | C29: Variable Air Volume | F29: 3 | G29: DX Unit | H29: DX/B/13 | I29: This DX unit is not available in I/O (Local and SWS) but available in the drawings
A30: VAV0012 | B30: VAV | C30: Variable Air Volume | F30: 4 | G30: DX Unit | H30: DX/B/14 | I30: This DX unit is not available in I/O (Local and SWS) but available in the drawings
A31: VAV0013 | B31: VAV | C31: Variable Air Volume | F31: 5 | G31: DX Unit | H31: DX/B/15 | I31: This DX unit is not available in I/O (Local and SWS) but available in the drawings
A32: VAV0014 | B32: VAV | C32: Variable Air Volume | F32: 6 | G32: DX Unit | H32: DX/B/16 | I32: This DX unit is not available in I/O (Local and SWS) but available in the drawings
A33: VAV0015 | B33: VAV | C33: Variable Air Volume | F33: 7 | G33: DX Unit | H33: DX/1/01 | I33: This DX unit is not available in I/O (Local and SWS) but available in the drawings
A34: VAV0016 | B34: VAV | C34: Variable Air Volume | F34: 8 | G34: DX Unit | H34: DX/1/02 | I34: This DX unit is not available in I/O (Local and SWS) but available in the drawings
A35: VAV0017 | B35: VAV | C35: Variable Air Volume | F35: 9 | G35: DX Unit | H35: DX/1/03 | I35: This DX unit is not available in I/O (Local and SWS) but available in the drawings
A36: VAV0018 | B36: VAV | C36: Variable Air Volume
A37: VAV0019 | B37: VAV | C37: Variable Air Volume
A38: VAV0020 | B38: VAV | C38: Variable Air Volume
A39: VAV0021 | B39: VAV | C39: Variable Air Volume
A40: VAV0022 | B40: VAV | C40: Variable Air Volume
A41: VAV0023 | B41: VAV | C41: Variable Air Volume
A42: VAV0024 | B42: VAV | C42: Variable Air Volume
A43: VAV0025 | B43: VAV | C43: Variable Air Volume
A44: VAV0026 | B44: VAV | C44: Variable Air Volume
A45: VAV0027 | B45: VAV | C45: Variable Air Volume
A46: VAV0028 | B46: VAV | C46: Variable Air Volume
A47: VAV0029 | B47: VAV | C47: Variable Air Volume
... A172: REF0001 | B172: EF | C172: Extract Fan

Sheet RDC Asset Register
A1: EQUIPMENT ASSET REGISTER
A2: Tag No. | B2: Equipment Type | C2: Description | D2: Remarks
A3: NB_AHU8511 | B3: AHU | C3: Air Handling Unit
A4: NB_AHU8512 | B4: AHU | C4: Air Handling Unit
A5: NB_AHU8513 | B5: AHU | C5: Air Handling Unit
A6: NB_AHU8514 | B6: AHU | C6: Air Handling Unit | H6: EQUIPMENT COUNT SUMMARY
A7: NB_AHU8515 | B7: AHU | C7: Air Handling Unit | H7: AHU | I7: =COUNTIF(B:B,"AHU") -> 37
A8: NB_AHU8516 | B8: AHU | C8: Air Handling Unit | H8: ERU | I8: =COUNTIF(B:B,"ERU") -> 11
A9: NB_AHU8517 | B9: AHU | C9: Air Handling Unit | H9: FCU | I9: =COUNTIF(B:B,"FCU") -> 135
A10: NB_AHU8518 | B10: AHU | C10: Air Handling Unit | H10: CHW Pump | I10: =COUNTIF(B:B,"CHW Pump") -> 9
A11: NB_AHU8519 | B11: AHU | C11: Air Handling Unit | H11: Variable Air Volume | I11: =COUNTIF(B:B,"VAV") -> 739
A12: NB_AHU8520 | B12: AHU | C12: Air Handling Unit | H12: Constant Air Volume | I12: =COUNTIF(B:B,"CAV") -> 78
A13: NB_AHU8521 | B13: AHU | C13: Air Handling Unit | H13: FEV | I13: =COUNTIF(B:B,"FEV") -> 76
A14: RDC_NB_ERU8531 | B14: ERU | C14: ERU | H14: VEV | I14: =COUNTIF(B:B,"VEV") -> 44
A15: RDC_NB_ERU8532 | B15: ERU | C15: ERU | H15: EAV | I15: =COUNTIF(B:B,"EAV") -> 51
A16: RDC_NB_ERU8533 | B16: ERU | C16: ERU | H16: Heat Exchanger | I16: =COUNTIF(B:B,"HEX") -> 7
A17: RDC_NB_ERU8534 | B17: ERU | C17: ERU | H17: EF | I17: =COUNTIF(B:B,"EF") -> 38
A18: RDC_NB_ERU8535 | B18: ERU | C18: ERU | H18: Generator | I18: =COUNTIF(B:B,"Generator") -> 3
A19: RDC_NB_ERU8536 | B19: ERU | C19: ERU | H19: TOTAL | I19: =SUM(I7:I18) -> 1228
A20: RDC_NB_ERU8537 | B20: ERU | C20: ERU
A21: RDC_NB_ERU8538 | B21: ERU | C21: ERU
A22: RDC_NB_ERU8539 | B22: ERU | C22: ERU
A23: RDC_NB_ERU8540 | B23: ERU | C23: ERU
A24: RDC_NB_ERU8541 | B24: ERU | C24: ERU
A25: RDC_SB_AHU8011 | B25: AHU | C25: Air Handling Unit
A26: RDC_SB_AHU8012 | B26: AHU | C26: Air Handling Unit
A27: RDC_SB_AHU8021 | B27: AHU | C27: Air Handling Unit
A28: RDC_SB_AHU8022 | B28: AHU | C28: Air Handling Unit
A29: RDC_SB_AHU8023 | B29: AHU | C29: Air Handling Unit | H29: # | I29: Equipment type | J29: Tag(s) in IO list | K29: Assumption
A30: RDC_SB_AHU8024 | B30: AHU | C30: Air Handling Unit | H30: 1 | I30: DX Unit | J30: RDC_UB_AHU8603_DXUnit | K30: This is the DX coil/compressor of AHU8603
A31: RDC_SB_AHU8025 | B31: AHU | C31: Air Handling Unit | H31: 2 | I31: DX Unit | J31: RDC_UB_AHU8604_DXUnit | K31: This is the DX coil/compressor of AHU8604
A32: RDC_SB_AHU8026 | B32: AHU | C32: Air Handling Unit | H32: 3 | I32: DX Unit | J32: RDC_UB_AHU8605_DXUnit | K32: This is the DX coil/compressor of AHU8605
A33: RDC_SB_AHU8031 | B33: AHU | C33: Air Handling Unit | H33: 4 | I33: DX Unit | J33: RDC_UB_AHU8606_DXUnit | K33: This is the DX coil/compressor of AHU8606
A34: RDC_SB_AHU8032 | B34: AHU | C34: Air Handling Unit | H34: 5 | I34: DX Unit | J34: RDC_UB_AHU8607_DXUnit | K34: This is the DX coil/compressor of AHU8607
A35: RDC_SB_AHU8033 | B35: AHU | C35: Air Handling Unit | H35: 6 | I35: DX Unit | J35: RDC_UB_AHU8608_DXUnit | K35: This is the DX coil/compressor of AHU8608
A36: RDC_SB_AHU8034 | B36: AHU | C36: Air Handling Unit | H36: 7 | I36: DX Unit | J36: RDC_UB_AHU8609_DXUnit | K36: This is the DX coil/compressor of AHU8609
A37: RDC_SB_AHU8035 | B37: AHU | C37: Air Handling Unit | H37: 8 | I37: EF | J37: RDC_SB_BUS_EFA1 | K37: Extract fans serving the bus station
A38: RDC_SB_AHU8036 | B38: AHU | C38: Air Handling Unit | H38: 9 | I38: EF | J38: RDC_SB_BUS_EFA2 | K38: Extract fans serving the bus station
A39: RDC_SB_AHU8037 | B39: AHU | C39: Air Handling Unit | H39: 10 | I39: EF | J39: RDC_SB_BUS_EFA3 | K39: Extract fans serving the bus station
A40: RDC_SB_AHU8041 | B40: AHU | C40: Air Handling Unit | H40: 11 | I40: EF | J40: RDC_SB_BUS_EFA4 | K40: Extract fans serving the bus station
A41: RDC_SB_AHU8042 | B41: AHU | C41: Air Handling Unit | H41: 12 | I41: EF | J41: RDC_SB_BUS_EFA5 | K41: Extract fans serving the bus station
... A56: RDC_NB_EF8552 | B56: EF | C56: EF | H56: 27 | I56: EF | J56: RDC_SB_BUS_EFD2 | K56: Extract fans serving the bus station
A57: RDC_NB_EF8553 | B57: EF | C57: EF
A58: RDC_NB_EF8554 | B58: EF | C58: EF
A59: RDC_SB_EF8041 | B59: EF | C59: EF
A60: RDC_SB_EF8042 | B60: EF | C60: EF
A61: RDC_SB_EF8043 | B61: EF | C61: EF
A62: RDC_SB_EF8044 | B62: EF | C62: EF
A63: RDC_SB_BUS_EFA1 | B63: EF | C63: EF
A64: RDC_SB_BUS_EFA2 | B64: EF | C64: EF
A65: RDC_SB_BUS_EFA3 | B65: EF | C65: EF
A66: RDC_SB_BUS_EFA4 | B66: EF | C66: EF
A67: RDC_SB_BUS_EFA5 | B67: EF | C67: EF
A68: RDC_SB_BUS_EFA6 | B68: EF | C68: EF
... A1230: RDC_NB_GF_FEV7262 | B1230: FEV | C1230: FEV

Sheet Controllable Asset Registry
A1: Controllable Asset Registry
A2: Tag No. | B2: Equipment Type | C2: Inluded/ Not Inlcuded | D2: ROOM NAME AS PER DRAWINGS | H2: ROOM NAME PER VAV / FCU LIST (WHERE DIFFERENT) | J2: ROOM PER BMS SCREEN | K2: BMS SCREEN (IMAGE FILE)
A3: QNL
A4: AHUB001 | B4: AHU | C4: Not Included | D4: Basement Level Zone 4 Plant Room 4 B.220 | E4: entity:QNL_B_220_PLANT_ROOM_04
A5: AHUB002 | B5: AHU | C5: Not Included | D5: Basement Level Zone 1 Plant Room 1 B.063 | E5: entity:QNL_B_063_PLANT_ROOM_01
A6: AHUB003 | B6: AHU | C6: Not Included | D6: Basement Level Zone 1 Plant Room 2 B.070 | E6: entity:QNL_B_070_PLANT_ROOM_02
A7: AHUB004 | B7: AHU | C7: Not Included | D7: Basement Level Zone 2 Plant Room 3 B.110 | E7: entity:QNL_B_110_PLANT_ROOM_03
A8: AHUB005 | B8: AHU | C8: Not Included | D8: Basement Level Zone 4 Plant Room 4 B.220 | E8: entity:QNL_B_220_PLANT_ROOM_04
A9: AHUB006 | B9: AHU | C9: Not Included | D9: Basement Level Zone 4 Plant Room 4 B.220 | E9: entity:QNL_B_220_PLANT_ROOM_04
A10: AHUB007 | B10: AHU | C10: Not Included | D10: Basement Level Zone 4 Plant Room 4 B.220 | E10: entity:QNL_B_220_PLANT_ROOM_04
A11: AHUB008 | B11: AHU | C11: Not Included | D11: Basement Level Zone 4 Plant Room 4 B.220 | E11: entity:QNL_B_220_PLANT_ROOM_04
A12: AHUB009 | B12: AHU | C12: Not Included | D12: Basement Level Zone 2 Plant Room 3 B.110 | E12: entity:QNL_B_110_PLANT_ROOM_03
A13: AHUB010 | B13: AHU | C13: Not Included | D13: Basement Level Zone 1 Plant Room 2 B.070 | E13: entity:QNL_B_070_PLANT_ROOM_02
A14: AHUB011 | B14: AHU | C14: Not Included | D14: Basement Level Zone 1 Plant Room 1 B.063 | E14: entity:QNL_B_063_PLANT_ROOM_01
A15: AHUB012 | B15: AHU | C15: Not Included | D15: Basement Level Zone 1 Plant Room 1 B.063 | E15: entity:QNL_B_063_PLANT_ROOM_01
... A20: FCU_1F_002 | B20: FCU | C20: Included | D20: ICT Room 02 L1.030 | E20: entity:QNL_L1_030_ICT_ROOM_02
A21: FCU_1F_003 | B21: FCU | C21: Not Included | D21: IDF Room 02 L1.099 | E21: entity:QNL_L1_099_IDF_ROOM_02 | J21: IDF Rm | K21: QNL/FF-2.jpg
A22: FCU_1F_004 | B22: FCU | C22: Included | D22: BRIDGE CEILING VOID L1.BR6 | E22: entity:QNL_L1_BR6_BRIDGE_CEILING_VOID
A23: FCU_1F_005 | B23: FCU | C23: Included | D23: BRIDGE CEILING VOID L1.BR6 | E23: entity:QNL_L1_BR6_BRIDGE_CEILING_VOID
A24: FCU_1F_006 | B24: FCU | C24: Included | D24: BRIDGE CEILING VOID L1.BR6 | E24: entity:QNL_L1_BR6_BRIDGE_CEILING_VOID
A25: FCU_1F_007 | B25: FCU | C25: Included | D25: BRIDGE CEILING VOID L1.BR6 | E25: entity:QNL_L1_BR6_BRIDGE_CEILING_VOID
A26: FCU_1F_008 | B26: FCU | C26: Included | D26: BRIDGE CEILING VOID L1.BR6 | E26: entity:QNL_L1_BR6_BRIDGE_CEILING_VOID
A27: FCU_1F_009 | B27: FCU | C27: Included | D27: BRIDGE CEILING VOID L1.BR5 | E27: entity:QNL_L1_BR5_BRIDGE_CEILING_VOID
A28: FCU_1F_010 | B28: FCU | C28: Included | D28: BRIDGE CEILING VOID L1.BR5 | E28: entity:QNL_L1_BR5_BRIDGE_CEILING_VOID
A29: FCU_1F_011 | B29: FCU | C29: Included | D29: BRIDGE CEILING VOID L1.BR5 | E29: entity:QNL_L1_BR5_BRIDGE_CEILING_VOID
A30: FCU_1F_012 | B30: FCU | C30: Included | D30: BRIDGE CEILING VOID L1.BR5 | E30: entity:QNL_L1_BR5_BRIDGE_CEILING_VOID
A31: FCU_1F_013 | B31: FCU | C31: Included | D31: BRIDGE CEILING VOID L1.BR6 | E31: entity:QNL_L1_BR6_BRIDGE_CEILING_VOID
A32: FCU_1F_014 | B32: FCU | C32: Included | D32: BRIDGE CEILING VOID L1.BR4 | E32: entity:QNL_L1_BR4_BRIDGE_CEILING_VOID
A33: FCU_1F_015 | B33: FCU | C33: Included | D33: BRIDGE CEILING VOID L1.BR6 | E33: entity:QNL_L1_BR6_BRIDGE_CEILING_VOID
... A77: FCU_1F_059 | B77: FCU | C77: Included | D77: Restaurant L1.150 | E77: entity:QNL_L1_150_RESTAURANT
A78: FCU_1F_060 | B78: FCU | C78: Included | D78: Restaurant L1.150 | E78: entity:QNL_L1_150_RESTAURANT | J78: Restaurant | K78: QNL/FF-2.jpg
A79: FCU_1F_061 | B79: FCU | C79: Included | D79: Restaurant L1.150 | E79: entity:QNL_L1_150_RESTAURANT | J79: Restaurant | K79: QNL/FF-2.jpg
A80: FCU_1F_062 | B80: FCU | C80: Included | D80: Restaurant L1.150 | E80: entity:QNL_L1_150_RESTAURANT
A81: FCU_1F_063 | B81: FCU | C81: Included | D81: Restaurant L1.150 | E81: entity:QNL_L1_150_RESTAURANT
A82: FCU_1F_064 | B82: FCU | C82: Included | D82: Restaurant L1.150 | E82: entity:QNL_L1_150_RESTAURANT | J82: Restaurant | K82: QNL/FF-2.jpg
A83: FCU_1F_065 | B83: FCU | C83: Not Included | D83: BRIDGE IDF L1.BI | E83: entity:QNL_L1_BI_BRIDGE_IDF
A84: FCU_2F_001 | B84: FCU | C84: Not Included | D84: IDF ROOM T1.275 | E84: entity:QNL_T1_275_IDF_ROOM
A85: FCU_2F_002 | B85: FCU | C85: Not Included | D85: IDF ROOM T1.276 | E85: entity:QNL_T1_276_IDF_ROOM
A86: FCU_2F_003 | B86: FCU | C86: Not Included | D86: IDF ROOM T1.171 | E86: entity:QNL_T1_171_IDF_ROOM
A87: FCU_2F_004 | B87: FCU | C87: Not Included | D87: IDF ROOM T1.1714 | E87: entity:QNL_T1_1714_IDF_ROOM
A88: FCU_2F_005 | B88: FCU | C88: Not Included | D88: MDF Room L2.009 | E88: entity:QNL_L2_009_KDF_ROOM
A89: FCU_2F_034 | B89: FCU | C89: Included | D89: Auditorium High Levlel in Ceiling Void L2.087 | E89: entity:QNL_L2_087_AUDITORIUM_HIGH_LEVLEL_IN_CEILING_VOID | J89: Auditorium | K89: QNL/SF-6.jpg
A90: FCU_2F_035 | B90: FCU | C90: Included | D90: Auditorium High Levlel in Ceiling Void L2.087 | E90: entity:QNL_L2_087_AUDITORIUM_HIGH_LEVLEL_IN_CEILING_VOID | J90: Auditorium | K90: QNL/SF-6.jpg
A91: FCU_2F_036 | B91: FCU | C91: Included | D91: Auditorium High Levlel in Ceiling Void L2.087 | E91: entity:QNL_L2_087_AUDITORIUM_HIGH_LEVLEL_IN_CEILING_VOID | J91: Auditorium | K91: QNL/SF-6.jpg
A92: FCU_2F_037 | B92: FCU | C92: Included | D92: Auditorium High Levlel in Ceiling Void L2.087 | E92: entity:QNL_L2_087_AUDITORIUM_HIGH_LEVLEL_IN_CEILING_VOID
A93: FCU_2F_038 | B93: FCU | C93: Included | D93: Auditorium Booths L2.087 | E93: entity:QNL_L2_087_AUDITORIUM_HIGH_LEVLEL_IN_CEILING_VOID
A94: FCU_2F_039 | B94: FCU | C94: Included | D94: Auditorium Booths L2.087 | E94: entity:QNL_L2_087_AUDITORIUM_HIGH_LEVLEL_IN_CEILING_VOID
A95: FCU_2F_040 | B95: FCU | C95: Included | D95: Auditorium Booths L2.087 | E95: entity:QNL_L2_087_AUDITORIUM_HIGH_LEVLEL_IN_CEILING_VOID
A96: FCU_2F_041 | B96: FCU | C96: Included | D96: Bridge Raised Floor L2.088 | E96: entity:QNL_L2_088_BRIDGE_RAISED_FLOOR
A97: FCU_2F_042 | B97: FCU | C97: Included | D97: STUDY AREA L2.088 | E97: entity:QNL_L2_088_BRIDGE_RAISED_FLOOR
A98: FCU_2F_043 | B98: FCU | C98: Included | D98: Bridge L2.088 | E98: entity:QNL_L2_088_BRIDGE_RAISED_FLOOR
A99: FCU_2F_044 | B99: FCU | C99: Included | D99: Bridge L2.088 | E99: entity:QNL_L2_088_BRIDGE_RAISED_FLOOR
A100: FCU_2F_045 | B100: FCU | C100: Included | D100: Group Study Room L2.081 | E100: entity:QNL_L2_081_GROUP_STUDY_ROOM | J100: Group Study Rm | K100: QNL/SF-6.jpg
A101: FCU_2F_046 | B101: FCU | C101: Included | D101: Group Study Room L2.076 | E101: entity:QNL_L2_076_GROUP_STUDY_ROOM | J101: Group Study Rm | K101: QNL/SF-6.jpg
A102: FCU_2F_047 | B102: FCU | C102: Included | D102: Group Study Room L2.076 | E102: entity:QNL_L2_076_GROUP_STUDY_ROOM | J102: Group Study Rm | K102: QNL/SF-6.jpg
A103: FCU_2F_048 | B103: FCU | C103: Included | D103: INDIVIDUAL STUDY ROOM L2.070 | E103: entity:QNL_L2_070_INDIVISTUDY_ROOM
A104: FCU_2F_049 | B104: FCU | C104: Included | D104: INDIVIDUAL STUDY ROOM L2.070 | E104: entity:QNL_L2_070_INDIVISTUDY_ROOM | J104: Indv. Study Rm | K104: QNL/SF-6.jpg
A105: FCU_2F_050 | B105: FCU | C105: Included | D105: INDIVIDUAL STUDY ROOM L2.070 | E105: entity:QNL_L2_070_INDIVISTUDY_ROOM | J105: Indv. Study Rm | K105: QNL/SF-6.jpg
A106: FCU_2F_051 | B106: FCU | C106: Included | D106: INDIVIDUAL STUDY ROOM L2.073 | E106: entity:QNL_L2_073_INDIVISTUDY_ROOM | J106: Indv. Study Rm | K106: QNL/SF-6.jpg
A107: FCU_2F_052 | B107: FCU | C107: Included | D107: INDIVIDUAL STUDY ROOM L2.073 | E107: entity:QNL_L2_073_INDIVISTUDY_ROOM | J107: Indv. Study Rm | K107: QNL/SF-6.jpg
A108: FCU_2F_053 | B108: FCU | C108: Included | D108: INDIVIDUAL STUDY ROOM L2.073 | E108: entity:QNL_L2_073_INDIVISTUDY_ROOM
A109: FCU_2F_054 | B109: FCU | C109: Included | D109: Lounge Area L2.088 | E109: entity:QNL_L2_088_LOUNGE_AREA | J109: Lounge area | K109: QNL/SF-6.jpg
A110: FCU_2F_055 | B110: FCU | C110: Included | D110: Lounge Area L2.088 | E110: entity:QNL_L2_088_LOUNGE_AREA | J110: Lounge area | K110: QNL/SF-6.jpg
A111: FCU_2F_056 | B111: FCU | C111: Included | D111: North East Core T1.021 | E111: entity:QNL_T1_021_OPEN_STUDY_TERRACE
A112: FCU_2F_057 | B112: FCU | C112: Included | D112: North East Core T1.021 | E112: entity:QNL_T1_021_OPEN_STUDY_TERRACE
A113: FCU_2F_058 | B113: FCU | C113: Included | D113: North East Core T1.021 | E113: entity:QNL_T1_021_OPEN_STUDY_TERRACE
A114: FCU_2F_059 | B114: FCU | C114: Included | D114: North East Core T1.021 | E114: entity:QNL_T1_021_OPEN_STUDY_TERRACE
A115: FCU_2F_060 | B115: FCU | C115: Included | D115: North West Core T1.020 | E115: entity:QNL_T1_020_OPEN_LOUNGE_TERRACE
A116: FCU_2F_061 | B116: FCU | C116: Included | D116: North West Core T1.020 | E116: entity:QNL_T1_020_OPEN_LOUNGE_TERRACE
A117: FCU_2F_062 | B117: FCU | C117: Included | D117: North West Core T1.020 | E117: entity:QNL_T1_020_OPEN_LOUNGE_TERRACE
A118: FCU_B_001 | B118: FCU | C118: Not Included | D118: IDF ROOM B.155 | E118: entity:QNL_B_155_FACULTY_CARRELS | J118: IDF Rm | K118: QNL/BF-8.jpg
A119: FCU_B_002 | B119: FCU | C119: Included | D119: FUMIGATION B.085 | E119: entity:QNL_B_085_FUMIGATION_ROOM
A120: FCU_B_003 | B120: FCU | C120: Not Included | D120: IDF (Corridor) B.062 | E120: entity:QNL_B_062_IDF_CORRIDOR | J120: IDF | K120: QNL/BF-2.jpg
A121: FCU_B_004 | B121: FCU | C121: Not Included | D121: IDF FM Storage B.215 | E121: entity:QNL_B_215_IDF_FM_STORAGE | J121: FM Storage | K121: QNL/BF-10.jpg
A122: FCU_B_005 | B122: FCU | C122: Not Included | D122: HL Plant Room B.140 | E122: entity:QNL_B_140_HL_PLANT_ROOM
A123: FCU_B_006 | B123: FCU | C123: Not Included | D123: Fire Command ROOM B.071 | E123: entity:QNL_B_071_FIRE_COMMAND_ROOM
A124: FCU_B_007 | B124: FCU | C124: Not Included | D124: Sprinklers Pumps ROOM B.072 | E124: entity:QNL_B_072_SPRIMKLERS_PUMPS_&_ZONES_VALVES
A125: FCU_B_008 | B125: FCU | C125: Not Included | D125: GAS SUPPRESSION ROOM B.087 | E125: entity:QNL_B_087_GAS_SUPPRESSION_ROOM | K125: QNL/BF-3.jpg
A126: FCU_B_009 | B126: FCU | C126: Included | D126: PEOPLE MOVER ROOM B.088 | E126: entity:QNL_B_088_PEOPLE_MOVER_PLANT
A127: FCU_B_010 | B127: FCU | C127: Not Included | D127: Security Contol Room B.105 | E127: entity:QNL_B_105_SECURITY_CONTOL_ROOM
A128: FCU_B_011 | B128: FCU | C128: Not Included | D128: Plant Room 1 B.063 | E128: entity:QNL_B_063_PLANT_ROOM_01 | J128: Plant Rm 1 | K128: QNL/BF-2.jpg
A129: FCU_B_012 | B129: FCU | C129: Not Included | D129: Plant Room 1 B.063 | E129: entity:QNL_B_063_PLANT_ROOM_01 | J129: Plant Rm 1 | K129: QNL/BF-2.jpg
A130: FCU_B_013 | B130: FCU | C130: Not Included | D130: Plant Room 2 B.070 | E130: entity:QNL_B_070_PLANT_ROOM_02 | J130: Plant Rm 2 | K130: QNL/BF-2.jpg
A131: FCU_B_014 | B131: FCU | C131: Not Included | D131: Plant Room 2 B.070 | E131: entity:QNL_B_070_PLANT_ROOM_02 | J131: Plant Rm 2 | K131: QNL/BF-2.jpg
A132: FCU_B_015 | B132: FCU | C132: Not Included | D132: Plant Room 3 B.110 | E132: entity:QNL_B_110_PLANT_ROOM_03 | J132: Plant Rm 3 | K132: QNL/BF-6.jpg
A133: FCU_B_016 | B133: FCU | C133: Not Included | D133: Plant Room 3 B.110 | E133: entity:QNL_B_110_PLANT_ROOM_03 | J133: Plant Rm 3 | K133: QNL/BF-6.jpg
A134: FCU_B_017 | B134: FCU | C134: Not Included | D134: Plant Room 3 B.110 | E134: entity:QNL_B_110_PLANT_ROOM_03 | J134: Plant Rm 3 | K134: QNL/BF-6.jpg
A135: FCU_B_018 | B135: FCU | C135: Not Included | D135: Plant Room 4 B.220 | E135: entity:QNL_B_220_PLANT_ROOM_04 | J135: Plant Rm 4 | K135: QNL/BF-10.jpg
A136: FCU_B_019 | B136: FCU | C136: Not Included | D136: Plant Room 4 B.220 | E136: entity:QNL_B_220_PLANT_ROOM_04 | J136: Plant Rm 4 | K136: QNL/BF-10.jpg
A137: FCU_B_020 | B137: FCU | C137: Not Included | D137: Plant Room 4 B.220 | E137: entity:QNL_B_220_PLANT_ROOM_04 | J137: Plant Rm 4 | K137: QNL/BF-10.jpg
A138: FCU_B_021 | B138: FCU | C138: Not Included | D138: Plant Room 4 B.220 | E138: entity:QNL_B_220_PLANT_ROOM_04 | J138: Plant Rm 4 | K138: QNL/BF-10.jpg
A139: FCU_B_022 | B139: FCU | C139: Included | D139: FM Storage B.210 | E139: entity:QNL_B_210_FM_STORAGE | J139: FM Storage | K139: QNL/BF-10.jpg
... A141: FCU_B_024 | B141: FCU | C141: Not Included | D141: PH Plant ROOM B.211 | E141: entity:QNL_B_211_PH_PLANT_ROOM | J141: PH Plant | K141: QNL/BF-10.jpg
A142: FCU_B_025 | B142: FCU | C142: Not Included | D142: MISTING PUMP ROOM B.212 | E142: entity:QNL_B_212_MISTING_PUMP_ROOM
A143: FCU_B_026 | B143: FCU | C143: Not Included | D143: MISTING PUMP ROOM B.212 | E143: entity:QNL_B_212_MISTING_PUMP_ROOM | J143: Misting System | K143: QNL/BF-10.jpg
A144: FCU_B_027 | B144: FCU | C144: Included | D144: Sorting Shelving Room B.121 | E144: entity:QNL_B_121_SORTING_SHELVING_ROOM
A145: FCU_B_028 | B145: FCU | C145: Included | D145: Sorting Shelving Room B.121 | E145: entity:QNL_B_121_SORTING_SHELVING_ROOM | J145: Sorting Shelving Rm | K145: QNL/BF-2.jpg
A146: FCU_B_029 | B146: FCU | C146: Included | D146: B.145.05 | E146: entity:QNL_B_145_LOBY_&_CSECURITY
A147: FCU_B_030 | B147: FCU | C147: Included | D147: PUMP ROOM B.226 | E147: entity:QNL_B_226_PUMP_ROOM | J147: Pump Rm 4 | K147: QNL/BF-10.jpg
A148: FCU_B_031 | B148: FCU | C148: Not Included | D148: IDF ROOM B.215A | E148: entity:QNL_B_215A_IDF
...

Sheet SSC Room Names with Equip.
A1: Name | B1: Number | C1: entity to use in Ontology | D1: Equipment located in Entity
A2: VENT PLANT | B2: B1.014 | C2: entity:SSC_B1_014_VENT_PLANT | D2: {=TRANSPOSE(_xlfn._xlws.FILTER('Controllable Asset Registry'!#REF!,IFERROR('Controllable Asset Registry'!#REF!=C2,FALSE),"No Equipment in entity"))} -> #REF! | E2: #REF!
A3: CHILLED WATER | B3: B1.013 | C3: entity:SSC_B1_013_CHILLED_WATER | D3: {=TRANSPOSE(_xlfn._xlws.FILTER('Controllable Asset Registry'!#REF!,IFERROR('Controllable Asset Registry'!#REF!=C3,FALSE),"No Equipment in entity"))} -> #REF! | E3: #REF!
A4: GENERATOR | B4: B1.012 | C4: entity:SSC_B1_012_GENERATOR | D4: {=TRANSPOSE(_xlfn._xlws.FILTER('Controllable Asset Registry'!#REF!,IFERROR('Controllable Asset Registry'!#REF!=C4,FALSE),"No Equipment in entity"))} -> #REF!
A5: STAIR-1 | B5: B1.ST-1 | C5: entity:SSC_B1_ST-1_STAIR-1 | D5: {=TRANSPOSE(_xlfn._xlws.FILTER('Controllable Asset Registry'!#REF!,IFERROR('Controllable Asset Registry'!#REF!=C5,FALSE),"No Equipment in entity"))} -> #REF!
A6: ENTRANCE | B6: B1.015 | C6: entity:SSC_B1_015_ENTRANCE | D6: {=TRANSPOSE(_xlfn._xlws.FILTER('Controllable Asset Registry'!#REF!,IFERROR('Controllable Asset Registry'!#REF!=C6,FALSE),"No Equipment in entity"))} -> #REF!
A7: LIFT | B7: B1.P-1 | C7: entity:SSC_B1_P-1_P1 | D7: {=TRANSPOSE(_xlfn._xlws.FILTER('Controllable Asset Registry'!#REF!,IFERROR('Controllable Asset Registry'!#REF!=C7,FALSE),"No Equipment in entity"))} -> #REF!
A8: LIFT | B8: B1.P-2 | C8: entity:SSC_B1_P-2_P2 | D8: {=TRANSPOSE(_xlfn._xlws.FILTER('Controllable Asset Registry'!#REF!,IFERROR('Controllable Asset Registry'!#REF!=C8,FALSE),"No Equipment in entity"))} -> #REF!
A9: SPRINKLER & WATER | B9: B1.016 | C9: entity:SSC_B1_016_SPRINKLER_&_WATER | D9: {=TRANSPOSE(_xlfn._xlws.FILTER('Controllable Asset Registry'!#REF!,IFERROR('Controllable Asset Registry'!#REF!=C9,FALSE),"No Equipment in entity"))} -> #REF!
A10: SER-2 | B10: B1.038 | C10: entity:SSC_B1_038_SER-2 | D10: {=TRANSPOSE(_xlfn._xlws.FILTER('Controllable Asset Registry'!#REF!,IFERROR('Controllable Asset Registry'!#REF!=C10,FALSE),"No Equipment in entity"))} -> #REF!
A11: MDF-2 | B11: B1.017 | C11: entity:SSC_B1_017_MDF-2 | D11: {=TRANSPOSE(_xlfn._xlws.FILTER('Controllable Asset Registry'!#REF!,IFERROR('Controllable Asset Registry'!#REF!=C11,FALSE),"No Equipment in entity"))} -> #REF!
A12: FM STORAGE | B12: B1.019 | C12: entity:SSC_B1_019_FM_STORAGE | D12: {=TRANSPOSE(_xlfn._xlws.FILTER('Controllable Asset Registry'!#REF!,IFERROR('Controllable Asset Registry'!#REF!=C12,FALSE),"No Equipment in entity"))} -> #REF!
A13: CONDENSER ROOM | B13: B1.018 | C13: entity:SSC_B1_018_CONDENSER_ROOM | D13: {=TRANSPOSE(_xlfn._xlws.FILTER('Controllable Asset Registry'!#REF!,IFERROR('Controllable Asset Registry'!#REF!=C13,FALSE),"No Equipment in entity"))} -> #REF!
A14: FILE STORAGE | B14: B1.028 | C14: entity:SSC_B1_028_FILE_STORAGE | D14: {=TRANSPOSE(_xlfn._xlws.FILTER('Controllable Asset Registry'!#REF!,IFERROR('Controllable Asset Registry'!#REF!=C14,FALSE),"No Equipment in entity"))} -> #REF!
A15: CORRIDOR | B15: B1.030 | C15: entity:SSC_B1_030_CORRIDOR | D15: {=TRANSPOSE(_xlfn._xlws.FILTER('Controllable Asset Registry'!#REF!,IFERROR('Controllable Asset Registry'!#REF!=C15,FALSE),"No Equipment in entity"))} -> #REF!
... A43: STAIR-9 | B43: 01.ST-9 | C43: entity:SSC_01_ST-9_STAIR-9 | D43: {=TRANSPOSE(_xlfn._xlws.FILTER('Controllable Asset Registry'!#REF!,IFERROR('Controllable Asset Registry'!#REF!=C43,FALSE),"No Equipment in entity"))} -> #REF!
A44: OUTDOOR AREA | B44: 1.037 | C44: entity:SSC_01_037_OUTDOOR_AREA | D44: {=TRANSPOSE(_xlfn._xlws.FILTER('Controllable Asset Registry'!#REF!,IFERROR('Controllable Asset Registry'!#REF!=C44,FALSE),"No Equipment in entity"))} -> #REF!
A45: SHELL SPACE | B45: 1.014 | C45: entity:SSC_01_014_SHELL_SPACE | D45: {=TRANSPOSE(_xlfn._xlws.FILTER('Controllable Asset Registry'!#REF!,IFERROR('Controllable Asset Registry'!#REF!=C45,FALSE),"No Equipment in entity"))} -> #REF! | E45: #REF! | F45: #REF!
A46: STAIR-3 | B46: 01.ST-3 | C46: entity:SSC_01_ST-3_STAIR-3 | D46: {=TRANSPOSE(_xlfn._xlws.FILTER('Controllable Asset Registry'!#REF!,IFERROR('Controllable Asset Registry'!#REF!=C46,FALSE),"No Equipment in entity"))} -> #REF!
A47: SHELL SPACE | B47: 1.015 | C47: entity:SSC_01_015_SHELL_SPACE | D47: {=TRANSPOSE(_xlfn._xlws.FILTER('Controllable Asset Registry'!#REF!,IFERROR('Controllable Asset Registry'!#REF!=C47,FALSE),"No Equipment in entity"))} -> #REF! | E47: #REF! | F47: #REF!
A48: STAIR-8 | B48: 01.ST-8 | C48: entity:SSC_01_ST-8_STAIR-8 | D48: {=TRANSPOSE(_xlfn._xlws.FILTER('Controllable Asset Registry'!#REF!,IFERROR('Controllable Asset Registry'!#REF!=C48,FALSE),"No Equipment in entity"))} -> #REF!
A49: SHELL SPACE | B49: 1.016 | C49: entity:SSC_01_016_SHELL_SPACE | D49: {=TRANSPOSE(_xlfn._xlws.FILTER('Controllable Asset Registry'!#REF!,IFERROR('Controllable Asset Registry'!#REF!=C49,FALSE),"No Equipment in entity"))} -> #REF!
A50: STORAGE | B50: 1.041 | C50: entity:SSC_01_041_STORAGE_ROOM | D50: {=TRANSPOSE(_xlfn._xlws.FILTER('Controllable Asset Registry'!#REF!,IFERROR('Controllable Asset Registry'!#REF!=C50,FALSE),"No Equipment in entity"))} -> #REF!
A51: FEMALE TOILET | B51: 1.017 | C51: entity:SSC_01_017_FEMALE_TOILET | D51: {=TRANSPOSE(_xlfn._xlws.FILTER('Controllable Asset Registry'!#REF!,IFERROR('Controllable Asset Registry'!#REF!=C51,FALSE),"No Equipment in entity"))} -> #REF!
A52: CORRIDOR | B52: 1.018 | C52: entity:SSC_01_018_CORRIDOR | D52: {=TRANSPOSE(_xlfn._xlws.FILTER('Controllable Asset Registry'!#REF!,IFERROR('Controllable Asset Registry'!#REF!=C52,FALSE),"No Equipment in entity"))} -> #REF!
A53: SHELL SPACE | B53: 1.002 | C53: entity:SSC_01_002_SHELL_SPACE | D53: {=TRANSPOSE(_xlfn._xlws.FILTER('Controllable Asset Registry'!#REF!,IFERROR('Controllable Asset Registry'!#REF!=C53,FALSE),"No Equipment in entity"))} -> #REF! | E53: #REF! | F53: #REF! | G53: #REF!
A54: ABLUTION ROOM | B54: 1.022 | C54: entity:SSC_01_022_ABLUTION_ROOM | D54: {=TRANSPOSE(_xlfn._xlws.FILTER('Controllable Asset Registry'!#REF!,IFERROR('Controllable Asset Registry'!#REF!=C54,FALSE),"No Equipment in entity"))} -> #REF!
A55: ABLUTION ROOM | B55: 1.021 | C55: entity:SSC_01_021_ABLUTION_ROOM | D55: {=TRANSPOSE(_xlfn._xlws.FILTER('Controllable Asset Registry'!#REF!,IFERROR('Controllable Asset Registry'!#REF!=C55,FALSE),"No Equipment in entity"))} -> #REF!
A56: CORRIDOR | B56: 1.023 | C56: entity:SSC_01_023_CORRIDOR | D56: {=TRANSPOSE(_xlfn._xlws.FILTER('Controllable Asset Registry'!#REF!,IFERROR('Controllable Asset Registry'!#REF!=C56,FALSE),"No Equipment in entity"))} -> #REF!
A57: CORRIDOR | B57: 1.02 | C57: entity:SSC_01_020_CORRIDOR | D57: {=TRANSPOSE(_xlfn._xlws.FILTER('Controllable Asset Registry'!#REF!,IFERROR('Controllable Asset Registry'!#REF!=C57,FALSE),"No Equipment in entity"))} -> #REF!
A58: CORRIDOR | B58: 1.024 | C58: entity:SSC_01_024_CORRIDOR | D58: {=TRANSPOSE(_xlfn._xlws.FILTER('Controllable Asset Registry'!#REF!,IFERROR('Controllable Asset Registry'!#REF!=C58,FALSE),"No Equipment in entity"))} -> #REF!
A59: IDF - 2 | B59: 1.039 | C59: entity:SSC_01_039_IDF_2 | D59: {=TRANSPOSE(_xlfn._xlws.FILTER('Controllable Asset Registry'!#REF!,IFERROR('Controllable Asset Registry'!#REF!=C59,FALSE),"No Equipment in entity"))} -> #REF! | E59: #REF!
A60: IDF - 1 | B60: 1.027 | C60: entity:SSC_01_027_IDF_1 | D60: {=TRANSPOSE(_xlfn._xlws.FILTER('Controllable Asset Registry'!#REF!,IFERROR('Controllable Asset Registry'!#REF!=C60,FALSE),"No Equipment in entity"))} -> #REF! | E60: #REF!
A61: FURNITURE STORAGE | B61: 1.026 | C61: entity:SSC_01_026_STORAGE_ROOM | D61: {=TRANSPOSE(_xlfn._xlws.FILTER('Controllable Asset Registry'!#REF!,IFERROR('Controllable Asset Registry'!#REF!=C61,FALSE),"No Equipment in entity"))} -> #REF!
A62: MALE TOILET | B62: 1.025 | C62: entity:SSC_01_025_MALE_TOILET | D62: {=TRANSPOSE(_xlfn._xlws.FILTER('Controllable Asset Registry'!#REF!,IFERROR('Controllable Asset Registry'!#REF!=C62,FALSE),"No Equipment in entity"))} -> #REF!
A63: PRAYER ROOM | B63: 1.019 | C63: entity:SSC_01_019_PRAYER_ROOM | D63: {=TRANSPOSE(_xlfn._xlws.FILTER('Controllable Asset Registry'!#REF!,IFERROR('Controllable Asset Registry'!#REF!=C63,FALSE),"No Equipment in entity"))} -> #REF! | E63: #REF! | F63: #REF! | G63: #REF! | H63: #REF! | I63: #REF!
A64: CORRIDOR | B64: 1.001 | C64: entity:SSC_01_001_CORRIDOR | D64: {=TRANSPOSE(_xlfn._xlws.FILTER('Controllable Asset Registry'!#REF!,IFERROR('Controllable Asset Registry'!#REF!=C64,FALSE),"No Equipment in entity"))} -> #REF! | E64: #REF! | F64: #REF!
A65: OPEN SPACE | B65: 1.003 | C65: entity:SSC_01_003_OPEN_SPACE | D65: {=TRANSPOSE(_xlfn._xlws.FILTER('Controllable Asset Registry'!#REF!,IFERROR('Controllable Asset Registry'!#REF!=C65,FALSE),"No Equipment in entity"))} -> #REF! | E65: #REF! | F65: #REF! | G65: #REF!
A66: SHELL SPACE | B66: 1.029 | C66: entity:SSC_01_029_ROOM_NO_42 | D66: {=TRANSPOSE(_xlfn._xlws.FILTER('Controllable Asset Registry'!#REF!,IFERROR('Controllable Asset Registry'!#REF!=C66,FALSE),"No Equipment in entity"))} -> #REF! | E66: #REF! | F66: #REF!
A67: STORAGE | B67: 1.012 | C67: entity:SSC_01_012_STORAGE | D67: {=TRANSPOSE(_xlfn._xlws.FILTER('Controllable Asset Registry'!#REF!,IFERROR('Controllable Asset Registry'!#REF!=C67,FALSE),"No Equipment in entity"))} -> #REF!
A68: LIFT | B68: 01.P-2 | C68: entity:SSC_01_P-2_P-2 | D68: {=TRANSPOSE(_xlfn._xlws.FILTER('Controllable Asset Registry'!#REF!,IFERROR('Controllable Asset Registry'!#REF!=C68,FALSE),"No Equipment in entity"))} -> #REF!
A69: LIFT | B69: 01.P-1 | C69: entity:SSC_01_P-1_P-1 | D69: {=TRANSPOSE(_xlfn._xlws.FILTER('Controllable Asset Registry'!#REF!,IFERROR('Controllable Asset Registry'!#REF!=C69,FALSE),"No Equipment in entity"))} -> #REF!
A70: CORRIDOR | B70: 1.013 | C70: entity:SSC_01_013_CORRIDOR | D70: {=TRANSPOSE(_xlfn._xlws.FILTER('Controllable Asset Registry'!#REF!,IFERROR('Controllable Asset Registry'!#REF!=C70,FALSE),"No Equipment in entity"))} -> #REF!
A71: STAIR-1 | B71: 01.ST-1 | C71: entity:SSC_01_ST-1_STAIR-1 | D71: {=TRANSPOSE(_xlfn._xlws.FILTER('Controllable Asset Registry'!#REF!,IFERROR('Controllable Asset Registry'!#REF!=C71,FALSE),"No Equipment in entity"))} -> #REF!
A72: AUDITORIUM MEETING ROOM | B72: 1.009 | C72: entity:SSC_01_009_AUDITORIUM | D72: {=TRANSPOSE(_xlfn._xlws.FILTER('Controllable Asset Registry'!#REF!,IFERROR('Controllable Asset Registry'!#REF!=C72,FALSE),"No Equipment in entity"))} -> #REF!
A73: STORAGE AREA | B73: 1.038 | C73: entity:SSC_01_038_STORAGE_AREA | D73: {=TRANSPOSE(_xlfn._xlws.FILTER('Controllable Asset Registry'!#REF!,IFERROR('Controllable Asset Registry'!#REF!=C73,FALSE),"No Equipment in entity"))} -> #REF!
A74: A / V ROOM | B74: 1.008 | C74: entity:SSC_01_008_AV_ROOM | D74: {=TRANSPOSE(_xlfn._xlws.FILTER('Controllable Asset Registry'!#REF!,IFERROR('Controllable Asset Registry'!#REF!=C74,FALSE),"No Equipment in entity"))} -> #REF! | E74: #REF!
A75: FEMALE TOILET | B75: 1.007 | C75: entity:SSC_01_007_FEMALE_TOILET | D75: {=TRANSPOSE(_xlfn._xlws.FILTER('Controllable Asset Registry'!#REF!,IFERROR('Controllable Asset Registry'!#REF!=C75,FALSE),"No Equipment in entity"))} -> #REF!
A76: MALE TOILET | B76: 1.006 | C76: entity:SSC_01_006_MALE_TOILET | D76: {=TRANSPOSE(_xlfn._xlws.FILTER('Controllable Asset Registry'!#REF!,IFERROR('Controllable Asset Registry'!#REF!=C76,FALSE),"No Equipment in entity"))} -> #REF!
A77: KITCHEN | B77: 1.005 | C77: entity:SSC_01_005_KITCHEN | D77: {=TRANSPOSE(_xlfn._xlws.FILTER('Controllable Asset Registry'!#REF!,IFERROR('Controllable Asset Registry'!#REF!=C77,FALSE),"No Equipment in entity"))} -> #REF!
A78: CORRIDOR | B78: 1.004 | C78: entity:SSC_01_004_CORRIDOR | D78: {=TRANSPOSE(_xlfn._xlws.FILTER('Controllable Asset Registry'!#REF!,IFERROR('Controllable Asset Registry'!#REF!=C78,FALSE),"No Equipment in entity"))} -> #REF!
A79: STAIR-4 | B79: 01.ST-4 | C79: entity:SSC_01_ST-4_STAIR_4 | D79: {=TRANSPOSE(_xlfn._xlws.FILTER('Controllable Asset Registry'!#REF!,IFERROR('Controllable Asset Registry'!#REF!=C79,FALSE),"No Equipment in entity"))} -> #REF!
A80: AIR LOCK | B80: 1.011 | C80: entity:SSC_01_011_AIR_LOCK | D80: {=TRANSPOSE(_xlfn._xlws.FILTER('Controllable Asset Registry'!#REF!,IFERROR('Controllable Asset Registry'!#REF!=C80,FALSE),"No Equipment in entity"))} -> #REF!
A81: CORRIDOR | B81: 1.01 | C81: entity:SSC_01_010_CORRIDOR | D81: {=TRANSPOSE(_xlfn._xlws.FILTER('Controllable Asset Registry'!#REF!,IFERROR('Controllable Asset Registry'!#REF!=C81,FALSE),"No Equipment in entity"))} -> #REF! | E81: #REF!
A82: STAIR-5 | B82: 01.ST-5 | C82: entity:SSC_01_ST-5_STAIR-5 | D82: {=TRANSPOSE(_xlfn._xlws.FILTER('Controllable Asset Registry'!#REF!,IFERROR('Controllable Asset Registry'!#REF!=C82,FALSE),"No Equipment in entity"))} -> #REF!
A83: STORAGE | B83: 1.03 | C83: entity:SSC_01_030_STORAGE | D83: {=TRANSPOSE(_xlfn._xlws.FILTER('Controllable Asset Registry'!#REF!,IFERROR('Controllable Asset Registry'!#REF!=C83,FALSE),"No Equipment in entity"))} -> #REF!
A84: TOILET | B84: 1.031 | C84: entity:SSC_01_031_TOILET | D84: {=TRANSPOSE(_xlfn._xlws.FILTER('Controllable Asset Registry'!#REF!,IFERROR('Controllable Asset Registry'!#REF!=C84,FALSE),"No Equipment in entity"))} -> #REF!
A85: VESTIBULE | B85: 1.032 | C85: entity:SSC_01_032_VESTIBULE | D85: {=TRANSPOSE(_xlfn._xlws.FILTER('Controllable Asset Registry'!#REF!,IFERROR('Controllable Asset Registry'!#REF!=C85,FALSE),"No Equipment in entity"))} -> #REF!
A86: JANITORS CLOSET | B86: 1.033 | C86: entity:SSC_01_033_JANITORS_CLOSET | D86: {=TRANSPOSE(_xlfn._xlws.FILTER('Controllable Asset Registry'!#REF!,IFERROR('Controllable Asset Registry'!#REF!=C86,FALSE),"No Equipment in entity"))} -> #REF!
A87: CORRIDOR | B87: 1.035 | C87: entity:SSC_01_035_CORRIDOR | D87: {=TRANSPOSE(_xlfn._xlws.FILTER('Controllable Asset Registry'!#REF!,IFERROR('Controllable Asset Registry'!#REF!=C87,FALSE),"No Equipment in entity"))} -> #REF!
A88: AIR LOCK | B88: 1.034 | C88: entity:SSC_01_034_AIR_LOCK | D88: {=TRANSPOSE(_xlfn._xlws.FILTER('Controllable Asset Registry'!#REF!,IFERROR('Controllable Asset Registry'!#REF!=C88,FALSE),"No Equipment in entity"))} -> #REF!
A89: STAIR-10 | B89: ST-10 | C89: entity:SSC_ST-10_STAIR-10 | D89: {=TRANSPOSE(_xlfn._xlws.FILTER('Controllable Asset Registry'!#REF!,IFERROR('Controllable Asset Registry'!#REF!=C89,FALSE),"No Equipment in entity"))} -> #REF!
A90: OUTDOOR AREA | B90: 1.036 | C90: entity:SSC_01_036_OUTDOOR_AREA | D90: {=TRANSPOSE(_xlfn._xlws.FILTER('Controllable Asset Registry'!#REF!,IFERROR('Controllable Asset Registry'!#REF!=C90,FALSE),"No Equipment in entity"))} -> #REF!
A91: STAIR-2 | B91: 01.ST-2 | C91: entity:SSC_01_ST-2_STAIR-2 | D91: {=TRANSPOSE(_xlfn._xlws.FILTER('Controllable Asset Registry'!#REF!,IFERROR('Controllable Asset Registry'!#REF!=C91,FALSE),"No Equipment in entity"))} -> #REF!
A92: CORRIDOR | B92: 1.028 | C92: entity:SSC_01_028_CORRIDOR | D92: {=TRANSPOSE(_xlfn._xlws.FILTER('Controllable Asset Registry'!#REF!,IFERROR('Controllable Asset Registry'!#REF!=C92,FALSE),"No Equipment in entity"))} -> #REF! | E92: #REF!
A93: RESEARCHER'S OFFICE | B93: 3.015 | C93: entity:SSC_03_015_RESEARCHERS_OFFICE | D93: {=TRANSPOSE(_xlfn._xlws.FILTER('Controllable Asset Registry'!#REF!,IFERROR('Controllable Asset Registry'!#REF!=C93,FALSE),"No Equipment in entity"))} -> #REF!
A94: VISITOR'S CUBICLE | B94: 3.014 | C94: entity:SSC_03_014_VISITORS_CUBICLE | D94: {=TRANSPOSE(_xlfn._xlws.FILTER('Controllable Asset Registry'!#REF!,IFERROR('Controllable Asset Registry'!#REF!=C94,FALSE),"No Equipment in entity"))} -> #REF!
A95: RESEARCHER'S OFFICE | B95: 3.013 | C95: entity:SSC_03_013_RESEARCHERS_OFFICE | D95: {=TRANSPOSE(_xlfn._xlws.FILTER('Controllable Asset Registry'!#REF!,IFERROR('Controllable Asset Registry'!#REF!=C95,FALSE),"No Equipment in entity"))} -> #REF!
A96: RESEARCHER'S OFFICE | B96: 3.012 | C96: entity:SSC_03_012_RESEARCHERS_OFFICE | D96: {=TRANSPOSE(_xlfn._xlws.FILTER('Controllable Asset Registry'!#REF!,IFERROR('Controllable Asset Registry'!#REF!=C96,FALSE),"No Equipment in entity"))} -> #REF!
A97: VISITOR'S CUBICLE | B97: 3.011 | C97: entity:SSC_03_011_VISITORS_CUBICLE | D97: {=TRANSPOSE(_xlfn._xlws.FILTER('Controllable Asset Registry'!#REF!,IFERROR('Controllable Asset Registry'!#REF!=C97,FALSE),"No Equipment in entity"))} -> #REF!
A98: RESEARCHER'S OFFICE | B98: 3.01 | C98: entity:SSC_03_010_RESEARCHERS_OFFICE | D98: {=TRANSPOSE(_xlfn._xlws.FILTER('Controllable Asset Registry'!#REF!,IFERROR('Controllable Asset Registry'!#REF!=C98,FALSE),"No Equipment in entity"))} -> #REF!
A99: RESEARCHER'S OFFICE | B99: 3.009 | C99: entity:SSC_03_009_RESEARCHERS_OFFICE | D99: {=TRANSPOSE(_xlfn._xlws.FILTER('Controllable Asset Registry'!#REF!,IFERROR('Controllable Asset Registry'!#REF!=C99,FALSE),"No Equipment in entity"))} -> #REF!
A100: VISITOR'S CUBICLE | B100: 3.008 | C100: entity:SSC_03_008_VISITORS_CUBICLE | D100: {=TRANSPOSE(_xlfn._xlws.FILTER('Controllable Asset Registry'!#REF!,IFERROR('Controllable Asset Registry'!#REF!=C100,FALSE),"No Equipment in entity"))} -> #REF!
A101: OPERATIONS MANAGER | B101: 3.007 | C101: entity:SSC_03_007_OPERATIONS_MANAGER | D101: {=TRANSPOSE(_xlfn._xlws.FILTER('Controllable Asset Registry'!#REF!,IFERROR('Controllable Asset Registry'!#REF!=C101,FALSE),"No Equipment in entity"))} -> #REF!
A102: MEETING ROOM | B102: 3.006 | C102: entity:SSC_03_006_MEETING_ROOM | D102: {=TRANSPOSE(_xlfn._xlws.FILTER('Controllable Asset Registry'!#REF!,IFERROR('Controllable Asset Registry'!#REF!=C102,FALSE),"No Equipment in entity"))} -> #REF! | E102: #REF!
A103: RESEARCHER'S OFFICE | B103: 3.005 | C103: entity:SSC_03_005_RESEARCHERS_OFFICE | D103: {=TRANSPOSE(_xlfn._xlws.FILTER('Controllable Asset Registry'!#REF!,IFERROR('Controllable Asset Registry'!#REF!=C103,FALSE),"No Equipment in entity"))} -> #REF!
A104: VISITOR'S CUBICLE | B104: 3.004 | C104: entity:SSC_03_004_VISITORS_CUBICLE | D104: {=TRANSPOSE(_xlfn._xlws.FILTER('Controllable Asset Registry'!#REF!,IFERROR('Controllable Asset Registry'!#REF!=C104,FALSE),"No Equipment in entity"))} -> #REF!
A105: RESEARCHER'S OFFICE | B105: 3.003 | C105: entity:SSC_03_003_RESEARCHERS_OFFICE | D105: {=TRANSPOSE(_xlfn._xlws.FILTER('Controllable Asset Registry'!#REF!,IFERROR('Controllable Asset Registry'!#REF!=C105,FALSE),"No Equipment in entity"))} -> #REF!
A106: DIRECTOR'S MEETING ROOM | B106: 3.002 | C106: entity:SSC_03_002_DIRECTORS_MEETING_ROOM | D106: {=TRANSPOSE(_xlfn._xlws.FILTER('Controllable Asset Registry'!#REF!,IFERROR('Controllable Asset Registry'!#REF!=C106,FALSE),"No Equipment in entity"))} -> #REF! | E106: #REF! | F106: #REF! | G106: #REF! | H106: #REF! | I106: #REF! | J106: #REF! | K106: #REF! | L106: #REF! | M106: #REF! | N106: #REF!
A107: DIRECTOR'S OFFICE | B107: 3.001 | C107: entity:SSC_03_001_DIRECTORS_OFFICE | D107: {=TRANSPOSE(_xlfn._xlws.FILTER('Controllable Asset Registry'!#REF!,IFERROR('Controllable Asset Registry'!#REF!=C107,FALSE),"No Equipment in entity"))} -> #REF!
A108: RESEARCHER'S OFFICE | B108: 3.017 | C108: entity:SSC_03_017_RESEARCHERS_OFFICE | D108: {=TRANSPOSE(_xlfn._xlws.FILTER('Controllable Asset Registry'!#REF!,IFERROR('Controllable Asset Registry'!#REF!=C108,FALSE),"No Equipment in entity"))} -> #REF!
A109: VISITOR'S CUBICLE | B109: 3.018 | C109: entity:SSC_03_018_VISITORS_CUBICLE | D109: {=TRANSPOSE(_xlfn._xlws.FILTER('Controllable Asset Registry'!#REF!,IFERROR('Controllable Asset Registry'!#REF!=C109,FALSE),"No Equipment in entity"))} -> #REF!
A110: IT MANAGER'S OFFICE | B110: 3.019 | C110: entity:SSC_03_019_IT_MANAGERS_OFFICE | D110: {=TRANSPOSE(_xlfn._xlws.FILTER('Controllable Asset Registry'!#REF!,IFERROR('Controllable Asset Registry'!#REF!=C110,FALSE),"No Equipment in entity"))} -> #REF!
A111: RESEARCHER'S OFFICE | B111: 3.02 | C111: entity:SSC_03_020_RESEARCHERS_OFFICE | D111: {=TRANSPOSE(_xlfn._xlws.FILTER('Controllable Asset Registry'!#REF!,IFERROR('Controllable Asset Registry'!#REF!=C111,FALSE),"No Equipment in entity"))} -> #REF!
A112: VISITOR'S CUBICLE | B112: 3.021 | C112: entity:SSC_03_021_VISITORS_CUBICLE | D112: {=TRANSPOSE(_xlfn._xlws.FILTER('Controllable Asset Registry'!#REF!,IFERROR('Controllable Asset Registry'!#REF!=C112,FALSE),"No Equipment in entity"))} -> #REF!
A113: RESEARCHER'S OFFICE | B113: 3.022 | C113: entity:SSC_03_022_RESEARCHERS_OFFICE | D113: {=TRANSPOSE(_xlfn._xlws.FILTER('Controllable Asset Registry'!#REF!,IFERROR('Controllable Asset Registry'!#REF!=C113,FALSE),"No Equipment in entity"))} -> #REF!
A114: RESEARCHER'S OFFICE | B114: 3.023 | C114: entity:SSC_03_023_RESEARCHERS_OFFICE | D114: {=TRANSPOSE(_xlfn._xlws.FILTER('Controllable Asset Registry'!#REF!,IFERROR('Controllable Asset Registry'!#REF!=C114,FALSE),"No Equipment in entity"))} -> #REF!
A115: VISITOR'S CUBICLE | B115: 3.024 | C115: entity:SSC_03_024_VISITORS_CUBICLE | D115: {=TRANSPOSE(_xlfn._xlws.FILTER('Controllable Asset Registry'!#REF!,IFERROR('Controllable Asset Registry'!#REF!=C115,FALSE),"No Equipment in entity"))} -> #REF!
A116: SECRETARIAL AREA | B116: 3.025 | C116: entity:SSC_03_025_SECRETARIAL_AREA | D116: {=TRANSPOSE(_xlfn._xlws.FILTER('Controllable Asset Registry'!#REF!,IFERROR('Controllable Asset Registry'!#REF!=C116,FALSE),"No Equipment in entity"))} -> #REF!
A117: MEETING ROOM | B117: 3.026 | C117: entity:SSC_03_026_MEETING_ROOM | D117: {=TRANSPOSE(_xlfn._xlws.FILTER('Controllable Asset Registry'!#REF!,IFERROR('Controllable Asset Registry'!#REF!=C117,FALSE),"No Equipment in entity"))} -> #REF! | E117: #REF! | F117: #REF!
A118: RESEARCHER'S OFFICE | B118: 3.027 | C118: entity:SSC_03_027_RESEARCHERS_OFFICE | D118: {=TRANSPOSE(_xlfn._xlws.FILTER('Controllable Asset Registry'!#REF!,IFERROR('Controllable Asset Registry'!#REF!=C118,FALSE),"No Equipment in entity"))} -> #REF!
A119: VISITOR'S CUBICLE | B119: 3.028 | C119: entity:SSC_03_028_VISITORS_CUBICLE | D119: {=TRANSPOSE(_xlfn._xlws.FILTER('Controllable Asset Registry'!#REF!,IFERROR('Controllable Asset Registry'!#REF!=C119,FALSE),"No Equipment in entity"))} -> #REF!
A120: RESEARCHER'S OFFICE | B120: 3.029 | C120: entity:SSC_03_029_RESEARCHERS_OFFICE | D120: {=TRANSPOSE(_xlfn._xlws.FILTER('Controllable Asset Registry'!#REF!,IFERROR('Controllable Asset Registry'!#REF!=C120,FALSE),"No Equipment in entity"))} -> #REF!
A121: ASSOC. DIRECTOR'S MEETING ROOM | B121: 3.03 | C121: entity:SSC_03_030_ASSOC_DIRECTORS_MEETING_ROOM | D121: {=TRANSPOSE(_xlfn._xlws.FILTER('Controllable Asset Registry'!#REF!,IFERROR('Controllable Asset Registry'!#REF!=C121,FALSE),"No Equipment in entity"))} -> #REF!
A122: ASSOC. DIRECTOR'S OFFICE | B122: 3.031 | C122: entity:SSC_03_031_ASSOC_DIRECTORS_OFFICE | D122: {=TRANSPOSE(_xlfn._xlws.FILTER('Controllable Asset Registry'!#REF!,IFERROR('Controllable Asset Registry'!#REF!=C122,FALSE),"No Equipment in entity"))} -> #REF!
A123: GENERAL OFFICE AREA | B123: 3.032 | C123: entity:SSC_03_032_GENERAL_OFFICE_AREA | D123: {=TRANSPOSE(_xlfn._xlws.FILTER('Controllable Asset Registry'!#REF!,IFERROR('Controllable Asset Registry'!#REF!=C123,FALSE),"No Equipment in entity"))} -> #REF!
A124: PRINTING | B124: 3.033 | C124: entity:SSC_03_033_PRINTING | D124: {=TRANSPOSE(_xlfn._xlws.FILTER('Controllable Asset Registry'!#REF!,IFERROR('Controllable Asset Registry'!#REF!=C124,FALSE),"No Equipment in entity"))} -> #REF!
A125: STAIR-2 | B125: 03.ST-2 | C125: entity:SSC_03_ST-2_STAIR-2 | D125: {=TRANSPOSE(_xlfn._xlws.FILTER('Controllable Asset Registry'!#REF!,IFERROR('Controllable Asset Registry'!#REF!=C125,FALSE),"No Equipment in entity"))} -> #REF!
A126: STORAGE | B126: 3.046 | C126: entity:SSC_03_046_STORAGE | D126: {=TRANSPOSE(_xlfn._xlws.FILTER('Controllable Asset Registry'!#REF!,IFERROR('Controllable Asset Registry'!#REF!=C126,FALSE),"No Equipment in entity"))} -> #REF!
A127: JANITOR'S CLOSET | B127: 3.045 | C127: entity:SSC_03_045_JANITORS_CLOSET | D127: {=TRANSPOSE(_xlfn._xlws.FILTER('Controllable Asset Registry'!#REF!,IFERROR('Controllable Asset Registry'!#REF!=C127,FALSE),"No Equipment in entity"))} -> #REF!
...

Sheet HQ Room Names with Equip.
A1: Room Entity Name | B1: Room Number Used | C1: Room Space (cleaned) | N1: Equipment Match Audit
A2: entity:HQ_B1.606_SECURE_STORAGE | B2: B1.606 | C2: SECURE_STORAGE | D2: {=TRANSPOSE(_xlfn._xlws.FILTER('Controllable Asset Registry'!#REF!,IFERROR('Controllable Asset Registry'!#REF!=A2,FALSE),"No Equipment in entity"))} -> #REF! | N2: Rooms listed (col A) | O2: =COUNTA(A2:A1042) -> 1040
A3: entity:HQ_B1.001_AHU_4 | B3: B1.001 | C3: AHU_4 | D3: {=TRANSPOSE(_xlfn._xlws.FILTER('Controllable Asset Registry'!#REF!,IFERROR('Controllable Asset Registry'!#REF!=A3,FALSE),"No Equipment in entity"))} -> #REF! | N3: Equipment names returned | O3: =COUNTA(D2:L1042)-COUNTIF(D2:L1042,"No Equipment in entity") -> 1040
A4: entity:HQ_B1.002_SECURITY_UPS_ROOM | B4: B1.002 | C4: SECURITY_UPS_ROOM | D4: {=TRANSPOSE(_xlfn._xlws.FILTER('Controllable Asset Registry'!#REF!,IFERROR('Controllable Asset Registry'!#REF!=A4,FALSE),"No Equipment in entity"))} -> #REF! | N4: Rooms with no equipment | O4: =COUNTIF(D2:L1042,"No Equipment in entity") -> 0
A5: entity:HQ_B1.003_CONTROL_ROOM | B5: B1.003 | C5: CONTROL_ROOM | D5: {=TRANSPOSE(_xlfn._xlws.FILTER('Controllable Asset Registry'!#REF!,IFERROR('Controllable Asset Registry'!#REF!=A5,FALSE),"No Equipment in entity"))} -> #REF! | N5: Equipment in source register | O5: =COUNTA('Controllable Asset Registry'!#REF!) -> 1
A6: entity:HQ_B1.005_MDF_1_ROOM | B6: B1.005 | C6: MDF_1_ROOM | D6: {=TRANSPOSE(_xlfn._xlws.FILTER('Controllable Asset Registry'!#REF!,IFERROR('Controllable Asset Registry'!#REF!=A6,FALSE),"No Equipment in entity"))} -> #REF! | N6: Distinct equipment returned | O6: {=SUM(--(_xlfn.UNIQUE(_xlfn.TOCOL(D2:L1042,3))<>"No Equipment in entity"))} -> #VALUE!
A7: entity:HQ_B1.006_AHU_1 | B7: B1.006 | C7: AHU_1 | D7: {=TRANSPOSE(_xlfn._xlws.FILTER('Controllable Asset Registry'!#REF!,IFERROR('Controllable Asset Registry'!#REF!=A7,FALSE),"No Equipment in entity"))} -> #REF! | N7: Duplicate room entries (col A) | O7: {=SUMPRODUCT((A2:A1042<>"")*(COUNTIF(A2:A1042,A2:A1042)>1))} -> 0
A8: entity:HQ_B1.007_COOLING_EQUIPMENT | B8: B1.007 | C8: COOLING_EQUIPMENT | D8: {=TRANSPOSE(_xlfn._xlws.FILTER('Controllable Asset Registry'!#REF!,IFERROR('Controllable Asset Registry'!#REF!=A8,FALSE),"No Equipment in entity"))} -> #REF! | N8: Duplicated equipment returns (D:L) | O8: {=SUMPRODUCT((D2:L1042<>"")*(D2:L1042<>"No Equipment in entity")*(COUNTIF(D2:L1042,D2:L1042)>1))} -> #REF!
A9: entity:HQ_B1.008_FM_STORAGE | B9: B1.008 | C9: FM_STORAGE | D9: {=TRANSPOSE(_xlfn._xlws.FILTER('Controllable Asset Registry'!#REF!,IFERROR('Controllable Asset Registry'!#REF!=A9,FALSE),"No Equipment in entity"))} -> #REF! | N9: Unplaced (in register, not on a room) | O9: =O5-O6 -> #VALUE!
A10: entity:HQ_B1.009_MV_SWITCH_ROOM | B10: B1.009 | C10: MV_SWITCH_ROOM | D10: {=TRANSPOSE(_xlfn._xlws.FILTER('Controllable Asset Registry'!#REF!,IFERROR('Controllable Asset Registry'!#REF!=A10,FALSE),"No Equipment in entity"))} -> #REF!
A11: entity:HQ_B1.010_TRANSFORMER_SUBSTATION | B11: B1.010 | C11: TRANSFORMER_SUBSTATION | D11: {=TRANSPOSE(_xlfn._xlws.FILTER('Controllable Asset Registry'!#REF!,IFERROR('Controllable Asset Registry'!#REF!=A11,FALSE),"No Equipment in entity"))} -> #REF!
A12: entity:HQ_B1.011_HV_INTAKE | B12: B1.011 | C12: HV_INTAKE | D12: {=TRANSPOSE(_xlfn._xlws.FILTER('Controllable Asset Registry'!#REF!,IFERROR('Controllable Asset Registry'!#REF!=A12,FALSE),"No Equipment in entity"))} -> #REF!
A13: entity:HQ_B1.012_GENERATOR | B13: B1.012 | C13: GENERATOR | D13: {=TRANSPOSE(_xlfn._xlws.FILTER('Controllable Asset Registry'!#REF!,IFERROR('Controllable Asset Registry'!#REF!=A13,FALSE),"No Equipment in entity"))} -> #REF!
A14: entity:HQ_B1.013_Q-TEL_INCOMING | B14: B1.013 | C14: Q-TEL_INCOMING | D14: {=TRANSPOSE(_xlfn._xlws.FILTER('Controllable Asset Registry'!#REF!,IFERROR('Controllable Asset Registry'!#REF!=A14,FALSE),"No Equipment in entity"))} -> #REF!
A15: entity:HQ_B1.014_SUPPORT_SPACE_DRY_WASTE_STORAGE | B15: B1.014 | C15: SUPPORT_SPACE_DRY_WASTE_STORAGE | D15: {=TRANSPOSE(_xlfn._xlws.FILTER('Controllable Asset Registry'!#REF!,IFERROR('Controllable Asset Registry'!#REF!=A15,FALSE),"No Equipment in entity"))} -> #REF!
A16: entity:HQ_B1.015_SUPPORT_SPACE_LOADING | B16: B1.015 | C16: SUPPORT_SPACE_LOADING | D16: {=TRANSPOSE(_xlfn._xlws.FILTER('Controllable Asset Registry'!#REF!,IFERROR('Controllable Asset Registry'!#REF!=A16,FALSE),"No Equipment in entity"))} -> #REF!
A17: entity:HQ_B1.016_AHU_2 | B17: B1.016 | C17: AHU_2 | D17: {=TRANSPOSE(_xlfn._xlws.FILTER('Controllable Asset Registry'!#REF!,IFERROR('Controllable Asset Registry'!#REF!=A17,FALSE),"No Equipment in entity"))} -> #REF!
A18: entity:HQ_B1.017_WATER_SERVICES | B18: B1.017 | C18: WATER_SERVICES | D18: {=TRANSPOSE(_xlfn._xlws.FILTER('Controllable Asset Registry'!#REF!,IFERROR('Controllable Asset Registry'!#REF!=A18,FALSE),"No Equipment in entity"))} -> #REF!
A19: entity:HQ_B1.018_PA_ROOM | B19: B1.018 | C19: PA_ROOM | D19: {=TRANSPOSE(_xlfn._xlws.FILTER('Controllable Asset Registry'!#REF!,IFERROR('Controllable Asset Registry'!#REF!=A19,FALSE),"No Equipment in entity"))} -> #REF!
A20: entity:HQ_B1.019_AHU | B20: B1.019 | C20: AHU | D20: {=TRANSPOSE(_xlfn._xlws.FILTER('Controllable Asset Registry'!#REF!,IFERROR('Controllable Asset Registry'!#REF!=A20,FALSE),"No Equipment in entity"))} -> #REF!
A21: entity:HQ_B1.020_CHILLED_WATER | B21: B1.020 | C21: CHILLED_WATER | D21: {=TRANSPOSE(_xlfn._xlws.FILTER('Controllable Asset Registry'!#REF!,IFERROR('Controllable Asset Registry'!#REF!=A21,FALSE),"No Equipment in entity"))} -> #REF!
... A986: entity:HQ_2.701_TERRACE | B986: 2.701 | C986: TERRACE | D986: {=TRANSPOSE(_xlfn._xlws.FILTER('Controllable Asset Registry'!#REF!,IFERROR('Controllable Asset Registry'!#REF!=A986,FALSE),"No Equipment in entity"))} -> #REF!
A987: entity:HQ_5.214_GSM_ROOM | B987: 5.214 | C987: GSM_ROOM | D987: {=TRANSPOSE(_xlfn._xlws.FILTER('Controllable Asset Registry'!#REF!,IFERROR('Controllable Asset Registry'!#REF!=A987,FALSE),"No Equipment in entity"))} -> #REF!
A988: entity:HQ_4.11_PRINT_COPY | B988: 4.11 | C988: PRINT_COPY | D988: {=TRANSPOSE(_xlfn._xlws.FILTER('Controllable Asset Registry'!#REF!,IFERROR('Controllable Asset Registry'!#REF!=A988,FALSE),"No Equipment in entity"))} -> #REF!
A989: entity:HQ_12.002_MCC_CLOSET | B989: 12.002 | C989: MCC_CLOSET | D989: {=TRANSPOSE(_xlfn._xlws.FILTER('Controllable Asset Registry'!#REF!,IFERROR('Controllable Asset Registry'!#REF!=A989,FALSE),"No Equipment in entity"))} -> #REF!
A990: entity:HQ_12.003_MCC_CLOSET | B990: 12.003 | C990: MCC_CLOSET | D990: {=TRANSPOSE(_xlfn._xlws.FILTER('Controllable Asset Registry'!#REF!,IFERROR('Controllable Asset Registry'!#REF!=A990,FALSE),"No Equipment in entity"))} -> #REF!
A991: entity:HQ_12.004_MCC_CLOSET | B991: 12.004 | C991: MCC_CLOSET | D991: {=TRANSPOSE(_xlfn._xlws.FILTER('Controllable Asset Registry'!#REF!,IFERROR('Controllable Asset Registry'!#REF!=A991,FALSE),"No Equipment in entity"))} -> #REF!
A992: entity:HQ_B1.004_STAFF_ENTRANCE | B992: B1.004 | C992: STAFF_ENTRANCE | D992: {=TRANSPOSE(_xlfn._xlws.FILTER('Controllable Asset Registry'!#REF!,IFERROR('Controllable Asset Registry'!#REF!=A992,FALSE),"No Equipment in entity"))} -> #REF!
A993: entity:HQ_G.400_CORRIDOR | B993: G.400 | C993: CORRIDOR | D993: {=TRANSPOSE(_xlfn._xlws.FILTER('Controllable Asset Registry'!#REF!,IFERROR('Controllable Asset Registry'!#REF!=A993,FALSE),"No Equipment in entity"))} -> #REF!
A994: entity:HQ_G.001_PR_&_MARKET_STAFF | B994: G.001 | C994: PR_&_MARKET_STAFF | D994: {=TRANSPOSE(_xlfn._xlws.FILTER('Controllable Asset Registry'!#REF!,IFERROR('Controllable Asset Registry'!#REF!=A994,FALSE),"No Equipment in entity"))} -> #REF!
A995: entity:HQ_G.030_STAFF | B995: G.030 | C995: STAFF | D995: {=TRANSPOSE(_xlfn._xlws.FILTER('Controllable Asset Registry'!#REF!,IFERROR('Controllable Asset Registry'!#REF!=A995,FALSE),"No Equipment in entity"))} -> #REF!
A996: entity:HQ_G.602_CORRIDOR_(SOUTH_EAST) | B996: G.602 | C996: CORRIDOR_(SOUTH_EAST) | D996: {=TRANSPOSE(_xlfn._xlws.FILTER('Controllable Asset Registry'!#REF!,IFERROR('Controllable Asset Registry'!#REF!=A996,FALSE),"No Equipment in entity"))} -> #REF!
A997: entity:HQ_G.603_CORRIDOR_(SOUTH_EAST) | B997: G.603 | C997: CORRIDOR_(SOUTH_EAST) | D997: {=TRANSPOSE(_xlfn._xlws.FILTER('Controllable Asset Registry'!#REF!,IFERROR('Controllable Asset Registry'!#REF!=A997,FALSE),"No Equipment in entity"))} -> #REF!
A998: entity:HQ_1.029_FINANCE_MANAGER | B998: 1.029 | C998: FINANCE_MANAGER | D998: {=TRANSPOSE(_xlfn._xlws.FILTER('Controllable Asset Registry'!#REF!,IFERROR('Controllable Asset Registry'!#REF!=A998,FALSE),"No Equipment in entity"))} -> #REF!
A999: entity:HQ_1.401_GROUND_FLOOR_VIP_ENTRANCE | B999: 1.401 | C999: GROUND_FLOOR_VIP_ENTRANCE | D999: {=TRANSPOSE(_xlfn._xlws.FILTER('Controllable Asset Registry'!#REF!,IFERROR('Controllable Asset Registry'!#REF!=A999,FALSE),"No Equipment in entity"))} -> #REF!
A1000: entity:HQ_2.110A_OFFICE_SPACE | B1000: 2.110A | C1000: OFFICE_SPACE | D1000: {=TRANSPOSE(_xlfn._xlws.FILTER('Controllable Asset Registry'!#REF!,IFERROR('Controllable Asset Registry'!#REF!=A1000,FALSE),"No Equipment in entity"))} -> #REF!
... A1006: entity:HQ_3.202B_OFFICE_SPACE | B1006: 3.202B | C1006: OFFICE_SPACE | D1006: {=TRANSPOSE(_xlfn._xlws.FILTER('Controllable Asset Registry'!#REF!,IFERROR('Controllable Asset Registry'!#REF!=A1006,FALSE),"No Equipment in entity"))} -> #REF!
A1007: entity:HQ_4.004_STR_PL_DIR_ENSUIT | B1007: 4.004 | C1007: STR_PL_DIR_ENSUIT | D1007: {=TRANSPOSE(_xlfn._xlws.FILTER('Controllable Asset Registry'!#REF!,IFERROR('Controllable Asset Registry'!#REF!=A1007,FALSE),"No Equipment in entity"))} -> #REF!
A1008: entity:HQ_4.015C_OFFICE_SPACE | B1008: 4.015C | C1008: OFFICE_SPACE | D1008: {=TRANSPOSE(_xlfn._xlws.FILTER('Controllable Asset Registry'!#REF!,IFERROR('Controllable Asset Registry'!#REF!=A1008,FALSE),"No Equipment in entity"))} -> #REF!
A1009: entity:HQ_4.015A_OFFICE_SPACE | B1009: 4.015A | C1009: OFFICE_SPACE | D1009: {=TRANSPOSE(_xlfn._xlws.FILTER('Controllable Asset Registry'!#REF!,IFERROR('Controllable Asset Registry'!#REF!=A1009,FALSE),"No Equipment in entity"))} -> #REF!
A1010: entity:HQ_4.003_STR_PL_DIR_EXEC_SECRE | B1010: 4.003 | C1010: STR_PL_DIR_EXEC_SECRE | D1010: {=TRANSPOSE(_xlfn._xlws.FILTER('Controllable Asset Registry'!#REF!,IFERROR('Controllable Asset Registry'!#REF!=A1010,FALSE),"No Equipment in entity"))} -> #REF!
A1011: entity:HQ_4.001B_OFFICE_SPACE | B1011: 4.001B | C1011: OFFICE_SPACE | D1011: {=TRANSPOSE(_xlfn._xlws.FILTER('Controllable Asset Registry'!#REF!,IFERROR('Controllable Asset Registry'!#REF!=A1011,FALSE),"No Equipment in entity"))} -> #REF!
A1012: entity:HQ_4.001D_OFFICE_SPACE | B1012: 4.001D | C1012: OFFICE_SPACE | D1012: {=TRANSPOSE(_xlfn._xlws.FILTER('Controllable Asset Registry'!#REF!,IFERROR('Controllable Asset Registry'!#REF!=A1012,FALSE),"No Equipment in entity"))} -> #REF!
A1013: entity:HQ_4.001F_OFFICE_SPACE | B1013: 4.001F | C1013: OFFICE_SPACE | D1013: {=TRANSPOSE(_xlfn._xlws.FILTER('Controllable Asset Registry'!#REF!,IFERROR('Controllable Asset Registry'!#REF!=A1013,FALSE),"No Equipment in entity"))} -> #REF!
A1014: entity:HQ_4.001G_OFFICE_SPACE | B1014: 4.001G | C1014: OFFICE_SPACE | D1014: {=TRANSPOSE(_xlfn._xlws.FILTER('Controllable Asset Registry'!#REF!,IFERROR('Controllable Asset Registry'!#REF!=A1014,FALSE),"No Equipment in entity"))} -> #REF!
A1015: entity:HQ_4.103_STORAGE_SPACE | B1015: 4.103 | C1015: STORAGE_SPACE | D1015: {=TRANSPOSE(_xlfn._xlws.FILTER('Controllable Asset Registry'!#REF!,IFERROR('Controllable Asset Registry'!#REF!=A1015,FALSE),"No Equipment in entity"))} -> #REF!
A1016: entity:HQ_5.110_VP_EDU_OFFICERS | B1016: 5.110 | C1016: VP_EDU_OFFICERS | D1016: {=TRANSPOSE(_xlfn._xlws.FILTER('Controllable Asset Registry'!#REF!,IFERROR('Controllable Asset Registry'!#REF!=A1016,FALSE),"No Equipment in entity"))} -> #REF!
A1017: entity:HQ_5.350_CORRIDOR | B1017: 5.350 | C1017: CORRIDOR | D1017: {=TRANSPOSE(_xlfn._xlws.FILTER('Controllable Asset Registry'!#REF!,IFERROR('Controllable Asset Registry'!#REF!=A1017,FALSE),"No Equipment in entity"))} -> #REF!
A1018: entity:HQ_7.031A_OFFICE_SPACE | B1018: 7.031A | C1018: OFFICE_SPACE | D1018: {=TRANSPOSE(_xlfn._xlws.FILTER('Controllable Asset Registry'!#REF!,IFERROR('Controllable Asset Registry'!#REF!=A1018,FALSE),"No Equipment in entity"))} -> #REF!
A1019: entity:HQ_7.301_MEETING_ROOM | B1019: 7.301 | C1019: MEETING_ROOM | D1019: {=TRANSPOSE(_xlfn._xlws.FILTER('Controllable Asset Registry'!#REF!,IFERROR('Controllable Asset Registry'!#REF!=A1019,FALSE),"No Equipment in entity"))} -> #REF!
A1020: entity:HQ_9.601_HH-WING_CORRIDOR | B1020: 9.601 | C1020: HH-WING_CORRIDOR | D1020: {=TRANSPOSE(_xlfn._xlws.FILTER('Controllable Asset Registry'!#REF!,IFERROR('Controllable Asset Registry'!#REF!=A1020,FALSE),"No Equipment in entity"))} -> #REF!
A1021: entity:HQ_10.002E_OFFICE_SPACE | B1021: 10.002E | C1021: OFFICE_SPACE | D1021: {=TRANSPOSE(_xlfn._xlws.FILTER('Controllable Asset Registry'!#REF!,IFERROR('Controllable Asset Registry'!#REF!=A1021,FALSE),"No Equipment in entity"))} -> #REF!
A1022: entity:HQ_10.002D_OFFICE_SPACE | B1022: 10.002D | C1022: OFFICE_SPACE | D1022: {=TRANSPOSE(_xlfn._xlws.FILTER('Controllable Asset Registry'!#REF!,IFERROR('Controllable Asset Registry'!#REF!=A1022,FALSE),"No Equipment in entity"))} -> #REF!
A1023: entity:HQ_10.002C_OFFICE_SPACE | B1023: 10.002C | C1023: OFFICE_SPACE | D1023: {=TRANSPOSE(_xlfn._xlws.FILTER('Controllable Asset Registry'!#REF!,IFERROR('Controllable Asset Registry'!#REF!=A1023,FALSE),"No Equipment in entity"))} -> #REF!
A1024: entity:HQ_10.002A_OFFICE_SPACE | B1024: 10.002A | C1024: OFFICE_SPACE | D1024: {=TRANSPOSE(_xlfn._xlws.FILTER('Controllable Asset Registry'!#REF!,IFERROR('Controllable Asset Registry'!#REF!=A1024,FALSE),"No Equipment in entity"))} -> #REF!
A1025: entity:HQ_11.103_SHEIKHA_WING_BUSINESS_LOUNGE | B1025: 11.103 | C1025: SHEIKHA_WING_BUSINESS_LOUNGE | D1025: {=TRANSPOSE(_xlfn._xlws.FILTER('Controllable Asset Registry'!#REF!,IFERROR('Controllable Asset Registry'!#REF!=A1025,FALSE),"No Equipment in entity"))} -> #REF!
A1026: entity:HQ_8.400_VISITORS_CENTER | B1026: 8.400 | C1026: VISITORS_CENTER | D1026: {=TRANSPOSE(_xlfn._xlws.FILTER('Controllable Asset Registry'!#REF!,IFERROR('Controllable Asset Registry'!#REF!=A1026,FALSE),"No Equipment in entity"))} -> #REF!
A1027: entity:HQ_B1.109_ROOM | B1027: B1.109 | C1027: ROOM | D1027: {=TRANSPOSE(_xlfn._xlws.FILTER('Controllable Asset Registry'!#REF!,IFERROR('Controllable Asset Registry'!#REF!=A1027,FALSE),"No Equipment in entity"))} -> #REF!
... A1041: entity:HQ_RF.002_ROOF_PLANT_WALKWAY | B1041: RF.002 | C1041: ROOF_PLANT_WALKWAY | D1041: {=TRANSPOSE(_xlfn._xlws.FILTER('Controllable Asset Registry'!#REF!,IFERROR('Controllable Asset Registry'!#REF!=A1041,FALSE),"No Equipment in entity"))} -> #REF!

Sheet QNL Room Names with Equip.
A1: Room Entity Name | B1: Room Number | C1: Room Name
A2: ="entity:QNL_"&B2&"_"&C2 -> entity:QNL_B_228_M1_HVAC_SHAFT | B2: B_228 | C2: M1_HVAC_SHAFT | D2: {=TRANSPOSE(_xlfn._xlws.FILTER('Controllable Asset Registry'!$A$4:$A$554,IFERROR('Controllable Asset Registry'!$E$4:$E$554=A2,FALSE),"No Equipment in entity"))} -> No Equipment in entity
A3: ="entity:QNL_"&B3&"_"&C3 -> entity:QNL_B_229_E1_ELEC_SHAFT | B3: B_229 | C3: E1_ELEC_SHAFT | D3: {=TRANSPOSE(_xlfn._xlws.FILTER('Controllable Asset Registry'!$A$4:$A$554,IFERROR('Controllable Asset Registry'!$E$4:$E$554=A3,FALSE),"No Equipment in entity"))} -> No Equipment in entity
A4: ="entity:QNL_"&B4&"_"&C4 -> entity:QNL_B_230_REFR_STORE | B4: B_230 | C4: REFR_STORE | D4: {=TRANSPOSE(_xlfn._xlws.FILTER('Controllable Asset Registry'!$A$4:$A$554,IFERROR('Controllable Asset Registry'!$E$4:$E$554=A4,FALSE),"No Equipment in entity"))} -> No Equipment in entity
A5: ="entity:QNL_"&B5&"_"&C5 -> entity:QNL_B_231_DISH_WASING | B5: B_231 | C5: DISH_WASING | D5: {=TRANSPOSE(_xlfn._xlws.FILTER('Controllable Asset Registry'!$A$4:$A$554,IFERROR('Controllable Asset Registry'!$E$4:$E$554=A5,FALSE),"No Equipment in entity"))} -> No Equipment in entity
A6: ="entity:QNL_"&B6&"_"&C6 -> entity:QNL_B_232_DRY_STORE | B6: B_232 | C6: DRY_STORE | D6: {=TRANSPOSE(_xlfn._xlws.FILTER('Controllable Asset Registry'!$A$4:$A$554,IFERROR('Controllable Asset Registry'!$E$4:$E$554=A6,FALSE),"No Equipment in entity"))} -> No Equipment in entity
A7: ="entity:QNL_"&B7&"_"&C7 -> entity:QNL_B_233_WC5_RISER | B7: B_233 | C7: WC5_RISER | D7: {=TRANSPOSE(_xlfn._xlws.FILTER('Controllable Asset Registry'!$A$4:$A$554,IFERROR('Controllable Asset Registry'!$E$4:$E$554=A7,FALSE),"No Equipment in entity"))} -> No Equipment in entity
A8: ="entity:QNL_"&B8&"_"&C8 -> entity:QNL_B_234_E3_ELEC_SHAFT | B8: B_234 | C8: E3_ELEC_SHAFT | D8: {=TRANSPOSE(_xlfn._xlws.FILTER('Controllable Asset Registry'!$A$4:$A$554,IFERROR('Controllable Asset Registry'!$E$4:$E$554=A8,FALSE),"No Equipment in entity"))} -> No Equipment in entity
A9: ="entity:QNL_"&B9&"_"&C9 -> entity:QNL_B_235_M2_HVAC_SHAFT_ABOVE | B9: B_235 | C9: M2_HVAC_SHAFT_ABOVE | D9: {=TRANSPOSE(_xlfn._xlws.FILTER('Controllable Asset Registry'!$A$4:$A$554,IFERROR('Controllable Asset Registry'!$E$4:$E$554=A9,FALSE),"No Equipment in entity"))} -> No Equipment in entity
A10: ="entity:QNL_"&B10&"_"&C10 -> entity:QNL_B_236_WC1_RISER | B10: B_236 | C10: WC1_RISER | D10: {=TRANSPOSE(_xlfn._xlws.FILTER('Controllable Asset Registry'!$A$4:$A$554,IFERROR('Controllable Asset Registry'!$E$4:$E$554=A10,FALSE),"No Equipment in entity"))} -> No Equipment in entity
A11: ="entity:QNL_"&B11&"_"&C11 -> entity:QNL_B_237_CORRIDOR | B11: B_237 | C11: CORRIDOR | D11: {=TRANSPOSE(_xlfn._xlws.FILTER('Controllable Asset Registry'!$A$4:$A$554,IFERROR('Controllable Asset Registry'!$E$4:$E$554=A11,FALSE),"No Equipment in entity"))} -> No Equipment in entity
A12: ="entity:QNL_"&B12&"_"&C12 -> entity:QNL_B_238_M3_HVAC_SHAFT | B12: B_238 | C12: M3_HVAC_SHAFT | D12: {=TRANSPOSE(_xlfn._xlws.FILTER('Controllable Asset Registry'!$A$4:$A$554,IFERROR('Controllable Asset Registry'!$E$4:$E$554=A12,FALSE),"No Equipment in entity"))} -> No Equipment in entity
A13: ="entity:QNL_"&B13&"_"&C13 -> entity:QNL_B_001_TECH_SERVICES_AND_COLLECTIONS_OFFICE | B13: B_001 | C13: TECH_SERVICES_AND_COLLECTIONS_OFFICE | D13: {=TRANSPOSE(_xlfn._xlws.FILTER('Controllable Asset Registry'!$A$4:$A$554,IFERROR('Controllable Asset Registry'!$E$4:$E$554=A13,FALSE),"No Equipment in entity"))} -> VAV_B_S11_003 | E13: VAV_B_S11_004 | F13: VAV_B_S11_005 | G13: VAV_B_S11_006 | H13: VAV_B_S11_007 | I13: VAV_B_S11_008 | J13: VAV_B_S11_009 | K13: VAV_B_S11_010 | L13: VAV_B_S11_013 | M13: VAV_B_S11_014 | N13: VAV_B_S11_015 | O13: VAV_B_S11_016 | P13: VAV_B_S11_017 | Q13: VAV_B_S11_018 | R13: VAV_B_S11_019 | S13: VAV_B_S11_020
A14: ="entity:QNL_"&B14&"_"&C14 -> entity:QNL_B_002_KITCHEN | B14: B_002 | C14: KITCHEN | D14: {=TRANSPOSE(_xlfn._xlws.FILTER('Controllable Asset Registry'!$A$4:$A$554,IFERROR('Controllable Asset Registry'!$E$4:$E$554=A14,FALSE),"No Equipment in entity"))} -> VAV_B_S11_024
A15: ="entity:QNL_"&B15&"_"&C15 -> entity:QNL_B_003_FINANCE_COORDINATOR_&_BUSINESS_SUPPORT_OFCR | B15: B_003 | C15: FINANCE_COORDINATOR_&_BUSINESS_SUPPORT_OFCR | D15: {=TRANSPOSE(_xlfn._xlws.FILTER('Controllable Asset Registry'!$A$4:$A$554,IFERROR('Controllable Asset Registry'!$E$4:$E$554=A15,FALSE),"No Equipment in entity"))} -> VAV_B_S11_026 | E15: VAV_B_S11_027
A16: ="entity:QNL_"&B16&"_"&C16 -> entity:QNL_B_004_ANALOG_RESOURCES | B16: B_004 | C16: ANALOG_RESOURCES | D16: {=TRANSPOSE(_xlfn._xlws.FILTER('Controllable Asset Registry'!$A$4:$A$554,IFERROR('Controllable Asset Registry'!$E$4:$E$554=A16,FALSE),"No Equipment in entity"))} -> VAV_B_S11_028
A17: ="entity:QNL_"&B17&"_"&C17 -> entity:QNL_B_005_DIGITAL_RESOURCES | B17: B_005 | C17: DIGITAL_RESOURCES | D17: {=TRANSPOSE(_xlfn._xlws.FILTER('Controllable Asset Registry'!$A$4:$A$554,IFERROR('Controllable Asset Registry'!$E$4:$E$554=A17,FALSE),"No Equipment in entity"))} -> VAV_B_S11_029
A18: ="entity:QNL_"&B18&"_"&C18 -> entity:QNL_B_006_BUDGET_&_PAYMENT_1 | B18: B_006 | C18: BUDGET_&_PAYMENT_1 | D18: {=TRANSPOSE(_xlfn._xlws.FILTER('Controllable Asset Registry'!$A$4:$A$554,IFERROR('Controllable Asset Registry'!$E$4:$E$554=A18,FALSE),"No Equipment in entity"))} -> VAV_B_S11_030
A19: ="entity:QNL_"&B19&"_"&C19 -> entity:QNL_B_007_BUDGET_&_PAYMENT_2 | B19: B_007 | C19: BUDGET_&_PAYMENT_2 | D19: {=TRANSPOSE(_xlfn._xlws.FILTER('Controllable Asset Registry'!$A$4:$A$554,IFERROR('Controllable Asset Registry'!$E$4:$E$554=A19,FALSE),"No Equipment in entity"))} -> VAV_B_S11_031
A20: ="entity:QNL_"&B20&"_"&C20 -> entity:QNL_B_008_RECEIVING_AREA | B20: B_008 | C20: RECEIVING_AREA | D20: {=TRANSPOSE(_xlfn._xlws.FILTER('Controllable Asset Registry'!$A$4:$A$554,IFERROR('Controllable Asset Registry'!$E$4:$E$554=A20,FALSE),"No Equipment in entity"))} -> VAV_B_S11_043 | E20: VAV_B_S11_044 | F20: VAV_B_S11_045 | G20: VAV_B_S11_046
A21: ="entity:QNL_"&B21&"_"&C21 -> entity:QNL_B_009_RECEPTION_&_LOUNGE | B21: B_009 | C21: RECEPTION_&_LOUNGE | D21: {=TRANSPOSE(_xlfn._xlws.FILTER('Controllable Asset Registry'!$A$4:$A$554,IFERROR('Controllable Asset Registry'!$E$4:$E$554=A21,FALSE),"No Equipment in entity"))} -> VAV_B_S11_021 | E21: VAV_B_S11_022 | F21: VAV_B_S11_023
A22: ="entity:QNL_"&B22&"_"&C22 -> entity:QNL_B_010_PATIO_GARDEN | B22: B_010 | C22: PATIO_GARDEN | D22: {=TRANSPOSE(_xlfn._xlws.FILTER('Controllable Asset Registry'!$A$4:$A$554,IFERROR('Controllable Asset Registry'!$E$4:$E$554=A22,FALSE),"No Equipment in entity"))} -> No Equipment in entity
A23: ="entity:QNL_"&B23&"_"&C23 -> entity:QNL_B_020_ENGINEERING | B23: B_020 | C23: ENGINEERING | D23: {=TRANSPOSE(_xlfn._xlws.FILTER('Controllable Asset Registry'!$A$4:$A$554,IFERROR('Controllable Asset Registry'!$E$4:$E$554=A23,FALSE),"No Equipment in entity"))} -> VAV_B_S11_034
A24: ="entity:QNL_"&B24&"_"&C24 -> entity:QNL_B_021_ARABIC_STUDIES | B24: B_021 | C24: ARABIC_STUDIES | D24: {=TRANSPOSE(_xlfn._xlws.FILTER('Controllable Asset Registry'!$A$4:$A$554,IFERROR('Controllable Asset Registry'!$E$4:$E$554=A24,FALSE),"No Equipment in entity"))} -> VAV_B_S11_035
A25: ="entity:QNL_"&B25&"_"&C25 -> entity:QNL_B_022_LICENSING_EXPERT | B25: B_022 | C25: LICENSING_EXPERT | D25: {=TRANSPOSE(_xlfn._xlws.FILTER('Controllable Asset Registry'!$A$4:$A$554,IFERROR('Controllable Asset Registry'!$E$4:$E$554=A25,FALSE),"No Equipment in entity"))} -> VAV_B_S11_036
A26: ="entity:QNL_"&B26&"_"&C26 -> entity:QNL_B_023_ARTS_&_HUMANITIES | B26: B_023 | C26: ARTS_&_HUMANITIES | D26: {=TRANSPOSE(_xlfn._xlws.FILTER('Controllable Asset Registry'!$A$4:$A$554,IFERROR('Controllable Asset Registry'!$E$4:$E$554=A26,FALSE),"No Equipment in entity"))} -> VAV_B_S11_037
A27: ="entity:QNL_"&B27&"_"&C27 -> entity:QNL_B_024_AD_COLLECTIONS | B27: B_024 | C27: AD_COLLECTIONS | D27: {=TRANSPOSE(_xlfn._xlws.FILTER('Controllable Asset Registry'!$A$4:$A$554,IFERROR('Controllable Asset Registry'!$E$4:$E$554=A27,FALSE),"No Equipment in entity"))} -> VAV_B_S11_032 | E27: VAV_B_S11_033
A28: ="entity:QNL_"&B28&"_"&C28 -> entity:QNL_B_025_SOCIAL_SCIENCES | B28: B_025 | C28: SOCIAL_SCIENCES | D28: {=TRANSPOSE(_xlfn._xlws.FILTER('Controllable Asset Registry'!$A$4:$A$554,IFERROR('Controllable Asset Registry'!$E$4:$E$554=A28,FALSE),"No Equipment in entity"))} -> VAV_B_S11_040
A29: ="entity:QNL_"&B29&"_"&C29 -> entity:QNL_B_026_BUSINESS_&_COMPUTING | B29: B_026 | C29: BUSINESS_&_COMPUTING | D29: {=TRANSPOSE(_xlfn._xlws.FILTER('Controllable Asset Registry'!$A$4:$A$554,IFERROR('Controllable Asset Registry'!$E$4:$E$554=A29,FALSE),"No Equipment in entity"))} -> VAV_B_S11_039
A30: ="entity:QNL_"&B30&"_"&C30 -> entity:QNL_B_027_PROCUREMENT_SPC_PROCUREMENT_OFCR | B30: B_027 | C30: PROCUREMENT_SPC_PROCUREMENT_OFCR | D30: {=TRANSPOSE(_xlfn._xlws.FILTER('Controllable Asset Registry'!$A$4:$A$554,IFERROR('Controllable Asset Registry'!$E$4:$E$554=A30,FALSE),"No Equipment in entity"))} -> VAV_B_S11_038
A31: ="entity:QNL_"&B31&"_"&C31 -> entity:QNL_B_028_STORAGE | B31: B_028 | C31: STORAGE | D31: {=TRANSPOSE(_xlfn._xlws.FILTER('Controllable Asset Registry'!$A$4:$A$554,IFERROR('Controllable Asset Registry'!$E$4:$E$554=A31,FALSE),"No Equipment in entity"))} -> VAV_B_S11_025
A32: ="entity:QNL_"&B32&"_"&C32 -> entity:QNL_B_029_LITERATURE_&_ANGUAGE | B32: B_029 | C32: LITERATURE_&_ANGUAGE | D32: {=TRANSPOSE(_xlfn._xlws.FILTER('Controllable Asset Registry'!$A$4:$A$554,IFERROR('Controllable Asset Registry'!$E$4:$E$554=A32,FALSE),"No Equipment in entity"))} -> VAV_B_S11_041
A33: ="entity:QNL_"&B33&"_"&C33 -> entity:QNL_B_030_SNR_P_COORDINATOR_&_P_COORDINATOR | B33: B_030 | C33: SNR_P_COORDINATOR_&_P_COORDINATOR | D33: {=TRANSPOSE(_xlfn._xlws.FILTER('Controllable Asset Registry'!$A$4:$A$554,IFERROR('Controllable Asset Registry'!$E$4:$E$554=A33,FALSE),"No Equipment in entity"))} -> VAV_B_S11_042
A34: ="entity:QNL_"&B34&"_"&C34 -> entity:QNL_B_031_JANITORS_ROOM | B34: B_031 | C34: JANITORS_ROOM | D34: {=TRANSPOSE(_xlfn._xlws.FILTER('Controllable Asset Registry'!$A$4:$A$554,IFERROR('Controllable Asset Registry'!$E$4:$E$554=A34,FALSE),"No Equipment in entity"))} -> No Equipment in entity
A35: ="entity:QNL_"&B35&"_"&C35 -> entity:QNL_B_032_REST_ROOM_MEN | B35: B_032 | C35: REST_ROOM_MEN | D35: {=TRANSPOSE(_xlfn._xlws.FILTER('Controllable Asset Registry'!$A$4:$A$554,IFERROR('Controllable Asset Registry'!$E$4:$E$554=A35,FALSE),"No Equipment in entity"))} -> No Equipment in entity
A36: ="entity:QNL_"&B36&"_"&C36 -> entity:QNL_B_034_MEETING_ROOM | B36: B_034 | C36: MEETING_ROOM | D36: {=TRANSPOSE(_xlfn._xlws.FILTER('Controllable Asset Registry'!$A$4:$A$554,IFERROR('Controllable Asset Registry'!$E$4:$E$554=A36,FALSE),"No Equipment in entity"))} -> VAV_B_S13_001 | E36: VAV_B_S13_002
A37: ="entity:QNL_"&B37&"_"&C37 -> entity:QNL_B036_REST_REST_ROOM_WOMEN | B37: B036_REST | C37: REST_ROOM_WOMEN | D37: {=TRANSPOSE(_xlfn._xlws.FILTER('Controllable Asset Registry'!$A$4:$A$554,IFERROR('Controllable Asset Registry'!$E$4:$E$554=A37,FALSE),"No Equipment in entity"))} -> No Equipment in entity
A38: ="entity:QNL_"&B38&"_"&C38 -> entity:QNL_B036_COR_CORRIDOR_4A | B38: B036_COR | C38: CORRIDOR_4A | D38: {=TRANSPOSE(_xlfn._xlws.FILTER('Controllable Asset Registry'!$A$4:$A$554,IFERROR('Controllable Asset Registry'!$E$4:$E$554=A38,FALSE),"No Equipment in entity"))} -> No Equipment in entity
A39: ="entity:QNL_"&B39&"_"&C39 -> entity:QNL_B_040_OFFICE | B39: B_040 | C39: OFFICE | D39: {=TRANSPOSE(_xlfn._xlws.FILTER('Controllable Asset Registry'!$A$4:$A$554,IFERROR('Controllable Asset Registry'!$E$4:$E$554=A39,FALSE),"No Equipment in entity"))} -> VAV_B_S14_001 | E39: CAV_B_S14_001
A40: ="entity:QNL_"&B40&"_"&C40 -> entity:QNL_B_041_DIGITIZATION_ROOM | B40: B_041 | C40: DIGITIZATION_ROOM | D40: {=TRANSPOSE(_xlfn._xlws.FILTER('Controllable Asset Registry'!$A$4:$A$554,IFERROR('Controllable Asset Registry'!$E$4:$E$554=A40,FALSE),"No Equipment in entity"))} -> VAV_B_S14_004 | E40: VAV_B_S14_005 | F40: VAV_B_S14_006 | G40: VAV_B_S14_008 | H40: VAV_B_S14_010 | I40: VAV_B_S14_011 | J40: VAV_B_S14_012 | K40: VAV_B_S14_015 | L40: VAV_B_S14_016
A41: ="entity:QNL_"&B41&"_"&C41 -> entity:QNL_B_042_RECEPTION_&_LOUNGE | B41: B_042 | C41: RECEPTION_&_LOUNGE | D41: {=TRANSPOSE(_xlfn._xlws.FILTER('Controllable Asset Registry'!$A$4:$A$554,IFERROR('Controllable Asset Registry'!$E$4:$E$554=A41,FALSE),"No Equipment in entity"))} -> No Equipment in entity
A42: ="entity:QNL_"&B42&"_"&C42 -> entity:QNL_B_043_BINDING_&_PRESERVATION_SPACE | B42: B_043 | C42: BINDING_&_PRESERVATION_SPACE | D42: {=TRANSPOSE(_xlfn._xlws.FILTER('Controllable Asset Registry'!$A$4:$A$554,IFERROR('Controllable Asset Registry'!$E$4:$E$554=A42,FALSE),"No Equipment in entity"))} -> VAV_B_S14_042 | E42: VAV_B_S14_043 | F42: VAV_B_S14_044 | G42: VAV_B_S14_045 | H42: VAV_B_S14_046 | I42: VAV_B_S14_048 | J42: VAV_B_S14_049 | K42: VAV_B_S14_050 | L42: VAV_B_S14_051
A43: ="entity:QNL_"&B43&"_"&C43 -> entity:QNL_B044_BOH_B_O_H_KITCHEN | B43: B044_BOH | C43: B_O_H_KITCHEN | D43: {=TRANSPOSE(_xlfn._xlws.FILTER('Controllable Asset Registry'!$A$4:$A$554,IFERROR('Controllable Asset Registry'!$E$4:$E$554=A43,FALSE),"No Equipment in entity"))} -> No Equipment in entity
A44: ="entity:QNL_"&B44&"_"&C44 -> entity:QNL_B044_FIN_FINE_BINDING | B44: B044_FIN | C44: FINE_BINDING | D44: {=TRANSPOSE(_xlfn._xlws.FILTER('Controllable Asset Registry'!$A$4:$A$554,IFERROR('Controllable Asset Registry'!$E$4:$E$554=A44,FALSE),"No Equipment in entity"))} -> No Equipment in entity
A45: ="entity:QNL_"&B45&"_"&C45 -> entity:QNL_B046_RES_REST_ROOM_MEN | B45: B046_RES | C45: REST_ROOM_MEN | D45: {=TRANSPOSE(_xlfn._xlws.FILTER('Controllable Asset Registry'!$A$4:$A$554,IFERROR('Controllable Asset Registry'!$E$4:$E$554=A45,FALSE),"No Equipment in entity"))} -> No Equipment in entity
A46: ="entity:QNL_"&B46&"_"&C46 -> entity:QNL_B046_ITT_ITTIGATION_CONTROL_ROOM | B46: B046_ITT | C46: ITTIGATION_CONTROL_ROOM | D46: {=TRANSPOSE(_xlfn._xlws.FILTER('Controllable Asset Registry'!$A$4:$A$554,IFERROR('Controllable Asset Registry'!$E$4:$E$554=A46,FALSE),"No Equipment in entity"))} -> DX_B11
A47: ="entity:QNL_"&B47&"_"&C47 -> entity:QNL_B_047_REST_ROOM_WOMEN | B47: B_047 | C47: REST_ROOM_WOMEN | D47: {=TRANSPOSE(_xlfn._xlws.FILTER('Controllable Asset Registry'!$A$4:$A$554,IFERROR('Controllable Asset Registry'!$E$4:$E$554=A47,FALSE),"No Equipment in entity"))} -> No Equipment in entity
A48: ="entity:QNL_"&B48&"_"&C48 -> entity:QNL_B_048_QTEL_ROOM | B48: B_048 | C48: QTEL_ROOM | D48: {=TRANSPOSE(_xlfn._xlws.FILTER('Controllable Asset Registry'!$A$4:$A$554,IFERROR('Controllable Asset Registry'!$E$4:$E$554=A48,FALSE),"No Equipment in entity"))} -> CCU_B01 | E48: CCU_B02
A49: ="entity:QNL_"&B49&"_"&C49 -> entity:QNL_B_049_MEP_KITCHEN | B49: B_049 | C49: MEP_KITCHEN | D49: {=TRANSPOSE(_xlfn._xlws.FILTER('Controllable Asset Registry'!$A$4:$A$554,IFERROR('Controllable Asset Registry'!$E$4:$E$554=A49,FALSE),"No Equipment in entity"))} -> KEF_B019
A50: ="entity:QNL_"&B50&"_"&C50 -> entity:QNL_B-04B_ST-04B | B50: B-04B | C50: ST-04B | D50: {=TRANSPOSE(_xlfn._xlws.FILTER('Controllable Asset Registry'!$A$4:$A$554,IFERROR('Controllable Asset Registry'!$E$4:$E$554=A50,FALSE),"No Equipment in entity"))} -> No Equipment in entity
A51: ="entity:QNL_"&B51&"_"&C51 -> entity:QNL_B_050_TELECOM_ROOM | B51: B_050 | C51: TELECOM_ROOM | D51: {=TRANSPOSE(_xlfn._xlws.FILTER('Controllable Asset Registry'!$A$4:$A$554,IFERROR('Controllable Asset Registry'!$E$4:$E$554=A51,FALSE),"No Equipment in entity"))} -> CCU_B03 | E51: CCU_B04
A52: ="entity:QNL_"&B52&"_"&C52 -> entity:QNL_B_051_STORAGE | B52: B_051 | C52: STORAGE | D52: {=TRANSPOSE(_xlfn._xlws.FILTER('Controllable Asset Registry'!$A$4:$A$554,IFERROR('Controllable Asset Registry'!$E$4:$E$554=A52,FALSE),"No Equipment in entity"))} -> No Equipment in entity
A53: ="entity:QNL_"&B53&"_"&C53 -> entity:QNL_B_053_CORRIDORS | B53: B_053 | C53: CORRIDORS | D53: {=TRANSPOSE(_xlfn._xlws.FILTER('Controllable Asset Registry'!$A$4:$A$554,IFERROR('Controllable Asset Registry'!$E$4:$E$554=A53,FALSE),"No Equipment in entity"))} -> No Equipment in entity
A54: ="entity:QNL_"&B54&"_"&C54 -> entity:QNL_B_054_PATIO_GARDEN | B54: B_054 | C54: PATIO_GARDEN | D54: {=TRANSPOSE(_xlfn._xlws.FILTER('Controllable Asset Registry'!$A$4:$A$554,IFERROR('Controllable Asset Registry'!$E$4:$E$554=A54,FALSE),"No Equipment in entity"))} -> No Equipment in entity
A55: ="entity:QNL_"&B55&"_"&C55 -> entity:QNL_B057_DIG_OFFICE_DIG_INIT | B55: B057_DIG | C55: OFFICE_DIG_INIT | D55: {=TRANSPOSE(_xlfn._xlws.FILTER('Controllable Asset Registry'!$A$4:$A$554,IFERROR('Controllable Asset Registry'!$E$4:$E$554=A55,FALSE),"No Equipment in entity"))} -> No Equipment in entity
A56: ="entity:QNL_"&B56&"_"&C56 -> entity:QNL_B057_AD_OFFICE_AD_FOR_LIT | B56: B057_AD | C56: OFFICE_AD_FOR_LIT | D56: {=TRANSPOSE(_xlfn._xlws.FILTER('Controllable Asset Registry'!$A$4:$A$554,IFERROR('Controllable Asset Registry'!$E$4:$E$554=A56,FALSE),"No Equipment in entity"))} -> No Equipment in entity
A57: ="entity:QNL_"&B57&"_"&C57 -> entity:QNL_B_058_SHELL_SPACE | B57: B_058 | C57: SHELL_SPACE | D57: {=TRANSPOSE(_xlfn._xlws.FILTER('Controllable Asset Registry'!$A$4:$A$554,IFERROR('Controllable Asset Registry'!$E$4:$E$554=A57,FALSE),"No Equipment in entity"))} -> VAV_B_S14_007 | E57: VAV_B_S14_013
A58: ="entity:QNL_"&B58&"_"&C58 -> entity:QNL_B_060_MAINTENANCE | B58: B_060 | C58: MAINTENANCE | D58: {=TRANSPOSE(_xlfn._xlws.FILTER('Controllable Asset Registry'!$A$4:$A$554,IFERROR('Controllable Asset Registry'!$E$4:$E$554=A58,FALSE),"No Equipment in entity"))} -> No Equipment in entity
A59: ="entity:QNL_"&B59&"_"&C59 -> entity:QNL_B_062_IDF_CORRIDOR | B59: B_062 | C59: IDF_CORRIDOR | D59: {=TRANSPOSE(_xlfn._xlws.FILTER('Controllable Asset Registry'!$A$4:$A$554,IFERROR('Controllable Asset Registry'!$E$4:$E$554=A59,FALSE),"No Equipment in entity"))} -> FCU_B_003
A60: ="entity:QNL_"&B60&"_"&C60 -> entity:QNL_B_063_PLANT_ROOM_01 | B60: B_063 | C60: PLANT_ROOM_01 | D60: {=TRANSPOSE(_xlfn._xlws.FILTER('Controllable Asset Registry'!$A$4:$A$554,IFERROR('Controllable Asset Registry'!$E$4:$E$554=A60,FALSE),"No Equipment in entity"))} -> AHUB002 | E60: AHUB011 | F60: AHUB012 | G60: FCU_B_011 | H60: FCU_B_012 | I60: CAV_B_S12_001 | J60: CAV_B_S12_002 | K60: CAV_B_S12_003 | L60: CAV_B_S15_001 | M60: CAV_B_S15_002 | N60: CAV_B_S15_003
A61: ="entity:QNL_"&B61&"_"&C61 -> entity:QNL_B_065_VENTLATON | B61: B_065 | C61: VENTLATON | D61: {=TRANSPOSE(_xlfn._xlws.FILTER('Controllable Asset Registry'!$A$4:$A$554,IFERROR('Controllable Asset Registry'!$E$4:$E$554=A61,FALSE),"No Equipment in entity"))} -> No Equipment in entity
A62: ="entity:QNL_"&B62&"_"&C62 -> entity:QNL_B_066_CORRIDOR | B62: B_066 | C62: CORRIDOR | D62: {=TRANSPOSE(_xlfn._xlws.FILTER('Controllable Asset Registry'!$A$4:$A$554,IFERROR('Controllable Asset Registry'!$E$4:$E$554=A62,FALSE),"No Equipment in entity"))} -> No Equipment in entity
A63: ="entity:QNL_"&B63&"_"&C63 -> entity:QNL_B_067_VENTLATON | B63: B_067 | C63: VENTLATON | D63: {=TRANSPOSE(_xlfn._xlws.FILTER('Controllable Asset Registry'!$A$4:$A$554,IFERROR('Controllable Asset Registry'!$E$4:$E$554=A63,FALSE),"No Equipment in entity"))} -> No Equipment in entity
A64: ="entity:QNL_"&B64&"_"&C64 -> entity:QNL_B_068_CORRIDOR | B64: B_068 | C64: CORRIDOR | D64: {=TRANSPOSE(_xlfn._xlws.FILTER('Controllable Asset Registry'!$A$4:$A$554,IFERROR('Controllable Asset Registry'!$E$4:$E$554=A64,FALSE),"No Equipment in entity"))} -> No Equipment in entity
A65: ="entity:QNL_"&B65&"_"&C65 -> entity:QNL_B_070_PLANT_ROOM_02 | B65: B_070 | C65: PLANT_ROOM_02 | D65: {=TRANSPOSE(_xlfn._xlws.FILTER('Controllable Asset Registry'!$A$4:$A$554,IFERROR('Controllable Asset Registry'!$E$4:$E$554=A65,FALSE),"No Equipment in entity"))} -> AHUB003 | E65: AHUB010 | F65: AHUB013 | G65: FCU_B_013 | H65: FCU_B_014 | I65: CAV_B_S13_010 | J65: CAV_B_S13_011 | K65: CAV_B_S13_012 | L65: EF_BBV01 | M65: EF_BBV02 | N65: TEF_B02A | O65: TEF_B02B
A66: ="entity:QNL_"&B66&"_"&C66 -> entity:QNL_B_071_FIRE_COMMAND_ROOM | B66: B_071 | C66: FIRE_COMMAND_ROOM | D66: {=TRANSPOSE(_xlfn._xlws.FILTER('Controllable Asset Registry'!$A$4:$A$554,IFERROR('Controllable Asset Registry'!$E$4:$E$554=A66,FALSE),"No Equipment in entity"))} -> FCU_B_006 | E66: EF_B14
A67: ="entity:QNL_"&B67&"_"&C67 -> entity:QNL_B_072_SPRIMKLERS_PUMPS_&_ZONES_VALVES | B67: B_072 | C67: SPRIMKLERS_PUMPS_&_ZONES_VALVES | D67: {=TRANSPOSE(_xlfn._xlws.FILTER('Controllable Asset Registry'!$A$4:$A$554,IFERROR('Controllable Asset Registry'!$E$4:$E$554=A67,FALSE),"No Equipment in entity"))} -> FCU_B_007 | E67: CAV_B_S13_021 | F67: EF_B13
A68: ="entity:QNL_"&B68&"_"&C68 -> entity:QNL_B_080_GENERATOR | B68: B_080 | C68: GENERATOR | D68: {=TRANSPOSE(_xlfn._xlws.FILTER('Controllable Asset Registry'!$A$4:$A$554,IFERROR('Controllable Asset Registry'!$E$4:$E$554=A68,FALSE),"No Equipment in entity"))} -> EF_B09 | E68: ELEC_Gen
A69: ="entity:QNL_"&B69&"_"&C69 -> entity:QNL_B_081_MV_ROOM | B69: B_081 | C69: MV_ROOM | D69: {=TRANSPOSE(_xlfn._xlws.FILTER('Controllable Asset Registry'!$A$4:$A$554,IFERROR('Controllable Asset Registry'!$E$4:$E$554=A69,FALSE),"No Equipment in entity"))} -> DX_B01 | E69: DX_B02
A70: ="entity:QNL_"&B70&"_"&C70 -> entity:QNL_B_082_TRANSFORMER_ROOM | B70: B_082 | C70: TRANSFORMER_ROOM | D70: {=TRANSPOSE(_xlfn._xlws.FILTER('Controllable Asset Registry'!$A$4:$A$554,IFERROR('Controllable Asset Registry'!$E$4:$E$554=A70,FALSE),"No Equipment in entity"))} -> DX_B03 | E70: DX_B04 | F70: DX_B14
A71: ="entity:QNL_"&B71&"_"&C71 -> entity:QNL_B_084_UPS_BATTERY_ROOM | B71: B_084 | C71: UPS_BATTERY_ROOM | D71: {=TRANSPOSE(_xlfn._xlws.FILTER('Controllable Asset Registry'!$A$4:$A$554,IFERROR('Controllable Asset Registry'!$E$4:$E$554=A71,FALSE),"No Equipment in entity"))} -> CAV_B_S13_020 | E71: DX_B08 | F71: DX_B09
A72: ="entity:QNL_"&B72&"_"&C72 -> entity:QNL_B_085_FUMIGATION_ROOM | B72: B_085 | C72: FUMIGATION_ROOM | D72: {=TRANSPOSE(_xlfn._xlws.FILTER('Controllable Asset Registry'!$A$4:$A$554,IFERROR('Controllable Asset Registry'!$E$4:$E$554=A72,FALSE),"No Equipment in entity"))} -> FCU_B_002 | E72: VAV_B_S13_006 | F72: EF_B05
A73: ="entity:QNL_"&B73&"_"&C73 -> entity:QNL_B_086_FREEZE_AREA | B73: B_086 | C73: FREEZE_AREA | D73: {=TRANSPOSE(_xlfn._xlws.FILTER('Controllable Asset Registry'!$A$4:$A$554,IFERROR('Controllable Asset Registry'!$E$4:$E$554=A73,FALSE),"No Equipment in entity"))} -> No Equipment in entity
A74: ="entity:QNL_"&B74&"_"&C74 -> entity:QNL_B_087_GAS_SUPPRESSION_ROOM | B74: B_087 | C74: GAS_SUPPRESSION_ROOM | D74: {=TRANSPOSE(_xlfn._xlws.FILTER('Controllable Asset Registry'!$A$4:$A$554,IFERROR('Controllable Asset Registry'!$E$4:$E$554=A74,FALSE),"No Equipment in entity"))} -> FCU_B_008 | E74: CAV_B_S13_013
A75: ="entity:QNL_"&B75&"_"&C75 -> entity:QNL_B_088_PEOPLE_MOVER_PLANT | B75: B_088 | C75: PEOPLE_MOVER_PLANT | D75: {=TRANSPOSE(_xlfn._xlws.FILTER('Controllable Asset Registry'!$A$4:$A$554,IFERROR('Controllable Asset Registry'!$E$4:$E$554=A75,FALSE),"No Equipment in entity"))} -> FCU_B_009
A76: ="entity:QNL_"&B76&"_"&C76 -> entity:QNL_B_089_SERVER_ROOM | B76: B_089 | C76: SERVER_ROOM | D76: {=TRANSPOSE(_xlfn._xlws.FILTER('Controllable Asset Registry'!$A$4:$A$554,IFERROR('Controllable Asset Registry'!$E$4:$E$554=A76,FALSE),"No Equipment in entity"))} -> CAV_B_S13_015 | E76: CCU_B05 | F76: CCU_B06 | G76: CCU_B07
A77: ="entity:QNL_"&B77&"_"&C77 -> entity:QNL_B_091_FUEL_ROOM | B77: B_091 | C77: FUEL_ROOM | D77: {=TRANSPOSE(_xlfn._xlws.FILTER('Controllable Asset Registry'!$A$4:$A$554,IFERROR('Controllable Asset Registry'!$E$4:$E$554=A77,FALSE),"No Equipment in entity"))} -> EF_B11
A78: ="entity:QNL_"&B78&"_"&C78 -> entity:QNL_B_092_STORAGE | B78: B_092 | C78: STORAGE | D78: {=TRANSPOSE(_xlfn._xlws.FILTER('Controllable Asset Registry'!$A$4:$A$554,IFERROR('Controllable Asset Registry'!$E$4:$E$554=A78,FALSE),"No Equipment in entity"))} -> DX_B20
A79: ="entity:QNL_"&B79&"_"&C79 -> entity:QNL_B_0924_FUEL_TANK_CHERRY_PICKER_PANKING | B79: B_0924 | C79: FUEL_TANK_CHERRY_PICKER_PANKING | D79: {=TRANSPOSE(_xlfn._xlws.FILTER('Controllable Asset Registry'!$A$4:$A$554,IFERROR('Controllable Asset Registry'!$E$4:$E$554=A79,FALSE),"No Equipment in entity"))} -> No Equipment in entity
A80: ="entity:QNL_"&B80&"_"&C80 -> entity:QNL_B_093_TRANSH_CHAMBER | B80: B_093 | C80: TRANSH_CHAMBER | D80: {=TRANSPOSE(_xlfn._xlws.FILTER('Controllable Asset Registry'!$A$4:$A$554,IFERROR('Controllable Asset Registry'!$E$4:$E$554=A80,FALSE),"No Equipment in entity"))} -> DX_B13 | E80: DX_B15 | F80: EF_B10
A81: ="entity:QNL_"&B81&"_"&C81 -> entity:QNL_B_095_EMERGENCY_LIGHTING_BATTERY_ROOM | B81: B_095 | C81: EMERGENCY_LIGHTING_BATTERY_ROOM | D81: {=TRANSPOSE(_xlfn._xlws.FILTER('Controllable Asset Registry'!$A$4:$A$554,IFERROR('Controllable Asset Registry'!$E$4:$E$554=A81,FALSE),"No Equipment in entity"))} -> DX_B07 | E81: DX_B16
A82: ="entity:QNL_"&B82&"_"&C82 -> entity:QNL_B_100_LOADING_DOCK | B82: B_100 | C82: LOADING_DOCK | D82: {=TRANSPOSE(_xlfn._xlws.FILTER('Controllable Asset Registry'!$A$4:$A$554,IFERROR('Controllable Asset Registry'!$E$4:$E$554=A82,FALSE),"No Equipment in entity"))} -> No Equipment in entity
A83: ="entity:QNL_"&B83&"_"&C83 -> entity:QNL_B_101_SHIPPING_CLERK | B83: B_101 | C83: SHIPPING_CLERK | D83: {=TRANSPOSE(_xlfn._xlws.FILTER('Controllable Asset Registry'!$A$4:$A$554,IFERROR('Controllable Asset Registry'!$E$4:$E$554=A83,FALSE),"No Equipment in entity"))} -> VAV_B_S13_007
A84: ="entity:QNL_"&B84&"_"&C84 -> entity:QNL_B_102_SECURITY_&_BMS | B84: B_102 | C84: SECURITY_&_BMS | D84: {=TRANSPOSE(_xlfn._xlws.FILTER('Controllable Asset Registry'!$A$4:$A$554,IFERROR('Controllable Asset Registry'!$E$4:$E$554=A84,FALSE),"No Equipment in entity"))} -> DX_B10
A85: ="entity:QNL_"&B85&"_"&C85 -> entity:QNL_B_103_PROCESSING_ROOM | B85: B_103 | C85: PROCESSING_ROOM | D85: {=TRANSPOSE(_xlfn._xlws.FILTER('Controllable Asset Registry'!$A$4:$A$554,IFERROR('Controllable Asset Registry'!$E$4:$E$554=A85,FALSE),"No Equipment in entity"))} -> VAV_B_S13_003 | E85: VAV_B_S13_004
A86: ="entity:QNL_"&B86&"_"&C86 -> entity:QNL_B_104_STORAGE | B86: B_104 | C86: STORAGE | D86: {=TRANSPOSE(_xlfn._xlws.FILTER('Controllable Asset Registry'!$A$4:$A$554,IFERROR('Controllable Asset Registry'!$E$4:$E$554=A86,FALSE),"No Equipment in entity"))} -> CAV_B_S13_009
A87: ="entity:QNL_"&B87&"_"&C87 -> entity:QNL_B106_RES_REST_ROOM_SECURITY | B87: B106_RES | C87: REST_ROOM_SECURITY | D87: {=TRANSPOSE(_xlfn._xlws.FILTER('Controllable Asset Registry'!$A$4:$A$554,IFERROR('Controllable Asset Registry'!$E$4:$E$554=A87,FALSE),"No Equipment in entity"))} -> DX_B22
A88: ="entity:QNL_"&B88&"_"&C88 -> entity:QNL_B106_SEC_SECURITY_STORES_SECURITY_UPS | B88: B106_SEC | C88: SECURITY_STORES_SECURITY_UPS | D88: {=TRANSPOSE(_xlfn._xlws.FILTER('Controllable Asset Registry'!$A$4:$A$554,IFERROR('Controllable Asset Registry'!$E$4:$E$554=A88,FALSE),"No Equipment in entity"))} -> No Equipment in entity
A89: ="entity:QNL_"&B89&"_"&C89 -> entity:QNL_B_107_SECURITY_EQUIPMENT_ROOM | B89: B_107 | C89: SECURITY_EQUIPMENT_ROOM | D89: {=TRANSPOSE(_xlfn._xlws.FILTER('Controllable Asset Registry'!$A$4:$A$554,IFERROR('Controllable Asset Registry'!$E$4:$E$554=A89,FALSE),"No Equipment in entity"))} -> DX_B12 | E89: DX_B23
A90: ="entity:QNL_"&B90&"_"&C90 -> entity:QNL_B_108_TOILET | B90: B_108 | C90: TOILET | D90: {=TRANSPOSE(_xlfn._xlws.FILTER('Controllable Asset Registry'!$A$4:$A$554,IFERROR('Controllable Asset Registry'!$E$4:$E$554=A90,FALSE),"No Equipment in entity"))} -> No Equipment in entity
A91: ="entity:QNL_"&B91&"_"&C91 -> entity:QNL_B_109_LOADING_AREA | B91: B_109 | C91: LOADING_AREA | D91: {=TRANSPOSE(_xlfn._xlws.FILTER('Controllable Asset Registry'!$A$4:$A$554,IFERROR('Controllable Asset Registry'!$E$4:$E$554=A91,FALSE),"No Equipment in entity"))} -> EF_B07 | E91: EF_B08 | F91: EF_B15 | G91: EF_B16
A92: ="entity:QNL_"&B92&"_"&C92 -> entity:QNL_B_110_PLANT_ROOM_03 | B92: B_110 | C92: PLANT_ROOM_03 | D92: {=TRANSPOSE(_xlfn._xlws.FILTER('Controllable Asset Registry'!$A$4:$A$554,IFERROR('Controllable Asset Registry'!$E$4:$E$554=A92,FALSE),"No Equipment in entity"))} -> AHUB004 | E92: AHUB009 | F92: AHUB014 | G92: AHUB015 | H92: FCU_B_015 | I92: FCU_B_016 | J92: FCU_B_017 | K92: CAV_B_S14_003 | L92: CAV_B_S14_004 | M92: CAV_B_S14_005 | N92: TEF_B01A | O92: TEF_B01B
A93: ="entity:QNL_"&B93&"_"&C93 -> entity:QNL_B_111_STORAGE | B93: B_111 | C93: STORAGE | D93: {=TRANSPOSE(_xlfn._xlws.FILTER('Controllable Asset Registry'!$A$4:$A$554,IFERROR('Controllable Asset Registry'!$E$4:$E$554=A93,FALSE),"No Equipment in entity"))} -> No Equipment in entity
A94: ="entity:QNL_"&B94&"_"&C94 -> entity:QNL_B_112_CORRIDOR | B94: B_112 | C94: CORRIDOR | D94: {=TRANSPOSE(_xlfn._xlws.FILTER('Controllable Asset Registry'!$A$4:$A$554,IFERROR('Controllable Asset Registry'!$E$4:$E$554=A94,FALSE),"No Equipment in entity"))} -> No Equipment in entity
A95: ="entity:QNL_"&B95&"_"&C95 -> entity:QNL_B_113_MAINTENANCE | B95: B_113 | C95: MAINTENANCE | D95: {=TRANSPOSE(_xlfn._xlws.FILTER('Controllable Asset Registry'!$A$4:$A$554,IFERROR('Controllable Asset Registry'!$E$4:$E$554=A95,FALSE),"No Equipment in entity"))} -> No Equipment in entity
A96: ="entity:QNL_"&B96&"_"&C96 -> entity:QNL_B_114_VENTLATON | B96: B_114 | C96: VENTLATON | D96: {=TRANSPOSE(_xlfn._xlws.FILTER('Controllable Asset Registry'!$A$4:$A$554,IFERROR('Controllable Asset Registry'!$E$4:$E$554=A96,FALSE),"No Equipment in entity"))} -> No Equipment in entity
A97: ="entity:QNL_"&B97&"_"&C97 -> entity:QNL_B_115_CORRIDOR | B97: B_115 | C97: CORRIDOR | D97: {=TRANSPOSE(_xlfn._xlws.FILTER('Controllable Asset Registry'!$A$4:$A$554,IFERROR('Controllable Asset Registry'!$E$4:$E$554=A97,FALSE),"No Equipment in entity"))} -> No Equipment in entity
A98: ="entity:QNL_"&B98&"_"&C98 -> entity:QNL_B_116_VENTLATON | B98: B_116 | C98: VENTLATON | D98: {=TRANSPOSE(_xlfn._xlws.FILTER('Controllable Asset Registry'!$A$4:$A$554,IFERROR('Controllable Asset Registry'!$E$4:$E$554=A98,FALSE),"No Equipment in entity"))} -> No Equipment in entity
A99: ="entity:QNL_"&B99&"_"&C99 -> entity:QNL_B_120_COMPACT_SHELVING_-MAIN_COLLECTION | B99: B_120 | C99: COMPACT_SHELVING_-MAIN_COLLECTION | D99: {=TRANSPOSE(_xlfn._xlws.FILTER('Controllable Asset Registry'!$A$4:$A$554,IFERROR('Controllable Asset Registry'!$E$4:$E$554=A99,FALSE),"No Equipment in entity"))} -> TEF_B03A | E99: TEF_B03B
A100: ="entity:QNL_"&B100&"_"&C100 -> entity:QNL_B_121_SORTING_SHELVING_ROOM | B100: B_121 | C100: SORTING_SHELVING_ROOM | D100: {=TRANSPOSE(_xlfn._xlws.FILTER('Controllable Asset Registry'!$A$4:$A$554,IFERROR('Controllable Asset Registry'!$E$4:$E$554=A100,FALSE),"No Equipment in entity"))} -> FCU_B_027 | E100: FCU_B_028
...
